Workbook

Sheet Summary
B2: Dự án An Bình
B3: Prepared by
B4: Vị trí: | D4: [Cập nhật vị trí dự án An Bình]
B5: Đơn vị tư vấn: | D5: Tiger capital
B6: Tọa độ:
B7: A | C7: Thông số quy hoạch
C9: STT | D9: Hạng mục đất | E9: Diện tích (m2) | F9: Tỷ lệ đất (%) | G9: Hệ số | H9: MĐXD (%) | I9: Tầng cao | J9: Tổng diện tích sàn xây dựng (m2) | K9: Tổng diện tích thương phẩm (m2) | L9: Số lượng sản phẩm | M9: Diện tích trung bình 1 sản phẩm (m2) | N9: Dân số
C10: I | D10: Đất khu vực lập quy hoạch | E10: =+E11+E19+E20+E21 -> 26556 | F10: =+E10/$E$23 -> 0.94081949
C11: 1 | D11: =+'1. thong tin quy hoach'!C10 -> Đất ở | E11: =+'1. thong tin quy hoach'!D10 -> 21178.41 | F11: =+E11/$E$23 -> 0.75030355 | G11: 10.21 | J11: =+J12+J17 -> 172561.1 | K11: =+K12+K17 -> 97820.305 | L11: =+L12+L17 -> 1521.3544 | N11: =+N12+N17 -> 2700
C12: 1.1 | D12: Khối cao tầng | E12: =+'1. thong tin quy hoach'!D12 -> 14605.8 | F12: =+E12/$E$23 -> 0.51745072 | G12: 10.21 | H12: 0.4 | I12: =+'1. thong tin quy hoach'!G12 -> 30 | J12: =+'1. thong tin quy hoach'!I12 -> 146585.35 | K12: =SUM(K13:K16) -> 91247.695 | L12: =SUM(L13:L16) -> 1448.3254 | N12: =+'1. thong tin quy hoach'!M12 -> 2407.884
D13: =+'1. thong tin quy hoach'!C13 -> Căn hộ khối tháp | J13: =+'1. thong tin quy hoach'!I13 -> 103768.6 | K13: =+'1. thong tin quy hoach'!K13 -> 81145.098 | L13: =+'1. thong tin quy hoach'!L13 -> 1275 | M13: =+'1. thong tin quy hoach'!N13 -> 63.643214
D14: =+'1. thong tin quy hoach'!C14 -> Căn shop TM khối đế | J14: =+'1. thong tin quy hoach'!I14 -> 2321.0467 | K14: =+'1. thong tin quy hoach'!K14 -> 2246.1743 | L14: =+'1. thong tin quy hoach'!L14 -> 18 | M14: =+'1. thong tin quy hoach'!N14 -> 124.78746
D15: OFT | J15: =+'1. thong tin quy hoach'!I15 -> 8219.248 | K15: =+'1. thong tin quy hoach'!K15 -> 6156.4232 | L15: =+'1. thong tin quy hoach'!L15 -> 154.32543 | M15: =+'1. thong tin quy hoach'!N15 -> 39.892473
D16: =+'1. thong tin quy hoach'!C16 -> Nhà trẻ | J16: =+'1. thong tin quy hoach'!I16 -> 2000 | K16: =+'1. thong tin quy hoach'!K16 -> 1700 | L16: =+'1. thong tin quy hoach'!L16 -> 1
C17: 1.2 | D17: Khối thấp tầng | E17: =+'1. thong tin quy hoach'!D37 -> 6572.61 | F17: =+E17/$E$23 -> 0.23285282 | G17: 0 | H17: =+'1. thong tin quy hoach'!F37 -> 0.75 | I17: =+'1. thong tin quy hoach'!G37 -> 3 | J17: =+'1. thong tin quy hoach'!I37 -> 25975.746 | K17: =SUM(K18:K18) -> 6572.61 | L17: =+SUM(L18:L18) -> 73.029 | M17: =+M18 -> 90 | N17: =+N18 -> 292.116
D18: ='1. thong tin quy hoach'!C38 -> Nhà ở liên kế khu A | E18: =+'1. thong tin quy hoach'!D38 -> 6572.61 | H18: =+'1. thong tin quy hoach'!F38 -> 0.75 | I18: =+'1. thong tin quy hoach'!G38 -> 3 | J18: =+'1. thong tin quy hoach'!I38 -> 25975.746 | K18: =+'1. thong tin quy hoach'!J38 -> 6572.61 | L18: =+'1. thong tin quy hoach'!L38 -> 73.029 | M18: =+'1. thong tin quy hoach'!N38 -> 90 | N18: =+'1. thong tin quy hoach'!M37 -> 292.116
C19: 2 | D19: Đất công trình công cộng | E19: =+'1. thong tin quy hoach'!D43 -> 0
C20: 3 | D20: Đất cây xanh nhóm ở thấp tầng | E20: =+'1. thong tin quy hoach'!D47 -> 0
C21: 4 | D21: Đất giao thông | E21: =+'1. thong tin quy hoach'!D48 -> 5377.59
C22: II | D22: Đất ngoài khu vực quy hoạch | E22: =+'1. thong tin quy hoach'!D53 -> 1670.456
C23: III | D23: Tổng diện tích đất | E23: =+E10+E22 -> 28226.456
B25: B. | C25: TỔNG MỨC ĐẦU TƯ
C27: Thời điểm triển khai xây dựng (dự kiến): | E27: Q1/2027
C29: STT | D29: Hạng mục | E29: Diện tích (m2) | F29: Đơn giá gồm VAT (trđ/m2) | G29: Giá trị (gồm VAT) (triệu đồng) | I29: Tỷ trọng (%) | L29: Hạng mục | N29: Tổng cộng | O29: 2026 | P29: 2027 | Q29: 2028 | R29: 2029 | S29: 2030 | T29: 2031
C30: I | D30: Các loại chi phí đất & pháp lý | E30: =+E23 -> 28226.456 | F30: =+G30/E30 -> 38.616497 | G30: =SUM(G31:H33) -> 1090006.8 | I30: =+G30/$G$45 -> 0.30237882 | L30: Chi phí đất | N30: =SUM(O30:T30) -> 0
D31: Chi phí nhận chuyển nhượng | E31: =+E30 -> 28226.456 | F31: =+G31/E31 -> 18.422433 | G31: =+'3.Du toan'!F12 -> 520000 | L31: Chi phí chuyển nhượng | N31: =SUM(O31:T31) -> 1 | O31: =SUMIF('2.Tien do'!$E$7:$AN$7,Summary!O$29,'2.Tien do'!$E10:$AN10) -> 1 | P31: =SUMIF('2.Tien do'!$E$7:$AN$7,Summary!P$29,'2.Tien do'!$E10:$AN10) -> 0 | Q31: =SUMIF('2.Tien do'!$E$7:$AN$7,Summary!Q$29,'2.Tien do'!$E10:$AN10) -> 0 | R31: =SUMIF('2.Tien do'!$E$7:$AN$7,Summary!R$29,'2.Tien do'!$E10:$AN10) -> 0 | S31: =SUMIF('2.Tien do'!$E$7:$AN$7,Summary!S$29,'2.Tien do'!$E10:$AN10) -> 0 | T31: =SUMIF('2.Tien do'!$E$7:$AN$7,Summary!T$29,'2.Tien do'!$E10:$AN10) -> 0
D32: Chí phí tiền sử dụng đất | E32: =+E11 -> 21178.41 | F32: =+G32/E32 -> 22.888307 | G32: =+'3.Du toan'!F13 -> 484737.94 | L32: Chi phí tiền sử dụng đất | N32: =SUM(O32:T32) -> 1 | O32: =SUMIF('2.Tien do'!$E$7:$AN$7,Summary!O$29,'2.Tien do'!$E11:$AN11) -> 0 | P32: =SUMIF('2.Tien do'!$E$7:$AN$7,Summary!P$29,'2.Tien do'!$E11:$AN11) -> 1 | Q32: =SUMIF('2.Tien do'!$E$7:$AN$7,Summary!Q$29,'2.Tien do'!$E11:$AN11) -> 0 | R32: =SUMIF('2.Tien do'!$E$7:$AN$7,Summary!R$29,'2.Tien do'!$E11:$AN11) -> 0 | S32: =SUMIF('2.Tien do'!$E$7:$AN$7,Summary!S$29,'2.Tien do'!$E11:$AN11) -> 0 | T32: =SUMIF('2.Tien do'!$E$7:$AN$7,Summary!T$29,'2.Tien do'!$E11:$AN11) -> 0
D33: Chi phí pháp lý | E33: =+E10 -> 26556 | F33: =+G33/E33 -> 3.2109092 | G33: =+'3.Du toan'!F15 -> 85268.906 | L33: Chi phí pháp lý | N33: =SUM(O33:T33) -> 1 | O33: =SUMIF('2.Tien do'!$E$7:$AN$7,Summary!O$29,'2.Tien do'!$E13:$AN13) -> 0.05 | P33: =SUMIF('2.Tien do'!$E$7:$AN$7,Summary!P$29,'2.Tien do'!$E13:$AN13) -> 0.2 | Q33: =SUMIF('2.Tien do'!$E$7:$AN$7,Summary!Q$29,'2.Tien do'!$E13:$AN13) -> 0.2 | R33: =SUMIF('2.Tien do'!$E$7:$AN$7,Summary!R$29,'2.Tien do'!$E13:$AN13) -> 0.1 | S33: =SUMIF('2.Tien do'!$E$7:$AN$7,Summary!S$29,'2.Tien do'!$E13:$AN13) -> 0.45 | T33: =SUMIF('2.Tien do'!$E$7:$AN$7,Summary!T$29,'2.Tien do'!$E13:$AN13) -> 0
C34: II | D34: Chi phí phát triển dự án | E34: =+J11 -> 172561.1 | F34: =+G34/E34 -> 13.942993 | G34: =SUM(G35:H36) -> 2406018.3 | I34: =+G34/$G$45 -> 0.66745359 | L34: Chi phí phát triển dự án | N34: =SUM(O34:T34) -> 0
D35: Chi phí xây dựng hạ tầng cảnh quan | E35: =+'3.Du toan'!D17 -> 28226.456 | F35: =+G35/E35 -> 0 | G35: =+'3.Du toan'!F17 -> 0 | L35: Hạ tầng kỹ thuật | N35: =SUM(O35:T35) -> 1 | O35: =SUMIF('2.Tien do'!$E$7:$AN$7,Summary!O$29,'2.Tien do'!$E16:$AN16) -> 0 | P35: =SUMIF('2.Tien do'!$E$7:$AN$7,Summary!P$29,'2.Tien do'!$E16:$AN16) -> 0 | Q35: =SUMIF('2.Tien do'!$E$7:$AN$7,Summary!Q$29,'2.Tien do'!$E16:$AN16) -> 1 | R35: =SUMIF('2.Tien do'!$E$7:$AN$7,Summary!R$29,'2.Tien do'!$E16:$AN16) -> 0 | S35: =SUMIF('2.Tien do'!$E$7:$AN$7,Summary!S$29,'2.Tien do'!$E16:$AN16) -> 0 | T35: =SUMIF('2.Tien do'!$E$7:$AN$7,Summary!T$29,'2.Tien do'!$E16:$AN16) -> 0
D36: Chi phí xây dựng công trình chính | E36: =+J11 -> 172561.1 | F36: =+G36/E36 -> 13.942993 | G36: =+H37+H43 -> 2406018.3 | L36: Xây dựng công trình chính
D37: Khối cao tầng | E37: =+J12 -> 146585.35 | F37: =+H37/E37 -> 15.0865 | H37: =+'3.Du toan'!F19 -> 2211460 | L37: Khối cao tầng | N37: =SUM(O37:T37) -> 1 | O37: =SUMIF('3.Du toan'!$AU$8:$CG$8,Summary!O$29,'3.Du toan'!$AU19:$CG19)/'3.Du toan'!$F$19 -> 0 | P37: =SUMIF('3.Du toan'!$AU$8:$CG$8,Summary!P$29,'3.Du toan'!$AU19:$CG19)/'3.Du toan'!$F$19 -> 0.022906514 | Q37: =SUMIF('3.Du toan'!$AU$8:$CG$8,Summary!Q$29,'3.Du toan'!$AU19:$CG19)/'3.Du toan'!$F$19 -> 0.31035501 | R37: =SUMIF('3.Du toan'!$AU$8:$CG$8,Summary!R$29,'3.Du toan'!$AU19:$CG19)/'3.Du toan'!$F$19 -> 0.54648858 | S37: =SUMIF('3.Du toan'!$AU$8:$CG$8,Summary!S$29,'3.Du toan'!$AU19:$CG19)/'3.Du toan'!$F$19 -> 0.12024989 | T37: =SUMIF('3.Du toan'!$AU$8:$CG$8,Summary!T$29,'3.Du toan'!$AU19:$CG19)/'3.Du toan'!$F$19 -> 0
D38: Chi phí xây dựng thiết bị | E38: =+J12 -> 146585.35 | F38: =+H38/E38 -> 13 | H38: =+'3.Du toan'!F20 -> 1905609.6 | L38: Khu nhà liên kế | N38: =SUM(O38:T38) -> 1 | O38: =IFERROR(SUMIF('3.Du toan'!$AU$8:$CG$8,Summary!O$29,'3.Du toan'!$AU61:$CG61)/'3.Du toan'!$F$61,0) -> 0 | P38: =IFERROR(SUMIF('3.Du toan'!$AU$8:$CG$8,Summary!P$29,'3.Du toan'!$AU61:$CG61)/'3.Du toan'!$F$61,0) -> 0 | Q38: =IFERROR(SUMIF('3.Du toan'!$AU$8:$CG$8,Summary!Q$29,'3.Du toan'!$AU61:$CG61)/'3.Du toan'!$F$61,0) -> 0.75 | R38: =IFERROR(SUMIF('3.Du toan'!$AU$8:$CG$8,Summary!R$29,'3.Du toan'!$AU61:$CG61)/'3.Du toan'!$F$61,0) -> 0.25 | S38: =IFERROR(SUMIF('3.Du toan'!$AU$8:$CG$8,Summary!S$29,'3.Du toan'!$AU61:$CG61)/'3.Du toan'!$F$61,0) -> 0 | T38: =IFERROR(SUMIF('3.Du toan'!$AU$8:$CG$8,Summary!T$29,'3.Du toan'!$AU61:$CG61)/'3.Du toan'!$F$61,0) -> 0
D39: Chi phí quản lý dự án | F39: =+G39/$E$34 -> 0.11043101 | G39: =+'3.Du toan'!F28 -> 19056.096 | I39: =+'3.Du toan'!E28 -> 0.01
D40: Chi phí tư vấn | F40: =+G40/$E$34 -> 0.44172403 | G40: =+'3.Du toan'!F29 -> 76224.384 | I40: =+'3.Du toan'!E29 -> 0.04
D41: Chi phí khác | F41: =+G41/$E$34 -> 0.055215503 | G41: =+'3.Du toan'!F30 -> 9528.0481 | I41: =+'3.Du toan'!E30 -> 0.005
D42: Chi phí dự phòng cao tầng | F42: =+G42/$E$34 -> 1.1650471 | G42: =+'3.Du toan'!F31 -> 201041.81 | I42: =+'3.Du toan'!E31 -> 0.1
D43: Khối thấp tầng | E43: =+J17 -> 25975.746 | F43: =IFERROR(H43/E43,0) -> 7.49 | H43: =+'3.Du toan'!F61 -> 194558.34
C44: III | D44: Lãi vay vốn hóa (cơ sở ls 12%) | G44: =+'3.Du toan'!F78 -> 108747.29 | I44: =+G44/$G$45 -> 0.030167589
D45: TỔNG CỘNG | G45: =+G30+G34+G44 -> 3604772.4 | I45: =+G45='3.Du toan'!F79 -> TRUE
B47: C. | C47: CƠ CẤU VỐN
C49: STT | D49: Cơ cấu sử dụng vốn | E49: Giá trị (triệu đồng) | G49: Tỷ lệ
C50: 1 | D50: Vốn chủ sở hữu | E50: =+'6.Vay von'!C17 -> 813975.15 | G50: =E50/$E$53 -> 0.16955614
C51: 2 | D51: Vốn vay trong thời gian xây dựng | E51: =+'6.Vay von'!C18 -> 655683.49 | G51: =E51/$E$53 -> 0.13658299
C52: 3 | D52: Huy động từ khách hàng | E52: =+'6.Vay von'!C19 -> 3330964.6 | G52: =E52/$E$53 -> 0.69386086
C53: TỔNG CỘNG | E53: =SUM(E50:E52) -> 4800623.2 | G53: =E53/$E$53 -> 1
B55: D. | C55: THÔNG TIN KINH DOANH
C57: Thông tin giá bán dự kiến | L57: Tiến độ kinh doanh
C59: STT | D59: Hạng mục thương phẩm | E59: Diện tích kinh doanh (m2) | F59: Đơn giá bán gồm VAT (tr.đt/m2) | G59: Doanh thu bán hàng gồm VAT (tr.đ) | I59: Số lượng sản phẩm | J59: Giá trung bình sản phẩm (tr.đ) | L59: Hạng mục | N59: Tổng cộng | O59: 2026 | P59: 2027 | Q59: 2028 | R59: 2029 | S59: 2030 | T59: 2031
C60: 1 | D60: =+'2.Tien do'!C65 -> Căn hộ khối tháp | E60: =+K13 -> 81145.098 | F60: =+'5.Doanh thu'!E13 -> 51.754461 | G60: =+E60*F60 -> 4199620.8 | I60: =L13 -> 1275 | J60: =+G60/I60 -> 3293.8202 | L60: =+'2.Tien do'!C65 -> Căn hộ khối tháp | N60: =+SUM(O60:T60) -> 1 | O60: =SUMIF('2.Tien do'!$E$7:$AN$7,Summary!O$59,'2.Tien do'!$E65:$AN65) -> 0 | P60: =SUMIF('2.Tien do'!$E$7:$AN$7,Summary!P$59,'2.Tien do'!$E65:$AN65) -> 0 | Q60: =SUMIF('2.Tien do'!$E$7:$AN$7,Summary!Q$59,'2.Tien do'!$E65:$AN65) -> 0.85286041 | R60: =SUMIF('2.Tien do'!$E$7:$AN$7,Summary!R$59,'2.Tien do'!$E65:$AN65) -> 0.14713959 | S60: =SUMIF('2.Tien do'!$E$7:$AN$7,Summary!S$59,'2.Tien do'!$E65:$AN65) -> 0 | T60: =SUMIF('2.Tien do'!$E$7:$AN$7,Summary!T$59,'2.Tien do'!$E65:$AN65) -> 0
C61: =+C60+1 -> 2 | D61: =+'2.Tien do'!C66 -> Căn hộ shop TM | E61: =+K14 -> 2246.1743 | F61: =+'5.Doanh thu'!E19 -> 54.504461 | H61: =+E61*F61 -> 122426.52 | I61: =L14 -> 18 | J61: =+H61/I61 -> 6801.4732 | L61: =+'2.Tien do'!C66 -> Căn hộ shop TM | N61: =+SUM(O61:T61) -> 1 | O61: =SUMIF('2.Tien do'!$E$7:$AN$7,Summary!O$59,'2.Tien do'!$E66:$AN66) -> 0 | P61: =SUMIF('2.Tien do'!$E$7:$AN$7,Summary!P$59,'2.Tien do'!$E66:$AN66) -> 0 | Q61: =SUMIF('2.Tien do'!$E$7:$AN$7,Summary!Q$59,'2.Tien do'!$E66:$AN66) -> 0 | R61: =SUMIF('2.Tien do'!$E$7:$AN$7,Summary!R$59,'2.Tien do'!$E66:$AN66) -> 1 | S61: =SUMIF('2.Tien do'!$E$7:$AN$7,Summary!S$59,'2.Tien do'!$E66:$AN66) -> 0 | T61: =SUMIF('2.Tien do'!$E$7:$AN$7,Summary!T$59,'2.Tien do'!$E66:$AN66) -> 0
C62: =+C61+1 -> 3 | D62: =+'2.Tien do'!C68 -> Căn officetel | E62: =+K15 -> 6156.4232 | F62: =+'5.Doanh thu'!E31 -> 49.141961 | H62: =+E62*F62 -> 302538.71 | I62: =L15 -> 154.32543 | J62: =+H62/I62 -> 1960.3944 | L62: =+'2.Tien do'!C68 -> Căn officetel | N62: =+SUM(O62:T62) -> 1 | O62: =SUMIF('2.Tien do'!$E$7:$AN$7,Summary!O$59,'2.Tien do'!$E68:$AN68) -> 0 | P62: =SUMIF('2.Tien do'!$E$7:$AN$7,Summary!P$59,'2.Tien do'!$E68:$AN68) -> 0 | Q62: =SUMIF('2.Tien do'!$E$7:$AN$7,Summary!Q$59,'2.Tien do'!$E68:$AN68) -> 0.85286041 | R62: =SUMIF('2.Tien do'!$E$7:$AN$7,Summary!R$59,'2.Tien do'!$E68:$AN68) -> 0.14713959 | S62: =SUMIF('2.Tien do'!$E$7:$AN$7,Summary!S$59,'2.Tien do'!$E68:$AN68) -> 0 | T62: =SUMIF('2.Tien do'!$E$7:$AN$7,Summary!T$59,'2.Tien do'!$E68:$AN68) -> 0
C63: =+C62+1 -> 4 | D63: =+'2.Tien do'!C71 -> Nhà phố liên kế | E63: =+K18 -> 6572.61 | F63: =+'5.Doanh thu'!E98 -> 87.504461 | H63: =+E63*F63 -> 575132.69 | I63: =+L18 -> 73.029 | J63: =IFERROR(H63/I63,0) -> 7875.4015 | L63: =+'2.Tien do'!C71 -> Nhà phố liên kế | N63: =+SUM(O63:T63) -> 1 | O63: =SUMIF('2.Tien do'!$E$7:$AN$7,Summary!O$59,'2.Tien do'!$E71:$AN71) -> 0 | P63: =SUMIF('2.Tien do'!$E$7:$AN$7,Summary!P$59,'2.Tien do'!$E71:$AN71) -> 0 | Q63: =SUMIF('2.Tien do'!$E$7:$AN$7,Summary!Q$59,'2.Tien do'!$E71:$AN71) -> 0.66666667 | R63: =SUMIF('2.Tien do'!$E$7:$AN$7,Summary!R$59,'2.Tien do'!$E71:$AN71) -> 0.33333333 | S63: =SUMIF('2.Tien do'!$E$7:$AN$7,Summary!S$59,'2.Tien do'!$E71:$AN71) -> 0 | T63: =SUMIF('2.Tien do'!$E$7:$AN$7,Summary!T$59,'2.Tien do'!$E71:$AN71) -> 0
C64: =+C61+1 -> 3 | D64: =+'2.Tien do'!C70 -> Nhà trẻ | E64: =+K16 -> 1700 | F64: =+'5.Doanh thu'!E112 -> 18.063863 | G64: =+E64*F64 -> 30708.567 | I64: =+L16 -> 1 | L64: =+'2.Tien do'!C70 -> Nhà trẻ | N64: =+SUM(O64:T64) -> 1 | O64: =SUMIF('2.Tien do'!$E$7:$AN$7,Summary!O$59,'2.Tien do'!$E70:$AN70) -> 0 | P64: =SUMIF('2.Tien do'!$E$7:$AN$7,Summary!P$59,'2.Tien do'!$E70:$AN70) -> 0 | Q64: =SUMIF('2.Tien do'!$E$7:$AN$7,Summary!Q$59,'2.Tien do'!$E70:$AN70) -> 0 | R64: =SUMIF('2.Tien do'!$E$7:$AN$7,Summary!R$59,'2.Tien do'!$E70:$AN70) -> 0 | S64: =SUMIF('2.Tien do'!$E$7:$AN$7,Summary!S$59,'2.Tien do'!$E70:$AN70) -> 1 | T64: =SUMIF('2.Tien do'!$E$7:$AN$7,Summary!T$59,'2.Tien do'!$E70:$AN70) -> 0
C65: TỔNG CỘNG | G65: =SUM(G60:H64) -> 5230427.3
H66: =+G65-'5.Doanh thu'!G116 -> 0
C67: Chi phí bán hàng 17,5% doanh thu bán
B68: E. | C68: P&L DỰ ÁN (không gồm VAT)
C70: STT | D70: NỘI DUNG | E70: Diện tích (m2) | F70: Đơn giá (trđ/m2) | G70: Đơn giá/m2 thương phẩm | H70: Tỷ trọng (%) | I70: TỔNG (trđ) | J70: GHI CHÚ
C71: I | D71: DOANH THU (ko VAT) | E71: =SUM(E72:E76) -> 97820.305 | G71: =I71/E71 -> 49.059354 | I71: =SUM(I72:I76) -> 4799001
D72: =+'4.Chi phi hoat dong'!C70 -> Căn hộ khối tháp | E72: ='5.Doanh thu'!E12 -> 81145.098 | G72: =+'8.ĐO NHAY'!C8 -> 47.5 | H72: =I72/$I$71 -> 0.80316553 | I72: =+E72*G72 -> 3854392.1
D73: =+'4.Chi phi hoat dong'!C71 -> Căn hộ shop TM | E73: =+'5.Doanh thu'!E18 -> 2246.1743 | G73: =+'8.ĐO NHAY'!C9 -> 50 | H73: =I73/$I$71 -> 0.023402519 | I73: =+E73*G73 -> 112308.71
D74: =+'4.Chi phi hoat dong'!C36 -> Căn officetel | E74: =+'5.Doanh thu'!E30 -> 6156.4232 | G74: =+'8.ĐO NHAY'!C11 -> 45.125 | H74: =I74/$I$71 -> 0.05788884 | I74: =+E74*G74 -> 277808.6
D75: =+'4.Chi phi hoat dong'!C39 -> Nhà phố liên kế | E75: =+'5.Doanh thu'!E97 -> 6572.61 | G75: =+'8.ĐO NHAY'!C12 -> 80 | H75: =I75/$I$71 -> 0.1095663 | I75: =+E75*G75 -> 525808.8
D76: =+'4.Chi phi hoat dong'!C75 -> Nhà trẻ | E76: =+K16 -> 1700 | G76: =+IFERROR(I76/E76,0) -> 16.872184 | H76: =I76/$I$71 -> 0.005976809 | I76: ='4.Chi phi hoat dong'!D75 -> 28682.712 | J76: =+"Giá cho thuê: "&ROUND(QĐGB!H3,0)&"$/m2/tháng" -> Giá cho thuê: 4$/m2/tháng
C77: II | D77: CHI PHÍ (ko VAT) | G77: =I77/$E$71 -> 44.558703 | I77: =I78+I93+I104 -> 4358745.9
C78: 1 | D78: Chi phí đầu tư | G78: =I78/$E$71 -> 34.614935 | I78: =SUM(I79,I83:I84,I92) -> 3386043.5
D79: Các loại chi phí đất | E79: ='1. thong tin quy hoach'!D9 -> 26556 | F79: =I79/E79 -> 41.045596 | G79: =I79/$E$71 -> 11.142951 | H79: =I79/$I$78 -> 0.32191165 | I79: =SUM(I80:I82) -> 1090006.8
D80: Chi phí mua đất | E80: =+E23 -> 28226.456 | F80: =I80/E80 -> 18.422433 | H80: =I80/$I$78 -> 0.15357157 | I80: ='3.Du toan'!F12 -> 520000
D81: Chi phí tiền sử dụng đất | E81: =+E11 -> 21178.41 | F81: =+I81/E81 -> 22.888307 | H81: =I81/$I$78 -> 0.14315762 | I81: ='3.Du toan'!F13 -> 484737.94
D82: Chi phí pháp lý | H82: =I82/$I$78 -> 0.02518246 | I82: ='3.Du toan'!F15 -> 85268.906
D83: Chi phí xây dựng hạ tầng - công viên | E83: ='1. thong tin quy hoach'!D9 -> 26556 | I83: =+'3.Du toan'!F17/1.1 -> 0
D84: Chi phí xây dựng công trình chính | E84: =+E85+E91 -> 172561.1 | F84: =I84/E84 -> 12.675449 | G84: =I84/$E$71 -> 22.360279 | H84: =I84/$I$78 -> 0.64597202 | I84: =+I85+I91 -> 2187289.4
D85: Khối cao tầng | E85: =+J12 -> 146585.35 | F85: =+I85/E85 -> 13.715 | G85: =I85/SUM($E$72:$E$74) -> 22.450808 | I85: =+'3.Du toan'!F19/1.1 -> 2010418.1
D86: Chi phí xây dựng - thiết bị | E86: =+E85 -> 146585.35 | F86: =IFERROR(I86/E86,0) -> 11.818182 | G86: =I86/$E$71 -> 17.709742 | H86: =+I86/$I$78 -> 0.51162142 | I86: =+'3.Du toan'!F20/1.1 -> 1732372.4
D87: Chi phí quản lý dự án | G87: =I87/$E$71 -> 0.17709742 | H87: =I87/$I$78 -> 0.0051162142 | I87: =('3.Du toan'!F28+'3.Du toan'!F42+'3.Du toan'!F56)/1.1 -> 17323.724
D88: Chi phí tư vấn & thiết kế | G88: =I88/$E$71 -> 0.70838968 | H88: =I88/$I$78 -> 0.020464857 | I88: =+('3.Du toan'!F29+'3.Du toan'!F43+'3.Du toan'!F57)/1.1 -> 69294.895
D89: Chi phí khác | G89: =I89/$E$71 -> 0.088548711 | H89: =I89/$I$78 -> 0.0025581071 | I89: =+('3.Du toan'!F30+'3.Du toan'!F44+'3.Du toan'!F58)/1.1 -> 8661.8619
D90: Chi phí dự phòng | G90: =I90/$E$71 -> 1.8683778 | H90: =I90/$I$78 -> 0.05397606 | I90: =('3.Du toan'!F31+'3.Du toan'!F45+'3.Du toan'!F59)/1.1 -> 182765.29
D91: Khối thấp tầng | E91: =+J17 -> 25975.746 | F91: =IFERROR(I91/E91,0) -> 6.8090909 | G91: =IFERROR(I91/E75,0) -> 26.910347 | I91: =+'3.Du toan'!F61/1.1 -> 176871.22
D92: Lãi vay vốn hóa | G92: =I92/$E$71 -> 1.1117047 | H92: =I92/$I$78 -> 0.032116331 | I92: ='3.Du toan'!F78 -> 108747.29 | J92: ="Lãi suất "&'6.Vay von'!C11*100&"%/năm" -> Lãi suất 12%/năm
C93: 2 | D93: Chi phí hoạt động | G93: =I93/$E$71 -> 8.9521536 | I93: =SUM(I94,I101:I103) -> 875702.39 | J93: =ROUND(I93/I71,3)*100& "% /Doanh thu" -> 18.2% /Doanh thu
D94: Chi phí bán hàng, MKT, DVKH | G94: =I94/$E$71 -> 8.4574642 | I94: =SUM(I95:I100) -> 827311.72 | J94: =ROUND('4.Chi phi hoat dong'!D10,3)*100 & "% /Doanh thu bán (không bao gồm cho thuê)" -> 17.5% /Doanh thu bán (không bao gồm cho thuê)
D95: Chi phí Môi giới | G95: =I95/$E$71 -> 3.3826432 | I95: =+'4.Chi phi hoat dong'!E11/1.1 -> 330891.19 | J95: =ROUND('4.Chi phi hoat dong'!D11,3)*100 & "% /Doanh thu" -> 7% /Doanh thu
D96: Chi phí marketing | G96: =I96/$E$71 -> 0.96646949 | I96: =+'4.Chi phi hoat dong'!E12/1.1 -> 94540.34 | J96: =ROUND('4.Chi phi hoat dong'!D12,3)*100 & "% /Doanh thu" -> 2% /Doanh thu
D97: Chính sách bán hàng | G97: =I97/$E$71 -> 3.2376728 | I97: =+'4.Chi phi hoat dong'!E13/1.1 -> 316710.14 | J97: =ROUND('4.Chi phi hoat dong'!D13,3)*100 & "% /Doanh thu (gồm hỗ trợ lãi suất)" -> 6.7% /Doanh thu (gồm hỗ trợ lãi suất)
D98: Chi phí nhà mẫu (gồm xd & vận hành) | G98: =I98/$E$71 -> 0.48323474 | I98: =+'4.Chi phi hoat dong'!E14/1.1 -> 47270.17 | J98: =ROUND('4.Chi phi hoat dong'!D14,3)*100 & "% /Doanh thu" -> 1% /Doanh thu
D99: Chi phí hậu mãi | G99: =I99/$E$71 -> 0.24161737 | I99: =+'4.Chi phi hoat dong'!E15/1.1 -> 23635.085 | J99: =ROUND('4.Chi phi hoat dong'!D15,3)*100 & "% /Doanh thu" -> 0.5% /Doanh thu
D100: Chi phí dự phòng bán hàng | G100: =I100/$E$71 -> 0.14582659 | I100: =+'4.Chi phi hoat dong'!E17/1.1 -> 14264.802 | J100: =ROUND('4.Chi phi hoat dong'!D17,3)*100 & "% /Doanh thu" -> 0.3% /Doanh thu
D101: Chi phí bảo lãnh ngân hàng | G101: =I101/$E$71 -> 0.48041996 | I101: ='4.Chi phi hoat dong'!E20 -> 46994.827
D102: Chi phí bảo trì TMDV + nhà trẻ | G102: =I102/$E$71 -> 0.01426947 | I102: ='4.Chi phi hoat dong'!E18/1.1 -> 1395.844
D103: Chi phí hoàn thuế VAT | I103: =+'4.Chi phi hoat dong'!D28 -> 0 | J103: Giả định sẽ không được hoàn VAT và xem đây là 1 khoản chi phí
D104: Tác động thuế TNDN do chênh lệch giá vốn | I104: =+'7.CF'!D34/0.8 -> 97000
B105: F. | C105: HIỆU QUẢ DỰ ÁN & DÒNG TIỀN
C107: STT | D107: Hạng mục | E107: Giá trị | F107: Ghi chú | K107: Hạng mục | N107: Tổng cộng | O107: 2026 | P107: 2027 | Q107: 2028 | R107: 2029 | S107: 2030 | T107: 2031
C108: 1 | D108: Lợi nhuận trước thuế (tr.đồng) điều chỉnh thiệt hại thuế | E108: =+I71-I77 -> 440255.06 | G108: =+E108-'7.CF'!D44 -> -1.9208528e-09 | K108: =+'7.CF'!C9 -> Dòng tiền từ hoạt động đầu tư - kinh doanh | N108: =SUM(O108:T108) -> 460951.34 | O108: =+SUM(O109:O110,O113:O115) -> -524263.45 | P108: =+SUM(P109:P110,P113:P115) -> -552448.56 | Q108: =+SUM(Q109:Q110,Q113:Q115) -> -253806.29 | R108: =+SUM(R109:R110,R113:R115) -> 899225.08 | S108: =+SUM(S109:S110,S113:S115) -> 892244.56 | T108: =+SUM(T109:T110,T113:T115) -> 0
C109: 2 | D109: Lợi nhuận sau thuế (tr.đồng) điều chỉnh thiệt hại thuế | E109: =E108*0.8 -> 352204.05 | K109: =+'7.CF'!C11 -> + Doanh thu | N109: =SUM(O109:T109) -> 5230427.3 | O109: =SUMIF('7.CF'!$F$7:$CH$7,Summary!O$107,'7.CF'!$F11:$CH11) -> 0 | P109: =SUMIF('7.CF'!$F$7:$CH$7,Summary!P$107,'7.CF'!$F11:$CH11) -> 0 | Q109: =SUMIF('7.CF'!$F$7:$CH$7,Summary!Q$107,'7.CF'!$F11:$CH11) -> 1343625 | R109: =SUMIF('7.CF'!$F$7:$CH$7,Summary!R$107,'7.CF'!$F11:$CH11) -> 2439961.3 | S109: =SUMIF('7.CF'!$F$7:$CH$7,Summary!S$107,'7.CF'!$F11:$CH11) -> 1446841 | T109: =SUMIF('7.CF'!$F$7:$CH$7,Summary!T$107,'7.CF'!$F11:$CH11) -> 0
C110: 3 | D110: NPV (suất chiết khấu 11%) (tr.đồng) | E110: ='7.CF'!D45 -> 10965.21 | K110: =+'7.CF'!C13 -> + Chi phí đầu tư & xây dựng (không gồm lãi vay) | N110: =SUM(O110:T110) -> -3496025.1 | O110: =-SUMIF('7.CF'!$F$7:$CH$7,Summary!O$107,'7.CF'!$F13:$CH13) -> -524263.45 | P110: =-SUMIF('7.CF'!$F$7:$CH$7,Summary!P$107,'7.CF'!$F13:$CH13) -> -552448.56 | Q110: =-SUMIF('7.CF'!$F$7:$CH$7,Summary!Q$107,'7.CF'!$F13:$CH13) -> -849310.22 | R110: =-SUMIF('7.CF'!$F$7:$CH$7,Summary!R$107,'7.CF'!$F13:$CH13) -> -1265704.1 | S110: =-SUMIF('7.CF'!$F$7:$CH$7,Summary!S$107,'7.CF'!$F13:$CH13) -> -304298.83 | T110: =-SUMIF('7.CF'!$F$7:$CH$7,Summary!T$107,'7.CF'!$F13:$CH13) -> 0
C111: 4 | D111: IRR (%) | E111: ='7.CF'!D46 -> 0.11468721 | I111: . | K111: =+'7.CF'!C14 -> - Giá chuyển nhượng đến hiện trạng | N111: =SUM(O111:T111) -> -520000 | O111: =-SUMIF('7.CF'!$F$7:$CH$7,Summary!O$107,'7.CF'!$F14:$CH14) -> -520000 | P111: =-SUMIF('7.CF'!$F$7:$CH$7,Summary!P$107,'7.CF'!$F14:$CH14) -> 0 | Q111: =-SUMIF('7.CF'!$F$7:$CH$7,Summary!Q$107,'7.CF'!$F14:$CH14) -> 0 | R111: =-SUMIF('7.CF'!$F$7:$CH$7,Summary!R$107,'7.CF'!$F14:$CH14) -> 0 | S111: =-SUMIF('7.CF'!$F$7:$CH$7,Summary!S$107,'7.CF'!$F14:$CH14) -> 0 | T111: =-SUMIF('7.CF'!$F$7:$CH$7,Summary!T$107,'7.CF'!$F14:$CH14) -> 0
C112: 5 | D112: LNTT/Tổng mức đầu tư (%) | E112: =+'7.CF'!D49 -> 0.12213117 | K112: =+'7.CF'!C15 -> - Chi phí xây dựng và pháp lý khác | N112: =SUM(O112:T112) -> -2976025.1 | O112: =-SUMIF('7.CF'!$F$7:$CH$7,Summary!O$107,'7.CF'!$F15:$CH15) -> -4263.4453 | P112: =-SUMIF('7.CF'!$F$7:$CH$7,Summary!P$107,'7.CF'!$F15:$CH15) -> -552448.56 | Q112: =-SUMIF('7.CF'!$F$7:$CH$7,Summary!Q$107,'7.CF'!$F15:$CH15) -> -849310.22 | R112: =-SUMIF('7.CF'!$F$7:$CH$7,Summary!R$107,'7.CF'!$F15:$CH15) -> -1265704.1 | S112: =-SUMIF('7.CF'!$F$7:$CH$7,Summary!S$107,'7.CF'!$F15:$CH15) -> -304298.83 | T112: =-SUMIF('7.CF'!$F$7:$CH$7,Summary!T$107,'7.CF'!$F15:$CH15) -> 0
...

Sheet 1. thong tin quy hoach
B2: =+Summary!B2 -> Dự án Trần Đức 1
B3: Prepared by:
B6: CHỈ TIÊU QUY HOẠCH
B8: STT | C8: Cơ cấu sử dụng đất | D8: Diện tích (m2) | E8: Tỷ lệ (%) | F8: MĐXD (%) | G8: Tầng cao | H8: Diện tích xây dựng (m2) | I8: CFA (m2) | J8: NFA (m2) | K8: NFA - tim tường (m2) | L8: Số sản phẩm | M8: Dân số (người) | N8: Diện tích sản phẩm (đất nền) (m2)
B9: A | C9: Đất khu vực lập quy hoạch (trong ranh) | D9: =D10+D43+D47+D48+D52 -> 26556 | E9: =+D9/D54 -> 0.94081949
B10: 1 | C10: Đất ở | D10: =+D12+D37+D21+D29 -> 21178.41 | E10: =+D10/$D$54 -> 0.75030355 | H10: =+H11+H37 -> 12232.358 | I10: =+I11+I37 -> 172561.1 | J10: =+J11+J37 -> 91551.966 | K10: =+K11+K37 -> 97820.305 | L10: =+L11+L37 -> 1521.3544 | M10: =+M11+M37 -> 2700
B11: 1.1 | C11: Đất chung cư | D11: =+D12+D21+D29 -> 14605.8 | E11: =+D11/$D$54 -> 0.51745072 | G11: =MAX(G12,G21,G29) -> 30 | H11: =+H12+H21+H29 -> 7302.9 | I11: =+I12+I21+I29 -> 146585.35 | J11: =+J12+J21+J29 -> 84979.356 | K11: =+K12+K21+K29 -> 91247.695 | L11: =+L12+L21+L29 -> 1448.3254 | M11: =+M12+M21+M29 -> 2407.884
B12: a | C12: Block A | D12: 15626 | E12: =+D12/$D$54 -> 0.51745072 | F12: 0.386 | G12: 40 | H12: =+D12*F12 -> 7302.9 | I12: =+SUM(I13:I20) -> 146585.35 | J12: =SUM(J13:J20) -> 84979.356 | K12: =SUM(K13:K20) -> 91247.695 | L12: =SUM(L13:L20) -> 1448.3254 | M12: =SUM(M13:M20) -> 2407.884
C13: Căn hộ khối tháp | H13: =+D61*D64 -> 0 | I13: 145652.1 | J13: 106326 | K13: =+J13/O13 -> 81145.098 | L13: 1855 | M13: 3938 | N13: =+K13/L13 -> 63.643214 | O13: 0.93
C14: Căn shop TM khối đế | I14: 13997.7 | J14: 7109.4 | K14: =+J14/O14 -> 2246.1743 | L14: 23 | N14: =+K14/L14 -> 124.78746 | O14: 0.93
C15: OFT | I15: 6282 | J15: 3190.6 | K15: =+J15/O15 -> 6156.4232 | L15: 86 | N15: =+K15/L15 -> 39.892473 | O15: 0.93
C16: Nhà trẻ | I16: 2362.8 | J16: 2008.4 | K16: =+J16 -> 1700 | L16: 1
C17: SHCĐ | I17: 1484
C18: Để xe (tầng nổi)
C19: Để xe + kỹ thuật (hầm) | I19: 31000
C20: Diện tích khác (tum, mái, sân thượng, hồ bơi...) | I20: 1181.4
B21: b | C21: Block B | D21: 0 | E21: =+D21/$D$54 -> 0 | F21: 0.4 | G21: 0 | H21: =+D21*F21 -> 0 | I21: =SUM(I22:I28) -> 0 | J21: =SUM(J22:J28) -> 0 | K21: =SUM(K22:K28) -> 0 | L21: =SUM(L22:L28) -> 0 | M21: =SUM(M22:M28) -> 0
C22: Căn hộ chung cư | H22: =+D66*D69 -> 0 | K22: =+J22/0.93 -> 0 | N22: =+J22/L22 -> #DIV/0!
C23: Căn shop TM | K23: =+J23/0.93 -> 0 | N23: =+J23/L23 -> #DIV/0!
C24: Nhà trẻ | K24: =+J24/0.93 -> 0
C25: SHCĐ
C26: Để xe (tầng nổi)
C27: Để xe + kỹ thuật (hầm)
C28: Diện tích khác (tum, mái, sân thượng, hồ bơi...)
B29: c | C29: Chung cư… | D29: 0 | E29: =+D29/D54 -> 0 | F29: 0.55 | G29: 0 | H29: =+F29*D29 -> 0 | I29: =SUM(I30:I36) -> 0 | J29: =SUM(J30:J36) -> 0 | K29: =SUM(K30:K36) -> 0 | L29: =SUM(L30:L36) -> 0 | M29: =SUM(M30:M36) -> 0
C30: Căn hộ chung cư | H30: =+D71*D74 -> 0 | K30: =+J30/0.93 -> 0 | N30: =+IFERROR(J30/L30,0) -> 0
C31: TMDV | K31: =+J31/0.93 -> 0 | N31: =+IFERROR(J31/L31,0) -> 0
C32: Nhà trẻ | K32: =+J32/0.93 -> 0
C33: SHCĐ
C34: Để xe (tầng nổi)
C35: Nhà xe
C36: Diện tích kỹ thuật khác
B37: 1.2 | C37: Đất nhà ở thấp tầng | D37: =+SUM(D38:D42) -> 6572.61 | E37: =+D37/D54 -> 0.23285282 | F37: =+F38 -> 0.75 | G37: =+G38 -> 3 | H37: =SUM(H38:H42) -> 4929.4575 | I37: =+SUM(I38:I42) -> 25975.746 | J37: =+SUM(J38:J42) -> 6572.61 | K37: =+J37 -> 6572.61 | L37: =+SUM(L38:L42) -> 73.029 | M37: =+SUM(M38:M42) -> 292.116
C38: Nhà ở liên kế khu A | D38: 0 | F38: 0 | G38: 0 | H38: =+D38*F38 -> 4929.4575 | I38: 0 | J38: =+D38 -> 6572.61 | L38: 0 | M38: 0 | N38: =+IFERROR(J38/L38,0) -> 90
C39: Nhà ở liên kế khu B
C40: Shophouse khu C (đường D9)
C41: Biệt thự
B43: 2 | C43: Công trình dịch vụ công cộng | D43: =+SUM(D44:D46) -> 0 | E43: =+D43/$D$54 -> 0 | F43: =+F44 -> 0.4 | H43: =+SUM(H44:H46) -> 0 | I43: =+SUM(I44:I46) -> 0
B44: 2.1 | C44: Trường liên cấp | D44: 0 | F44: 0.4 | G44: 0 | H44: =+D44*F44 -> 0 | I44: =+H44*G44 -> 0
B45: 2.2 | C45: Đất văn hóa | F45: 0.4 | G45: 0 | H45: =+D45*F45 -> 0 | I45: =+H45*G45 -> 0
B46: 2.3 | C46: Đất y tế | F46: 0.4 | G46: 0 | H46: =+D46*F46 -> 0 | I46: =+H46*G46 -> 0
B47: 3 | C47: Đất cây xanh nhóm ở thấp tầng | D47: 0 | E47: =+D47/$D$54 -> 0
B48: 4 | C48: Đất giao thông nhóm ở | D48: =SUM(D49:D51) -> 5377.59 | E48: =+D48/$D$54 -> 0.19051595
C49: Đất giao thông | D49: 0
C50: Bãi đậu xe P1
C51: Bãi đậu xe P2, P3, P4
B52: 5 | C52: Đất hạ tầng kỹ thuật | E52: =+D52/$D$54 -> 0
B53: B | C53: Đất ngoài cơ cấu | D53: 4993 | E53: =+D53/$D$54 -> 0.059180508
C54: Tổng cộng (A+ B) | D54: =+D53+D9 -> 28226.456
B58: STT | C58: HẠNG MỤC | D58: GIÁ TRỊ | E58: GHI CHÚ
B59: 1 | C59: Tổng diện tích đất toàn khu | D59: =D60 -> 14605.8
C60: - Đất nhóm nhà Ở | D60: =D117-D116 -> 14605.8
C61: + Đất ở lâu dài | D61: =+D11 -> 14605.8
C62: + Đất TMDV | D62: =D59-D61 -> 0
B63: 2 | C63: Mật độ xây dựng (%)
C64: - Khối đế | D64: =+F13 -> 0
C65: - Khối tháp | D65: =+D64 -> 0
B66: 3 | C66: Tầng cao
C67: - Chung cư phức hợp
C68: + Tầng nổi | D68: =(D83+D84+D85+D91)/(D65*D59)+(D86+D87+D88+D89+D90)/(D64*D59) -> #DIV/0!
C69: + Tầng hầm | D69: =D94/(1*D60) -> 0.89953791
B70: 4 | C70: Hệ số sử dụng đất | D70: =+SUM(D71:D72) -> 6 | F70: =D70*D59 -> 87634.8
C71: - Căn hộ sở hữu lâu dài | D71: 8.8568
C72: - TMDV | D72: 1.3564
B74: 5 | C74: Hiệu quả thiết kế
C75: - Diện tích thương phẩm/diện tích GBA (NSA/GBA) | D75: =$D$97/D79 -> 0.64556706
C76: - Diện tích thương phẩm/diện tích CFA (NSA/CFA) | D76: =$D$97/D80 -> 0.68604636
C77: - Diện tích thương phẩm/diện tích GFA (NSA/GFA) | D77: =$D$97/D81 -> 0.78890047
B78: 6 | C78: Tổng diện tích sàn xây dựng
C79: Diện tích sàn Bê Tông (GBA) | D79: =D80+D92+D93 -> 107092.11 | F79: ='3.Du toan'!$F$20/'1. thong tin quy hoach'!D79 -> 17.794119
C80: Diện tích sàn xây dựng (CFA) | D80: =D81+D91+D94 -> 100773.27 | F80: ='3.Du toan'!$F$20/'1. thong tin quy hoach'!D80 -> 18.909872
C81: Diện tích sàn nổi (GFA) | D81: =D70*D59+D90 -> 87634.8
C82: Diện tích sàn tính hệ số | D82: =SUM(D83:D89) -> 87634.8 | E82: =D82-D59*D70 -> 0 | G82: Check
C83: - Căn hộ sở hữu lâu dài | D83: =+D71*D61*G85 -> 77874.526
C84: - Căn hộ dịch vụ | D84: 0 | F84: Hệ số ở | I84: Tỷ lệ diện tích cấu phần hệ số TMDV
C85: - Officetel | D85: 0 | F85: Căn hộ | G85: 0.98736177 | I85: Officetel | L85: 0
B86: =D86/(D83+D86) -> 0.10115053 | C86: - Căn shop TM | D86: =+$D$61*$D$72*L86 -> 8763.48 | F86: SHCĐ | G86: =+D89/($D$61*$D$71) -> 0.012638231 | I86: Căn shop | L86: 1
C87: - TMDV | D87: =+$D$61*$D$72*L87 -> 0 | F87: Nhà trẻ | G87: 0 | I87: TMDV tập trung | L87: 0
C88: - Nhà Trẻ | D88: 0 | G88: =SUM(G85:G87) -> 1 | L88: =SUM(L85:L87) -> 1
C89: - SHCD | D89: =+D105*0.8 -> 996.79393 | E89: =E99/60 -> 0
C90: - Để xe nổi | D90: =+D112-D95-D114*0.3 -> 9.094947e-13
C91: - Tầng tum+hệ thống kỹ thuật+PCCC | D91: =+D61*D64*0.3 -> 0
C92: - Diện tích khác (gồm để xe ngoài trời) | D92: =+D117*0.4+D114*0.3 -> 6318.8342
C93: - Tầng lánh nạn | D93: 0
C94: Hầm | D94: =+D95/0.95 -> 13138.471
C95: - Để xe hầm | D95: =D113*100%+D114*0.7 -> 12481.547 | E95: 5290
C96: - Kỹ thuật Hầm | D96: =+D94-D95 -> 656.92354
B97: 7 | C97: Tổng diện tích kinh doanh | D97: =SUM(D98:D103) -> 69135.135 | F97: DT tim tường | G97: DT thông thủy
C98: - Căn hộ sở hữu lâu dài | D98: =+D83*F98 -> 62299.621 | F98: 0.8 | G98: 0.73
C99: - Căn hộ dịch vụ | D99: 0
C100: - Officetel | D100: 0 | F100: =+D100/D85 -> #DIV/0! | G100: 0.74471247
C101: - Căn shop | D101: =+D86*F101 -> 6835.5144 | F101: 0.78 | G101: 0.725
C102: - TMDV (thuê lẻ) | D102: =+D87*F102 -> 0 | E102: =+D102/$D$97 -> 0 | F102: 0.78 | G102: 0.725
C103: - Nhà trẻ | D103: 0 | E103: =+D103/$D$97 -> 0 | F103: 0.94033906
B104: 8 | C104: Số lượng sản phẩm | D104: =SUM(D105:D107) -> 1303.955 | F104: DT 1 sản phẩm
C105: - Căn hộ Bán | D105: =D98/F105 -> 1245.9924 | F105: 50
C106: -TMDV | D106: 1 | F106: 0
C107: - Căn Shop | D107: =D101/F107 -> 56.96262 | F107: 120
B108: 9 | C108: Dân số được duyệt 1/2000 | D108: =+D109 -> 1894.9468
C109: Dân số theo yêu cầu | D109: =+(D98/F98*G98)/30 -> 1894.9468
...

Sheet 2.Tien do
B2: =+Summary!B2 -> Dự án Trần Đức 1
B3: Prepared by:
B5: TIMELINE DỰ ÁN
B7: HẠNG MỤC | D7: CBĐT | E7: 2026 | F7: 2026 | G7: 2026 | H7: 2026 | I7: =H7+1 -> 2027 | J7: =I7 -> 2027 | K7: =J7 -> 2027 | L7: =K7 -> 2027 | M7: =L7+1 -> 2028 | N7: =M7 -> 2028 | O7: =N7 -> 2028 | P7: =L7+1 -> 2028 | Q7: =M7+1 -> 2029 | R7: =N7+1 -> 2029 | S7: =O7+1 -> 2029 | T7: =P7+1 -> 2029 | U7: =Q7+1 -> 2030 | V7: =R7+1 -> 2030 | W7: =S7+1 -> 2030 | ... AN7: =AJ7+1 -> 2034 | AO7: =AN7+1 -> 2035 | AP7: =AO7+1 -> 2036 | AQ7: =AP7+1 -> 2037 | AR7: =AQ7+1 -> 2038
E8: Q1 | F8: Q2 | G8: Q3 | H8: Q4 | I8: Q1 | J8: Q2 | K8: Q3 | L8: Q4 | M8: Q1 | N8: Q2 | O8: Q3 | P8: Q4 | Q8: Q1 | R8: Q2 | S8: Q3 | T8: Q4 | U8: Q1 | V8: Q2 | W8: Q3 | X8: Q4 | Y8: Q1 | Z8: Q2 | AA8: Q3 | AB8: Q4 | AC8: Q1 | AD8: Q2 | AE8: Q3 | AF8: Q4 | AG8: Q1 | AH8: Q2 | AI8: Q3 | AJ8: Q4 | AK8: Q1 | AL8: Q2 | AM8: Q3 | AN8: Q4
B9: GIAI ĐOẠN ĐẦU TƯ & PHÁP LÝ | F9: M&A | G9: Hoàn thành M&A | H9: Chấp thuận CTĐT | I9: QH 1/500 | J9: Đóng LUR | K9: GPXD | N9: Ký HĐMB | O9: Bán thấp tầng | T9: Bàn giao thấp tầng | U9: Bàn giao chung cư | X9: Cấp sổ
C10: Tiến độ giải ngân M&A | F10: 0.3 | G10: 0.7
C11: Chi phí nghĩa vụ tài chính | J11: 1 | M11: 0 | AC11: 0 | AF11: 0 | AG11: 0 | AH11: 0 | AI11: 0 | AJ11: 0 | AK11: 0 | AL11: 0 | AM11: 0 | AN11: 0 | AO11: 0
C12: - | AC12: 0 | AF12: 0 | AG12: 0 | AH12: 0 | AI12: 0 | AJ12: 0 | AK12: 0 | AL12: 0 | AM12: 0 | AN12: 0 | AO12: 0
C13: Pháp lý | H13: 0.05 | I13: 0.05 | J13: 0.05 | K13: 0.1 | N13: 0.2 | Q13: 0.05 | T13: 0.05 | U13: 0.25 | X13: 0.2 | AF13: 0 | AG13: 0 | AH13: 0 | AI13: 0 | AJ13: 0 | AK13: 0 | AL13: 0 | AM13: 0 | AN13: 0 | AO13: 0
B15: HẠNG MỤC XÂY DỰNG
B16: 1 | C16: Hạ tầng kỹ thuật | N16: 0.4 | O16: 0.3 | P16: 0.3 | R16: 0
B17: 2 | C17: Xây dựng công trình chính
B18: 2.1 | C18: Xây dựng Chung cư Sky Habitat
C19: Chuẩn bị thi công | K19: 0.75 | L19: 0.25 | R19: =Q19 -> 0 | V19: =U19 -> 0 | AA19: =Z19 -> 0
C20: Phần ngầm | K20: 0 | L20: 0.05355623 | M20: 0.7 | N20: =1-M20-L20 -> 0.24644377
C21: Phần thân | K21: 0 | L21: 0 | M21: 0 | N21: =100%/8 -> 0.125 | O21: =100%/8 -> 0.125 | P21: =100%/8 -> 0.125 | Q21: =100%/8 -> 0.125 | R21: =100%/8 -> 0.125 | S21: =100%/8 -> 0.125 | T21: =100%/8 -> 0.125 | U21: =100%/8 -> 0.125
C22: Hoàn thiện | K22: 0 | L22: 0 | M22: 0 | N22: 0 | R22: 0.3 | S22: 0.3 | T22: 0.2 | U22: 0.2
C23: M&E | K23: 0 | L23: 0 | M23: 0 | N23: =100%/8 -> 0.125 | O23: =100%/8 -> 0.125 | P23: =100%/8 -> 0.125 | Q23: =100%/8 -> 0.125 | R23: =100%/8 -> 0.125 | S23: =100%/8 -> 0.125 | T23: =100%/8 -> 0.125 | U23: =100%/8 -> 0.125
C24: Xây dựng cảnh quan | K24: 0 | L24: 0 | M24: 0 | N24: 0 | R24: 0.3 | S24: 0.3 | T24: 0.2 | U24: 0.2
C25: Thiết bị | K25: 0 | L25: 0 | M25: 0 | Q25: 0.1 | R25: 0.2 | S25: 0.3 | T25: 0.3 | U25: 0.1
C26: Chi phí quản lý dự án | K26: 0 | L26: =100%/10 -> 0.1 | M26: =100%/10 -> 0.1 | N26: =100%/10 -> 0.1 | O26: =100%/10 -> 0.1 | P26: =100%/10 -> 0.1 | Q26: =100%/10 -> 0.1 | R26: =100%/10 -> 0.1 | S26: =100%/10 -> 0.1 | ... U26: =100%/10 -> 0.1
C27: Chi phí tư vấn đầu tư xây dựng | K27: 0 | L27: =100%/10 -> 0.1 | M27: =100%/10 -> 0.1 | N27: =100%/10 -> 0.1 | O27: =100%/10 -> 0.1 | P27: =100%/10 -> 0.1 | Q27: =100%/10 -> 0.1 | R27: =100%/10 -> 0.1 | S27: =100%/10 -> 0.1 | ... U27: =100%/10 -> 0.1
C28: Chi phí khác | K28: 0 | L28: =100%/10 -> 0.1 | M28: =100%/10 -> 0.1 | N28: =100%/10 -> 0.1 | O28: =100%/10 -> 0.1 | P28: =100%/10 -> 0.1 | Q28: =100%/10 -> 0.1 | R28: =100%/10 -> 0.1 | S28: =100%/10 -> 0.1 | ... U28: =100%/10 -> 0.1
C29: Chi phí dự phòng | K29: 0 | L29: =100%/10 -> 0.1 | M29: =100%/10 -> 0.1 | N29: =100%/10 -> 0.1 | O29: =100%/10 -> 0.1 | P29: =100%/10 -> 0.1 | Q29: =100%/10 -> 0.1 | R29: =100%/10 -> 0.1 | S29: =100%/10 -> 0.1 | ... U29: =100%/10 -> 0.1
B30: 2.2 | C30: Xây dựng Chung cư ….
C31: Chuẩn bị thi công | AA31: =Z31 -> 0
C32: Phần ngầm | G32: 0
C33: Phần thân | G33: 0
C34: Hoàn thiện | G34: 0
C35: M&E | G35: 0
C36: Xây dựng cảnh quan | G36: 0
C37: Thiết bị | G37: 0
C38: Chi phí quản lý dự án | G38: 0
C39: Chi phí tư vấn đầu tư xây dựng | G39: 0
C40: Chi phí khác | G40: 0
C41: Chi phí dự phòng | G41: 0
B42: 2.3 | C42: Xây dựng Chung cư …
C43: Chuẩn bị thi công | AA43: =Z43 -> 0
C44: Phần ngầm | G44: 0 | N44: 0 | O44: 0 | P44: 0 | Q44: 0 | R44: 0 | S44: 0 | T44: 0 | U44: 0 | V44: 0 | W44: 0
C45: Phần thân | G45: 0 | N45: 0 | O45: 0 | P45: 0 | Q45: 0 | R45: 0 | S45: 0 | T45: 0 | U45: 0 | V45: 0 | W45: 0
C46: Hoàn thiện | G46: 0 | N46: 0 | O46: 0 | P46: 0 | Q46: 0 | R46: 0 | S46: 0 | T46: 0 | U46: 0 | V46: 0 | W46: 0
C47: M&E | G47: 0 | N47: 0 | O47: 0 | P47: 0 | Q47: 0 | R47: 0 | S47: 0 | T47: 0 | U47: 0 | V47: 0 | W47: 0
C48: Xây dựng cảnh quan | G48: 0 | N48: 0 | O48: 0 | P48: 0 | Q48: 0 | R48: 0 | S48: 0 | T48: 0 | U48: 0 | V48: 0 | W48: 0
C49: Thiết bị | G49: 0 | N49: 0 | O49: 0 | P49: 0 | Q49: 0 | R49: 0 | S49: 0 | T49: 0 | U49: 0 | V49: 0 | W49: 0
C50: Chi phí quản lý dự án | G50: 0 | N50: 0 | O50: 0 | P50: 0 | Q50: 0 | R50: 0 | S50: 0 | T50: 0 | U50: 0 | V50: 0 | W50: 0
C51: Chi phí tư vấn đầu tư xây dựng | G51: 0 | N51: 0 | O51: 0 | P51: 0 | Q51: 0 | R51: 0 | S51: 0 | T51: 0 | U51: 0 | V51: 0 | W51: 0
C52: Chi phí khác | G52: 0 | N52: 0 | O52: 0 | P52: 0 | Q52: 0 | R52: 0 | S52: 0 | T52: 0 | U52: 0 | V52: 0 | W52: 0
C53: Chi phí dự phòng | G53: 0 | N53: 0 | O53: 0 | P53: 0 | Q53: 0 | R53: 0 | S53: 0 | T53: 0 | U53: 0 | V53: 0 | W53: 0
B54: 2.2 | C54: Xây dựng khu thấp tầng
C55: Nhà phố liên kế | N55: 0.25 | O55: 0.25 | P55: 0.25 | Q55: 0.25
B59: 3 | C59: Xây dựng công trình công cộng
C60: Trường liên cấp
C61: Đất y tế
C62: Đất văn hóa
B64: TIẾN ĐỘ BÁN HÀNG
C65: Căn hộ khối tháp | N65: 0.37528604 | O65: =0.377574370709382*100% -> 0.37757437 | P65: 0.1 | Q65: 0.05 | R65: 0.05 | S65: =100%-SUM(N65:R65) -> 0.047139588
C66: Căn hộ shop TM | Q66: 0.5 | R66: 0.3 | S66: 0.2
C67: Căn TMDV
C68: Căn officetel | N68: 0.37528604 | O68: =0.377574370709382*100% -> 0.37757437 | P68: 0.1 | Q68: 0.05 | R68: 0.05 | S68: =100%-SUM(N68:R68) -> 0.047139588
C69: TMDV tập trung
C70: Nhà trẻ | U70: 1
C71: Nhà phố liên kế | O71: =100%/3 -> 0.33333333 | P71: =100%/3 -> 0.33333333 | Q71: =100%/3 -> 0.33333333
V78: 0
M85: =L85+M84 -> 0

Sheet 3.Du toan
B2: =+Summary!B2 -> Dự án Trần Đức 1
B3: Prepared by:
B5: DỰ TOÁN ĐẦU TƯ
B7: STT | C7: HẠNG MỤC | D7: SUẤT ĐẦU TƯ | F7: TỔNG (tr.đ) | G7: TIẾN ĐỘ TRIỂN KHAI ĐẦU TƯ XÂY DỰNG | AT7: DÒNG TIỀN CHI TRẢ DỰ TOÁN CHI PHÍ ĐẦU TƯ PHÁT TRIỂN DỰ ÁN
D8: DIỆN TÍCH (m²) | E8: ĐƠN GIÁ (vnd/m²) | G8: CBĐT | H8: ='2.Tien do'!E7 -> 2026 | I8: ='2.Tien do'!F7 -> 2026 | J8: ='2.Tien do'!G7 -> 2026 | K8: ='2.Tien do'!H7 -> 2026 | L8: ='2.Tien do'!I7 -> 2027 | M8: ='2.Tien do'!J7 -> 2027 | N8: ='2.Tien do'!K7 -> 2027 | O8: ='2.Tien do'!L7 -> 2027 | ... AR8: ='2.Tien do'!AO7 -> 2035 | AT8: CBĐT | AU8: ='2.Tien do'!E7 -> 2026 | AV8: ='2.Tien do'!F7 -> 2026 | AW8: ='2.Tien do'!G7 -> 2026 | AX8: ='2.Tien do'!H7 -> 2026 | AY8: ='2.Tien do'!I7 -> 2027 | AZ8: ='2.Tien do'!J7 -> 2027 | BA8: ='2.Tien do'!K7 -> 2027 | BB8: ='2.Tien do'!L7 -> 2027 | ... CG8: ='2.Tien do'!AQ7 -> 2037
H9: ='2.Tien do'!E8 -> Q1 | I9: ='2.Tien do'!F8 -> Q2 | J9: ='2.Tien do'!G8 -> Q3 | K9: ='2.Tien do'!H8 -> Q4 | L9: ='2.Tien do'!I8 -> Q1 | M9: ='2.Tien do'!J8 -> Q2 | N9: ='2.Tien do'!K8 -> Q3 | O9: ='2.Tien do'!L8 -> Q4 | ... AR9: ='2.Tien do'!AO8 -> 0 | AU9: ='2.Tien do'!E8 -> Q1 | AV9: ='2.Tien do'!F8 -> Q2 | AW9: ='2.Tien do'!G8 -> Q3 | AX9: ='2.Tien do'!H8 -> Q4 | AY9: ='2.Tien do'!I8 -> Q1 | AZ9: ='2.Tien do'!J8 -> Q2 | BA9: ='2.Tien do'!K8 -> Q3 | BB9: ='2.Tien do'!L8 -> Q4 | ... CG9: ='2.Tien do'!AQ8 -> 0
B10: CHUẨN BỊ ĐẦU TƯ | D10: ='1. thong tin quy hoach'!$D$59 -> 14605.8 | E10: =F10*10^6/D10 -> 74628356 | F10: =F11+F15 -> 1090006.8 | AT10: =AT11+AT15 -> 0 | AU10: =AU11+AU15 -> 0 | AV10: =AV11+AV15 -> 156000 | AW10: =AW11+AW15 -> 364000 | AX10: =AX11+AX15 -> 4263.4453 | AY10: =AY11+AY15 -> 4263.4453 | AZ10: =AZ11+AZ15 -> 489001.39 | BA10: =BA11+BA15 -> 8526.8906 | ... CE10: =CE11+CE15 -> 0 | CH10: =F10-SUM(AT10:CG10) -> 0
B11: 1 | C11: Chi phí liên quan đến đất | D11: =+'1. thong tin quy hoach'!D54 -> 28226.456 | E11: =F11/D11*10^6 -> 35595611 | F11: =F13+F12+F14 -> 1004737.9 | AT11: =SUM(AT12:AT14) -> 0 | AU11: =SUM(AU12:AU14) -> 0 | AV11: =SUM(AV12:AV14) -> 156000 | AW11: =SUM(AW12:AW14) -> 364000 | AX11: =SUM(AX12:AX14) -> 0 | AY11: =SUM(AY12:AY14) -> 0 | AZ11: =SUM(AZ12:AZ14) -> 484737.94 | BA11: =SUM(BA12:BA14) -> 0 | ... CE11: =SUM(CE12:CE14) -> 0 | CH11: =F11-SUM(AT11:CG11) -> 0
C12: Chi phi mua đất/đấu giá | F12: =+'8.ĐO NHAY'!C20 -> 520000 | H12: ='2.Tien do'!E10 -> 0 | I12: ='2.Tien do'!F10 -> 0.3 | J12: ='2.Tien do'!G10 -> 0.7 | K12: ='2.Tien do'!H10 -> 0 | L12: ='2.Tien do'!I10 -> 0 | M12: ='2.Tien do'!J10 -> 0 | N12: ='2.Tien do'!K10 -> 0 | O12: ='2.Tien do'!L10 -> 0 | ... AR12: ='2.Tien do'!AO10 -> 0 | AT12: =$F12*G12 -> 0 | AU12: =$F12*H12 -> 0 | AV12: =$F12*I12 -> 156000 | AW12: =$F12*J12 -> 364000 | AX12: =$F12*K12 -> 0 | AY12: =$F12*L12 -> 0 | AZ12: =$F12*M12 -> 0 | BA12: =$F12*N12 -> 0 | ... CE12: =$F12*AR12 -> 0 | CH12: =F12-SUM(AT12:CG12) -> 0
C13: Chi phí nghĩa vụ tài chính | F13: =+TSDĐ!G389/10^6 -> 484737.94 | G13: ='2.Tien do'!D11 -> 0 | H13: ='2.Tien do'!E11 -> 0 | I13: ='2.Tien do'!F11 -> 0 | J13: ='2.Tien do'!G11 -> 0 | K13: ='2.Tien do'!H11 -> 0 | L13: ='2.Tien do'!I11 -> 0 | M13: ='2.Tien do'!J11 -> 1 | N13: ='2.Tien do'!K11 -> 0 | ... AR13: ='2.Tien do'!AO11 -> 0 | AT13: =$F13*G13 -> 0 | AU13: =$F13*H13 -> 0 | AV13: =$F13*I13 -> 0 | AW13: =$F13*J13 -> 0 | AX13: =$F13*K13 -> 0 | AY13: =$F13*L13 -> 0 | AZ13: =$F13*M13 -> 484737.94 | BA13: =$F13*N13 -> 0 | ... CE13: =$F13*AR13 -> 0 | CH13: =F13-SUM(AT13:CG13) -> 0
C14: … | F14: 0 | AB14: ='2.Tien do'!Y12 -> 0 | AC14: ='2.Tien do'!Z12 -> 0 | AD14: ='2.Tien do'!AA12 -> 0 | AE14: ='2.Tien do'!AB12 -> 0 | AF14: ='2.Tien do'!AC12 -> 0 | AG14: ='2.Tien do'!AD12 -> 0 | AH14: ='2.Tien do'!AE12 -> 0 | AI14: ='2.Tien do'!AF12 -> 0 | ... AR14: ='2.Tien do'!AO12 -> 0 | AT14: =$F14*G14 -> 0 | AU14: =$F14*H14 -> 0 | AV14: =$F14*I14 -> 0 | AW14: =$F14*J14 -> 0 | AX14: =$F14*K14 -> 0 | AY14: =$F14*L14 -> 0 | AZ14: =$F14*M14 -> 0 | BA14: =$F14*N14 -> 0 | ... CE14: =$F14*AR14 -> 0 | CH14: =F14-SUM(AT14:CG14) -> 0
C15: Pháp lý | D15: =+'1. thong tin quy hoach'!D54 -> 28226.456 | E15: =F15/D15*10^6 -> 3020886 | F15: =2.5%*(F11+F16) -> 85268.906 | G15: ='2.Tien do'!D13 -> 0 | H15: ='2.Tien do'!E13 -> 0 | I15: ='2.Tien do'!F13 -> 0 | J15: ='2.Tien do'!G13 -> 0 | K15: ='2.Tien do'!H13 -> 0.05 | L15: ='2.Tien do'!I13 -> 0.05 | M15: ='2.Tien do'!J13 -> 0.05 | N15: ='2.Tien do'!K13 -> 0.1 | ... AR15: ='2.Tien do'!AO13 -> 0 | AT15: =$F15*G15 -> 0 | AU15: =$F15*H15 -> 0 | AV15: =$F15*I15 -> 0 | AW15: =$F15*J15 -> 0 | AX15: =$F15*K15 -> 4263.4453 | AY15: =$F15*L15 -> 4263.4453 | AZ15: =$F15*M15 -> 4263.4453 | BA15: =$F15*N15 -> 8526.8906 | ... CE15: =$F15*AR15 -> 0 | CH15: =F15-SUM(AT15:CG15) -> 0
A16: =+F16/1.1 -> 2187289.4 | B16: XÂY DỰNG | D16: =+D19+D33 -> 146585.35 | E16: =F16/D16*10^6 -> 16413770 | F16: =F17+F18 -> 2406018.3 | AT16: =+AT17+AT18 -> 0 | AU16: =+AU17+AU18 -> 0 | AV16: =+AV17+AV18 -> 0 | AW16: =+AW17+AW18 -> 0 | AX16: =+AX17+AX18 -> 0 | AY16: =+AY17+AY18 -> 0 | AZ16: =+AZ17+AZ18 -> 0 | BA16: =+BA17+BA18 -> 1429.2072 | ... BR16: =+BR17+BR18 -> 0 | BS16: =+BS19 -> 0 | BT16: =+BT19 -> 0 | BU16: =+BU19 -> 0 | BV16: =+BV19 -> 0 | BW16: =+BW19 -> 0 | BX16: =+BX19 -> 0 | BY16: =+BY19 -> 0 | BZ16: =+BZ19 -> 0 | ... CE16: =+CE19 -> 0 | CH16: =F16-SUM(AT16:CG16) -> 0
A17: =+F17/1.1 -> 0 | B17: 1 | C17: Hạ tầng | D17: =+'1. thong tin quy hoach'!D54 -> 28226.456 | E17: 0 | F17: =+D17*E17/10^6 -> 0 | H17: =+'2.Tien do'!E16 -> 0 | I17: =+'2.Tien do'!F16 -> 0 | J17: =+'2.Tien do'!G16 -> 0 | K17: =+'2.Tien do'!H16 -> 0 | L17: =+'2.Tien do'!I16 -> 0 | M17: =+'2.Tien do'!J16 -> 0 | N17: =+'2.Tien do'!K16 -> 0 | O17: =+'2.Tien do'!L16 -> 0 | ... AR17: =+'2.Tien do'!AO16 -> 0 | AT17: =+G17*$F$17 -> 0 | AU17: =+H17*$F$17 -> 0 | AV17: =+I17*$F$17 -> 0 | AW17: =+J17*$F$17 -> 0 | AX17: =+K17*$F$17 -> 0 | AY17: =+L17*$F$17 -> 0 | AZ17: =+M17*$F$17 -> 0 | BA17: =+N17*$F$17 -> 0 | ... BR17: =+AE17*$F$17 -> 0 | CH17: =F17-SUM(AT17:CG17) -> 0
A18: =+F18/1.1 -> 2187289.4 | B18: 2 | C18: Xây dựng công trình chính | F18: =+F19+F33+F47+F61+F70 -> 2406018.3 | AT18: =+AT19+AT33+AT47+AT61+AT70 -> 0 | AU18: =+AU19+AU33+AU47+AU61+AU70 -> 0 | AV18: =+AV19+AV33+AV47+AV61+AV70 -> 0 | AW18: =+AW19+AW33+AW47+AW61+AW70 -> 0 | AX18: =+AX19+AX33+AX47+AX61+AX70 -> 0 | AY18: =+AY19+AY33+AY47+AY61+AY70 -> 0 | AZ18: =+AZ19+AZ33+AZ47+AZ61+AZ70 -> 0 | BA18: =+BA19+BA33+BA47+BA61+BA70 -> 1429.2072 | ... BR18: =+BR19+BR33+BR47+BR61+BR70 -> 0
B19: 2.1 | C19: =+'2.Tien do'!C18 -> Xây dựng Chung cư Sky Habitat | D19: =+'1. thong tin quy hoach'!I12 -> 146585.35 | E19: =F19/D19*10^6 -> 15086500 | F19: =SUM(F20,F28:F32) -> 2211460 | AT19: =SUM(AT21:AT32) -> 0 | AU19: =SUM(AU21:AU32) -> 0 | AV19: =SUM(AV21:AV32) -> 0 | AW19: =SUM(AW21:AW32) -> 0 | AX19: =SUM(AX21:AX32) -> 0 | AY19: =SUM(AY21:AY32) -> 0 | AZ19: =SUM(AZ21:AZ32) -> 0 | BA19: =SUM(BA21:BA32) -> 1429.2072 | ... CE19: =SUM(CE21:CE32) -> 0 | CH19: =F19-SUM(AT19:CG19) -> 0
C20: Chi phí xây lắp thiết bị | D20: =D19 -> 146585.35 | E20: ='8.ĐO NHAY'!$C$15*10^6 -> 13000000 | F20: =D20*E20/10^6 -> 1905609.6 | AT20: =SUM(AT21:AT27) -> 0 | AU20: =SUM(AU21:AU27) -> 0 | AV20: =SUM(AV21:AV27) -> 0 | AW20: =SUM(AW21:AW27) -> 0 | AX20: =SUM(AX21:AX27) -> 0 | AY20: =SUM(AY21:AY27) -> 0 | AZ20: =SUM(AZ21:AZ27) -> 0 | BA20: =SUM(BA21:BA27) -> 1429.2072 | ... CE20: =SUM(CE21:CE27) -> 0 | CH20: =F20-SUM(AT20:CG20) -> 0
C21: Chuẩn bị thi công | E21: 0.001 | F21: =E21*$F$20 -> 1905.6096 | H21: =+'2.Tien do'!E19 -> 0 | I21: =+'2.Tien do'!F19 -> 0 | J21: =+'2.Tien do'!G19 -> 0 | K21: =+'2.Tien do'!H19 -> 0 | L21: =+'2.Tien do'!I19 -> 0 | M21: =+'2.Tien do'!J19 -> 0 | N21: =+'2.Tien do'!K19 -> 0.75 | O21: =+'2.Tien do'!L19 -> 0.25 | ... AR21: =+'2.Tien do'!AO19 -> 0 | AT21: =$F21*G21 -> 0 | AU21: =$F21*H21 -> 0 | AV21: =$F21*I21 -> 0 | AW21: =$F21*J21 -> 0 | AX21: =$F21*K21 -> 0 | AY21: =$F21*L21 -> 0 | AZ21: =$F21*M21 -> 0 | BA21: =$F21*N21 -> 1429.2072 | ... CE21: =$F21*AR21 -> 0 | CH21: =F21-SUM(AT21:CG21) -> 0
C22: Phần ngầm | E22: 0.178 | F22: =E22*$F$20 -> 339198.51 | H22: =+'2.Tien do'!E20 -> 0 | I22: =+'2.Tien do'!F20 -> 0 | J22: =+'2.Tien do'!G20 -> 0 | K22: =+'2.Tien do'!H20 -> 0 | L22: =+'2.Tien do'!I20 -> 0 | M22: =+'2.Tien do'!J20 -> 0 | N22: =+'2.Tien do'!K20 -> 0 | O22: =+'2.Tien do'!L20 -> 0.05355623 | ... AR22: =+'2.Tien do'!AO20 -> 0 | AT22: =$F22*G22 -> 0 | AU22: =$F22*H22 -> 0 | AV22: =$F22*I22 -> 0 | AW22: =$F22*J22 -> 0 | AX22: =$F22*K22 -> 0 | AY22: =$F22*L22 -> 0 | AZ22: =$F22*M22 -> 0 | BA22: =$F22*N22 -> 0 | ... CE22: =$F22*AR22 -> 0 | CH22: =F22-SUM(AT22:CG22) -> 0
C23: Phần thân | E23: 0.228 | F23: =E23*$F$20 -> 434478.99 | H23: =+'2.Tien do'!E21 -> 0 | I23: =+'2.Tien do'!F21 -> 0 | J23: =+'2.Tien do'!G21 -> 0 | K23: =+'2.Tien do'!H21 -> 0 | L23: =+'2.Tien do'!I21 -> 0 | M23: =+'2.Tien do'!J21 -> 0 | N23: =+'2.Tien do'!K21 -> 0 | O23: =+'2.Tien do'!L21 -> 0 | ... AR23: =+'2.Tien do'!AO21 -> 0 | AT23: =$F23*G23 -> 0 | AU23: =$F23*H23 -> 0 | AV23: =$F23*I23 -> 0 | AW23: =$F23*J23 -> 0 | AX23: =$F23*K23 -> 0 | AY23: =$F23*L23 -> 0 | AZ23: =$F23*M23 -> 0 | BA23: =$F23*N23 -> 0 | ... CE23: =$F23*AR23 -> 0 | CH23: =F23-SUM(AT23:CG23) -> 0
C24: Hoàn thiện | E24: 0.312 | F24: =E24*$F$20 -> 594550.2 | H24: =+'2.Tien do'!E22 -> 0 | I24: =+'2.Tien do'!F22 -> 0 | J24: =+'2.Tien do'!G22 -> 0 | K24: =+'2.Tien do'!H22 -> 0 | L24: =+'2.Tien do'!I22 -> 0 | M24: =+'2.Tien do'!J22 -> 0 | N24: =+'2.Tien do'!K22 -> 0 | O24: =+'2.Tien do'!L22 -> 0 | ... AR24: =+'2.Tien do'!AO22 -> 0 | AT24: =$F24*G24 -> 0 | AU24: =$F24*H24 -> 0 | AV24: =$F24*I24 -> 0 | AW24: =$F24*J24 -> 0 | AX24: =$F24*K24 -> 0 | AY24: =$F24*L24 -> 0 | AZ24: =$F24*M24 -> 0 | BA24: =$F24*N24 -> 0 | ... CE24: =$F24*AR24 -> 0 | CH24: =F24-SUM(AT24:CG24) -> 0
C25: M&E | E25: 0.112 | F25: =E25*$F$20 -> 213428.28 | H25: =+'2.Tien do'!E23 -> 0 | I25: =+'2.Tien do'!F23 -> 0 | J25: =+'2.Tien do'!G23 -> 0 | K25: =+'2.Tien do'!H23 -> 0 | L25: =+'2.Tien do'!I23 -> 0 | M25: =+'2.Tien do'!J23 -> 0 | N25: =+'2.Tien do'!K23 -> 0 | O25: =+'2.Tien do'!L23 -> 0 | ... AR25: =+'2.Tien do'!AO23 -> 0 | AT25: =$F25*G25 -> 0 | AU25: =$F25*H25 -> 0 | AV25: =$F25*I25 -> 0 | AW25: =$F25*J25 -> 0 | AX25: =$F25*K25 -> 0 | AY25: =$F25*L25 -> 0 | AZ25: =$F25*M25 -> 0 | BA25: =$F25*N25 -> 0 | ... CE25: =$F25*AR25 -> 0 | CH25: =F25-SUM(AT25:CG25) -> 0
C26: Xây dựng cảnh quan | E26: 0.017 | F26: =E26*$F$20 -> 32395.363 | H26: =+'2.Tien do'!E24 -> 0 | I26: =+'2.Tien do'!F24 -> 0 | J26: =+'2.Tien do'!G24 -> 0 | K26: =+'2.Tien do'!H24 -> 0 | L26: =+'2.Tien do'!I24 -> 0 | M26: =+'2.Tien do'!J24 -> 0 | N26: =+'2.Tien do'!K24 -> 0 | O26: =+'2.Tien do'!L24 -> 0 | ... AR26: =+'2.Tien do'!AO24 -> 0 | AT26: =$F26*G26 -> 0 | AU26: =$F26*H26 -> 0 | AV26: =$F26*I26 -> 0 | AW26: =$F26*J26 -> 0 | AX26: =$F26*K26 -> 0 | AY26: =$F26*L26 -> 0 | AZ26: =$F26*M26 -> 0 | BA26: =$F26*N26 -> 0 | ... CE26: =$F26*AR26 -> 0 | CH26: =F26-SUM(AT26:CG26) -> 0
C27: Thiết bị | E27: 0.152 | F27: =E27*$F$20 -> 289652.66 | H27: =+'2.Tien do'!E25 -> 0 | I27: =+'2.Tien do'!F25 -> 0 | J27: =+'2.Tien do'!G25 -> 0 | K27: =+'2.Tien do'!H25 -> 0 | L27: =+'2.Tien do'!I25 -> 0 | M27: =+'2.Tien do'!J25 -> 0 | N27: =+'2.Tien do'!K25 -> 0 | O27: =+'2.Tien do'!L25 -> 0 | ... AR27: =+'2.Tien do'!AO25 -> 0 | AT27: =$F27*G27 -> 0 | AU27: =$F27*H27 -> 0 | AV27: =$F27*I27 -> 0 | AW27: =$F27*J27 -> 0 | AX27: =$F27*K27 -> 0 | AY27: =$F27*L27 -> 0 | AZ27: =$F27*M27 -> 0 | BA27: =$F27*N27 -> 0 | ... CE27: =$F27*AR27 -> 0 | CH27: =F27-SUM(AT27:CG27) -> 0
A28: =+F28/1.1 -> 17323.724 | C28: Chi phí quản lý dự án | E28: 0.01 | F28: =E28*$F$20 -> 19056.096 | H28: =+'2.Tien do'!E26 -> 0 | I28: =+'2.Tien do'!F26 -> 0 | J28: =+'2.Tien do'!G26 -> 0 | K28: =+'2.Tien do'!H26 -> 0 | L28: =+'2.Tien do'!I26 -> 0 | M28: =+'2.Tien do'!J26 -> 0 | N28: =+'2.Tien do'!K26 -> 0 | O28: =+'2.Tien do'!L26 -> 0.1 | ... AR28: =+'2.Tien do'!AO26 -> 0 | AT28: =$F28*G28 -> 0 | AU28: =$F28*H28 -> 0 | AV28: =$F28*I28 -> 0 | AW28: =$F28*J28 -> 0 | AX28: =$F28*K28 -> 0 | AY28: =$F28*L28 -> 0 | AZ28: =$F28*M28 -> 0 | BA28: =$F28*N28 -> 0 | ... CE28: =$F28*AR28 -> 0 | CH28: =F28-SUM(AT28:CG28) -> 0
A29: =+F29/1.1 -> 69294.895 | C29: Chi phí tư vấn đầu tư xây dựng | E29: 0.04 | F29: =E29*$F$20 -> 76224.384 | H29: =+'2.Tien do'!E27 -> 0 | I29: =+'2.Tien do'!F27 -> 0 | J29: =+'2.Tien do'!G27 -> 0 | K29: =+'2.Tien do'!H27 -> 0 | L29: =+'2.Tien do'!I27 -> 0 | M29: =+'2.Tien do'!J27 -> 0 | N29: =+'2.Tien do'!K27 -> 0 | O29: =+'2.Tien do'!L27 -> 0.1 | ... AR29: =+'2.Tien do'!AO27 -> 0 | AT29: =$F29*G29 -> 0 | AU29: =$F29*H29 -> 0 | AV29: =$F29*I29 -> 0 | AW29: =$F29*J29 -> 0 | AX29: =$F29*K29 -> 0 | AY29: =$F29*L29 -> 0 | AZ29: =$F29*M29 -> 0 | BA29: =$F29*N29 -> 0 | ... CE29: =$F29*AR29 -> 0 | CH29: =F29-SUM(AT29:CG29) -> 0
A30: =+F30/1.1 -> 8661.8619 | C30: Chi phí khác | E30: 0.005 | F30: =E30*$F$20 -> 9528.0481 | H30: =+'2.Tien do'!E28 -> 0 | I30: =+'2.Tien do'!F28 -> 0 | J30: =+'2.Tien do'!G28 -> 0 | K30: =+'2.Tien do'!H28 -> 0 | L30: =+'2.Tien do'!I28 -> 0 | M30: =+'2.Tien do'!J28 -> 0 | N30: =+'2.Tien do'!K28 -> 0 | O30: =+'2.Tien do'!L28 -> 0.1 | ... AR30: =+'2.Tien do'!AO28 -> 0 | AT30: =$F30*G30 -> 0 | AU30: =$F30*H30 -> 0 | AV30: =$F30*I30 -> 0 | AW30: =$F30*J30 -> 0 | AX30: =$F30*K30 -> 0 | AY30: =$F30*L30 -> 0 | AZ30: =$F30*M30 -> 0 | BA30: =$F30*N30 -> 0 | ... CE30: =$F30*AR30 -> 0 | CH30: =F30-SUM(AT30:CG30) -> 0
A31: =+F31/1.1 -> 182765.29 | C31: Chi phí dự phòng | E31: 0.1 | F31: =E31*(SUM(F28:F30)+F20) -> 201041.81 | H31: =+'2.Tien do'!E29 -> 0 | I31: =+'2.Tien do'!F29 -> 0 | J31: =+'2.Tien do'!G29 -> 0 | K31: =+'2.Tien do'!H29 -> 0 | L31: =+'2.Tien do'!I29 -> 0 | M31: =+'2.Tien do'!J29 -> 0 | N31: =+'2.Tien do'!K29 -> 0 | O31: =+'2.Tien do'!L29 -> 0.1 | ... AR31: =+'2.Tien do'!AO29 -> 0 | AT31: =$F31*G31 -> 0 | AU31: =$F31*H31 -> 0 | AV31: =$F31*I31 -> 0 | AW31: =$F31*J31 -> 0 | AX31: =$F31*K31 -> 0 | AY31: =$F31*L31 -> 0 | AZ31: =$F31*M31 -> 0 | BA31: =$F31*N31 -> 0 | ... CE31: =$F31*AR31 -> 0
E32: 0 | F32: =E32*(SUM(F28:F30)+F20) -> 0 | H32: =+H31 -> 0 | I32: =+I31 -> 0 | J32: =+J31 -> 0 | K32: =+K31 -> 0 | L32: =+L31 -> 0 | S32: =+S31 -> 0.1 | T32: =+T31 -> 0.1 | U32: =+U31 -> 0.1 | V32: =+V31 -> 0.1 | W32: =+W31 -> 0.1 | X32: =+X31 -> 0.1 | Y32: =+Y31 -> 0 | Z32: =+Z31 -> 0 | ... AR32: =+AR31 -> 0 | AT32: =$F32*G32 -> 0 | AU32: =$F32*H32 -> 0 | AV32: =$F32*I32 -> 0 | AW32: =$F32*J32 -> 0 | AX32: =$F32*K32 -> 0 | AY32: =$F32*L32 -> 0 | AZ32: =$F32*M32 -> 0 | BA32: =$F32*N32 -> 0 | ... CE32: =$F32*AR32 -> 0 | CH32: =F32-SUM(AT32:CG32) -> 0
B33: 2.1 | C33: =+'2.Tien do'!C30 -> Xây dựng Chung cư …. | D33: =+'1. thong tin quy hoach'!I21 -> 0 | E33: =F33/D33*10^6 -> #DIV/0! | F33: =SUM(F34,F42:F46) -> 0 | AT33: =SUM(AT35:AT46) -> 0 | AU33: =SUM(AU35:AU46) -> 0 | AV33: =SUM(AV35:AV46) -> 0 | AW33: =SUM(AW35:AW46) -> 0 | AX33: =SUM(AX35:AX46) -> 0 | AY33: =SUM(AY35:AY46) -> 0 | AZ33: =SUM(AZ35:AZ46) -> 0 | BA33: =SUM(BA35:BA46) -> 0 | ... CE33: =SUM(CE35:CE46) -> 0 | CH33: =F33-SUM(AT33:CG33) -> 0
C34: Chi phí xây lắp thiết bị | D34: =D33 -> 0 | E34: ='8.ĐO NHAY'!$C$16*10^6 -> 13000000 | F34: =D34*E34/10^6 -> 0 | AT34: =SUM(AT35:AT41) -> 0 | AU34: =SUM(AU35:AU41) -> 0 | AV34: =SUM(AV35:AV41) -> 0 | AW34: =SUM(AW35:AW41) -> 0 | AX34: =SUM(AX35:AX41) -> 0 | AY34: =SUM(AY35:AY41) -> 0 | AZ34: =SUM(AZ35:AZ41) -> 0 | BA34: =SUM(BA35:BA41) -> 0 | ... CE34: =SUM(CE35:CE41) -> 0 | CH34: =F34-SUM(AT34:CG34) -> 0
C35: Chuẩn bị thi công | E35: 0.001 | F35: =E35*$F$34 -> 0 | H35: =+'2.Tien do'!E31 -> 0 | I35: =+'2.Tien do'!F31 -> 0 | J35: =+'2.Tien do'!G31 -> 0 | K35: =+'2.Tien do'!H31 -> 0 | L35: =+'2.Tien do'!I31 -> 0 | M35: =+'2.Tien do'!J31 -> 0 | N35: =+'2.Tien do'!K31 -> 0 | O35: =+'2.Tien do'!L31 -> 0 | ... AR35: =+'2.Tien do'!AO31 -> 0 | AT35: =$F35*G35 -> 0 | AU35: =$F35*H35 -> 0 | AV35: =$F35*I35 -> 0 | AW35: =$F35*J35 -> 0 | AX35: =$F35*K35 -> 0 | AY35: =$F35*L35 -> 0 | AZ35: =$F35*M35 -> 0 | BA35: =$F35*N35 -> 0 | ... CE35: =$F35*AR35 -> 0 | CH35: =F35-SUM(AT35:CG35) -> 0
C36: Phần ngầm | E36: 0.178 | F36: =E36*$F$34 -> 0 | H36: =+'2.Tien do'!E32 -> 0 | I36: =+'2.Tien do'!F32 -> 0 | J36: =+'2.Tien do'!G32 -> 0 | K36: =+'2.Tien do'!H32 -> 0 | L36: =+'2.Tien do'!I32 -> 0 | M36: =+'2.Tien do'!J32 -> 0 | N36: =+'2.Tien do'!K32 -> 0 | O36: =+'2.Tien do'!L32 -> 0 | ... AR36: =+'2.Tien do'!AO32 -> 0 | AT36: =$F36*G36 -> 0 | AU36: =$F36*H36 -> 0 | AV36: =$F36*I36 -> 0 | AW36: =$F36*J36 -> 0 | AX36: =$F36*K36 -> 0 | AY36: =$F36*L36 -> 0 | AZ36: =$F36*M36 -> 0 | BA36: =$F36*N36 -> 0 | ... CE36: =$F36*AR36 -> 0 | CH36: =F36-SUM(AT36:CG36) -> 0
C37: Phần thân | E37: 0.228 | F37: =E37*$F$34 -> 0 | H37: =+'2.Tien do'!E33 -> 0 | I37: =+'2.Tien do'!F33 -> 0 | J37: =+'2.Tien do'!G33 -> 0 | K37: =+'2.Tien do'!H33 -> 0 | L37: =+'2.Tien do'!I33 -> 0 | M37: =+'2.Tien do'!J33 -> 0 | N37: =+'2.Tien do'!K33 -> 0 | O37: =+'2.Tien do'!L33 -> 0 | ... AR37: =+'2.Tien do'!AO33 -> 0 | AT37: =$F37*G37 -> 0 | AU37: =$F37*H37 -> 0 | AV37: =$F37*I37 -> 0 | AW37: =$F37*J37 -> 0 | AX37: =$F37*K37 -> 0 | AY37: =$F37*L37 -> 0 | AZ37: =$F37*M37 -> 0 | BA37: =$F37*N37 -> 0 | ... CE37: =$F37*AR37 -> 0 | CH37: =F37-SUM(AT37:CG37) -> 0
C38: Hoàn thiện | E38: 0.312 | F38: =E38*$F$34 -> 0 | H38: =+'2.Tien do'!E34 -> 0 | I38: =+'2.Tien do'!F34 -> 0 | J38: =+'2.Tien do'!G34 -> 0 | K38: =+'2.Tien do'!H34 -> 0 | L38: =+'2.Tien do'!I34 -> 0 | M38: =+'2.Tien do'!J34 -> 0 | N38: =+'2.Tien do'!K34 -> 0 | O38: =+'2.Tien do'!L34 -> 0 | ... AR38: =+'2.Tien do'!AO34 -> 0 | AT38: =$F38*G38 -> 0 | AU38: =$F38*H38 -> 0 | AV38: =$F38*I38 -> 0 | AW38: =$F38*J38 -> 0 | AX38: =$F38*K38 -> 0 | AY38: =$F38*L38 -> 0 | AZ38: =$F38*M38 -> 0 | BA38: =$F38*N38 -> 0 | ... CE38: =$F38*AR38 -> 0 | CH38: =F38-SUM(AT38:CG38) -> 0
C39: M&E | E39: 0.112 | F39: =E39*$F$34 -> 0 | H39: =+'2.Tien do'!E35 -> 0 | I39: =+'2.Tien do'!F35 -> 0 | J39: =+'2.Tien do'!G35 -> 0 | K39: =+'2.Tien do'!H35 -> 0 | L39: =+'2.Tien do'!I35 -> 0 | M39: =+'2.Tien do'!J35 -> 0 | N39: =+'2.Tien do'!K35 -> 0 | O39: =+'2.Tien do'!L35 -> 0 | ... AR39: =+'2.Tien do'!AO35 -> 0 | AT39: =$F39*G39 -> 0 | AU39: =$F39*H39 -> 0 | AV39: =$F39*I39 -> 0 | AW39: =$F39*J39 -> 0 | AX39: =$F39*K39 -> 0 | AY39: =$F39*L39 -> 0 | AZ39: =$F39*M39 -> 0 | BA39: =$F39*N39 -> 0 | ... CE39: =$F39*AR39 -> 0 | CH39: =F39-SUM(AT39:CG39) -> 0
C40: Xây dựng cảnh quan | E40: 0.017 | F40: =E40*$F$34 -> 0 | H40: =+'2.Tien do'!E36 -> 0 | I40: =+'2.Tien do'!F36 -> 0 | J40: =+'2.Tien do'!G36 -> 0 | K40: =+'2.Tien do'!H36 -> 0 | L40: =+'2.Tien do'!I36 -> 0 | M40: =+'2.Tien do'!J36 -> 0 | N40: =+'2.Tien do'!K36 -> 0 | O40: =+'2.Tien do'!L36 -> 0 | ... AR40: =+'2.Tien do'!AO36 -> 0 | AT40: =$F40*G40 -> 0 | AU40: =$F40*H40 -> 0 | AV40: =$F40*I40 -> 0 | AW40: =$F40*J40 -> 0 | AX40: =$F40*K40 -> 0 | AY40: =$F40*L40 -> 0 | AZ40: =$F40*M40 -> 0 | BA40: =$F40*N40 -> 0 | ... CE40: =$F40*AR40 -> 0 | CH40: =F40-SUM(AT40:CG40) -> 0
C41: Thiết bị | E41: 0.152 | F41: =E41*$F$34 -> 0 | H41: =+'2.Tien do'!E37 -> 0 | I41: =+'2.Tien do'!F37 -> 0 | J41: =+'2.Tien do'!G37 -> 0 | K41: =+'2.Tien do'!H37 -> 0 | L41: =+'2.Tien do'!I37 -> 0 | M41: =+'2.Tien do'!J37 -> 0 | N41: =+'2.Tien do'!K37 -> 0 | O41: =+'2.Tien do'!L37 -> 0 | ... AR41: =+'2.Tien do'!AO37 -> 0 | AT41: =$F41*G41 -> 0 | AU41: =$F41*H41 -> 0 | AV41: =$F41*I41 -> 0 | AW41: =$F41*J41 -> 0 | AX41: =$F41*K41 -> 0 | AY41: =$F41*L41 -> 0 | AZ41: =$F41*M41 -> 0 | BA41: =$F41*N41 -> 0 | ... CE41: =$F41*AR41 -> 0 | CH41: =F41-SUM(AT41:CG41) -> 0
C42: Chi phí quản lý dự án | E42: 0.01 | F42: =E42*$F$34 -> 0 | H42: =+'2.Tien do'!E38 -> 0 | I42: =+'2.Tien do'!F38 -> 0 | J42: =+'2.Tien do'!G38 -> 0 | K42: =+'2.Tien do'!H38 -> 0 | L42: =+'2.Tien do'!I38 -> 0 | M42: =+'2.Tien do'!J38 -> 0 | N42: =+'2.Tien do'!K38 -> 0 | O42: =+'2.Tien do'!L38 -> 0 | ... AR42: =+'2.Tien do'!AO38 -> 0 | AT42: =$F42*G42 -> 0 | AU42: =$F42*H42 -> 0 | AV42: =$F42*I42 -> 0 | AW42: =$F42*J42 -> 0 | AX42: =$F42*K42 -> 0 | AY42: =$F42*L42 -> 0 | AZ42: =$F42*M42 -> 0 | BA42: =$F42*N42 -> 0 | ... CE42: =$F42*AR42 -> 0 | CH42: =F42-SUM(AT42:CG42) -> 0
C43: Chi phí tư vấn đầu tư xây dựng | E43: 0.04 | F43: =E43*$F$34 -> 0 | H43: =+'2.Tien do'!E39 -> 0 | I43: =+'2.Tien do'!F39 -> 0 | J43: =+'2.Tien do'!G39 -> 0 | K43: =+'2.Tien do'!H39 -> 0 | L43: =+'2.Tien do'!I39 -> 0 | M43: =+'2.Tien do'!J39 -> 0 | N43: =+'2.Tien do'!K39 -> 0 | O43: =+'2.Tien do'!L39 -> 0 | ... AR43: =+'2.Tien do'!AO39 -> 0 | AT43: =$F43*G43 -> 0 | AU43: =$F43*H43 -> 0 | AV43: =$F43*I43 -> 0 | AW43: =$F43*J43 -> 0 | AX43: =$F43*K43 -> 0 | AY43: =$F43*L43 -> 0 | AZ43: =$F43*M43 -> 0 | BA43: =$F43*N43 -> 0 | ... CE43: =$F43*AR43 -> 0 | CH43: =F43-SUM(AT43:CG43) -> 0
C44: Chi phí khác | E44: 0.005 | F44: =E44*$F$34 -> 0 | H44: =+'2.Tien do'!E40 -> 0 | I44: =+'2.Tien do'!F40 -> 0 | J44: =+'2.Tien do'!G40 -> 0 | K44: =+'2.Tien do'!H40 -> 0 | L44: =+'2.Tien do'!I40 -> 0 | M44: =+'2.Tien do'!J40 -> 0 | N44: =+'2.Tien do'!K40 -> 0 | O44: =+'2.Tien do'!L40 -> 0 | ... AR44: =+'2.Tien do'!AO40 -> 0 | AT44: =$F44*G44 -> 0 | AU44: =$F44*H44 -> 0 | AV44: =$F44*I44 -> 0 | AW44: =$F44*J44 -> 0 | AX44: =$F44*K44 -> 0 | AY44: =$F44*L44 -> 0 | AZ44: =$F44*M44 -> 0 | BA44: =$F44*N44 -> 0 | ... CE44: =$F44*AR44 -> 0 | CH44: =F44-SUM(AT44:CG44) -> 0
C45: Chi phí dự phòng | E45: 0.1 | F45: =E45*(SUM(F42:F44)+F34) -> 0 | H45: =+'2.Tien do'!E41 -> 0 | I45: =+'2.Tien do'!F41 -> 0 | J45: =+'2.Tien do'!G41 -> 0 | K45: =+'2.Tien do'!H41 -> 0 | L45: =+'2.Tien do'!I41 -> 0 | M45: =+'2.Tien do'!J41 -> 0 | N45: =+'2.Tien do'!K41 -> 0 | O45: =+'2.Tien do'!L41 -> 0 | ... AR45: =+'2.Tien do'!AO41 -> 0 | AT45: =$F45*G45 -> 0 | AU45: =$F45*H45 -> 0 | AV45: =$F45*I45 -> 0 | AW45: =$F45*J45 -> 0 | AX45: =$F45*K45 -> 0 | AY45: =$F45*L45 -> 0 | AZ45: =$F45*M45 -> 0 | BA45: =$F45*N45 -> 0 | ... CE45: =$F45*AR45 -> 0
E46: 0 | F46: =E46*(SUM(F42:F44)+F34) -> 0 | H46: =+'2.Tien do'!E42 -> 0 | I46: =+'2.Tien do'!F42 -> 0 | J46: =+'2.Tien do'!G42 -> 0 | K46: =+'2.Tien do'!H42 -> 0 | L46: =+'2.Tien do'!I42 -> 0 | M46: =+'2.Tien do'!J42 -> 0 | N46: =+'2.Tien do'!K42 -> 0 | O46: =+'2.Tien do'!L42 -> 0 | ... AR46: =+'2.Tien do'!AO42 -> 0 | AT46: =$F46*G46 -> 0 | AU46: =$F46*H46 -> 0 | AV46: =$F46*I46 -> 0 | AW46: =$F46*J46 -> 0 | AX46: =$F46*K46 -> 0 | AY46: =$F46*L46 -> 0 | AZ46: =$F46*M46 -> 0 | BA46: =$F46*N46 -> 0 | ... CE46: =$F46*AR46 -> 0 | CH46: =F46-SUM(AT46:CG46) -> 0
B47: 2.1 | C47: =+'2.Tien do'!C42 -> Xây dựng Chung cư … | D47: =+'1. thong tin quy hoach'!I29 -> 0 | E47: =F47/D47*10^6 -> #DIV/0! | F47: =SUM(F48,F56:F60) -> 0 | AT47: =SUM(AT49:AT60) -> 0 | AU47: =SUM(AU49:AU60) -> 0 | AV47: =SUM(AV49:AV60) -> 0 | AW47: =SUM(AW49:AW60) -> 0 | AX47: =SUM(AX49:AX60) -> 0 | AY47: =SUM(AY49:AY60) -> 0 | AZ47: =SUM(AZ49:AZ60) -> 0 | BA47: =SUM(BA49:BA60) -> 0 | ... CE47: =SUM(CE49:CE60) -> 0 | CH47: =F47-SUM(AT47:CG47) -> 0
C48: Chi phí xây lắp thiết bị | D48: =D47 -> 0 | E48: ='8.ĐO NHAY'!$C$15*10^6 -> 13000000 | F48: =D48*E48/10^6 -> 0 | AT48: =SUM(AT49:AT55) -> 0 | AU48: =SUM(AU49:AU55) -> 0 | AV48: =SUM(AV49:AV55) -> 0 | AW48: =SUM(AW49:AW55) -> 0 | AX48: =SUM(AX49:AX55) -> 0 | AY48: =SUM(AY49:AY55) -> 0 | AZ48: =SUM(AZ49:AZ55) -> 0 | BA48: =SUM(BA49:BA55) -> 0 | ... CE48: =SUM(CE49:CE55) -> 0 | CH48: =F48-SUM(AT48:CG48) -> 0
C49: Chuẩn bị thi công | E49: 0.001 | F49: =E49*$F$48 -> 0 | H49: =+'2.Tien do'!E43 -> 0 | I49: =+'2.Tien do'!F43 -> 0 | J49: =+'2.Tien do'!G43 -> 0 | K49: =+'2.Tien do'!H43 -> 0 | L49: =+'2.Tien do'!I43 -> 0 | M49: =+'2.Tien do'!J43 -> 0 | N49: =+'2.Tien do'!K43 -> 0 | O49: =+'2.Tien do'!L43 -> 0 | ... AR49: =+'2.Tien do'!AO43 -> 0 | AT49: =$F49*G49 -> 0 | AU49: =$F49*H49 -> 0 | AV49: =$F49*I49 -> 0 | AW49: =$F49*J49 -> 0 | AX49: =$F49*K49 -> 0 | AY49: =$F49*L49 -> 0 | AZ49: =$F49*M49 -> 0 | BA49: =$F49*N49 -> 0 | ... CE49: =$F49*AR49 -> 0 | CH49: =F49-SUM(AT49:CG49) -> 0
C50: Phần ngầm | E50: 0.178 | F50: =E50*$F$48 -> 0 | H50: =+'2.Tien do'!E44 -> 0 | I50: =+'2.Tien do'!F44 -> 0 | J50: =+'2.Tien do'!G44 -> 0 | K50: =+'2.Tien do'!H44 -> 0 | L50: =+'2.Tien do'!I44 -> 0 | M50: =+'2.Tien do'!J44 -> 0 | N50: =+'2.Tien do'!K44 -> 0 | O50: =+'2.Tien do'!L44 -> 0 | ... AR50: =+'2.Tien do'!AO44 -> 0 | AT50: =$F50*G50 -> 0 | AU50: =$F50*H50 -> 0 | AV50: =$F50*I50 -> 0 | AW50: =$F50*J50 -> 0 | AX50: =$F50*K50 -> 0 | AY50: =$F50*L50 -> 0 | AZ50: =$F50*M50 -> 0 | BA50: =$F50*N50 -> 0 | ... CE50: =$F50*AR50 -> 0 | CH50: =F50-SUM(AT50:CG50) -> 0
C51: Phần thân | E51: 0.228 | F51: =E51*$F$48 -> 0 | H51: =+'2.Tien do'!E45 -> 0 | I51: =+'2.Tien do'!F45 -> 0 | J51: =+'2.Tien do'!G45 -> 0 | K51: =+'2.Tien do'!H45 -> 0 | L51: =+'2.Tien do'!I45 -> 0 | M51: =+'2.Tien do'!J45 -> 0 | N51: =+'2.Tien do'!K45 -> 0 | O51: =+'2.Tien do'!L45 -> 0 | ... AR51: =+'2.Tien do'!AO45 -> 0 | AT51: =$F51*G51 -> 0 | AU51: =$F51*H51 -> 0 | AV51: =$F51*I51 -> 0 | AW51: =$F51*J51 -> 0 | AX51: =$F51*K51 -> 0 | AY51: =$F51*L51 -> 0 | AZ51: =$F51*M51 -> 0 | BA51: =$F51*N51 -> 0 | ... CE51: =$F51*AR51 -> 0 | CH51: =F51-SUM(AT51:CG51) -> 0
C52: Hoàn thiện | E52: 0.312 | F52: =E52*$F$48 -> 0 | H52: =+'2.Tien do'!E46 -> 0 | I52: =+'2.Tien do'!F46 -> 0 | J52: =+'2.Tien do'!G46 -> 0 | K52: =+'2.Tien do'!H46 -> 0 | L52: =+'2.Tien do'!I46 -> 0 | M52: =+'2.Tien do'!J46 -> 0 | N52: =+'2.Tien do'!K46 -> 0 | O52: =+'2.Tien do'!L46 -> 0 | ... AR52: =+'2.Tien do'!AO46 -> 0 | AT52: =$F52*G52 -> 0 | AU52: =$F52*H52 -> 0 | AV52: =$F52*I52 -> 0 | AW52: =$F52*J52 -> 0 | AX52: =$F52*K52 -> 0 | AY52: =$F52*L52 -> 0 | AZ52: =$F52*M52 -> 0 | BA52: =$F52*N52 -> 0 | ... CE52: =$F52*AR52 -> 0 | CH52: =F52-SUM(AT52:CG52) -> 0
C53: M&E | E53: 0.112 | F53: =E53*$F$48 -> 0 | H53: =+'2.Tien do'!E47 -> 0 | I53: =+'2.Tien do'!F47 -> 0 | J53: =+'2.Tien do'!G47 -> 0 | K53: =+'2.Tien do'!H47 -> 0 | L53: =+'2.Tien do'!I47 -> 0 | M53: =+'2.Tien do'!J47 -> 0 | N53: =+'2.Tien do'!K47 -> 0 | O53: =+'2.Tien do'!L47 -> 0 | ... AR53: =+'2.Tien do'!AO47 -> 0 | AT53: =$F53*G53 -> 0 | AU53: =$F53*H53 -> 0 | AV53: =$F53*I53 -> 0 | AW53: =$F53*J53 -> 0 | AX53: =$F53*K53 -> 0 | AY53: =$F53*L53 -> 0 | AZ53: =$F53*M53 -> 0 | BA53: =$F53*N53 -> 0 | ... CE53: =$F53*AR53 -> 0 | CH53: =F53-SUM(AT53:CG53) -> 0
C54: Xây dựng cảnh quan | E54: 0.017 | F54: =E54*$F$48 -> 0 | H54: =+'2.Tien do'!E48 -> 0 | I54: =+'2.Tien do'!F48 -> 0 | J54: =+'2.Tien do'!G48 -> 0 | K54: =+'2.Tien do'!H48 -> 0 | L54: =+'2.Tien do'!I48 -> 0 | M54: =+'2.Tien do'!J48 -> 0 | N54: =+'2.Tien do'!K48 -> 0 | O54: =+'2.Tien do'!L48 -> 0 | ... AR54: =+'2.Tien do'!AO48 -> 0 | AT54: =$F54*G54 -> 0 | AU54: =$F54*H54 -> 0 | AV54: =$F54*I54 -> 0 | AW54: =$F54*J54 -> 0 | AX54: =$F54*K54 -> 0 | AY54: =$F54*L54 -> 0 | AZ54: =$F54*M54 -> 0 | BA54: =$F54*N54 -> 0 | ... CE54: =$F54*AR54 -> 0 | CH54: =F54-SUM(AT54:CG54) -> 0
C55: Thiết bị | E55: 0.152 | F55: =E55*$F$48 -> 0 | H55: =+'2.Tien do'!E49 -> 0 | I55: =+'2.Tien do'!F49 -> 0 | J55: =+'2.Tien do'!G49 -> 0 | K55: =+'2.Tien do'!H49 -> 0 | L55: =+'2.Tien do'!I49 -> 0 | M55: =+'2.Tien do'!J49 -> 0 | N55: =+'2.Tien do'!K49 -> 0 | O55: =+'2.Tien do'!L49 -> 0 | ... AR55: =+'2.Tien do'!AO49 -> 0 | AT55: =$F55*G55 -> 0 | AU55: =$F55*H55 -> 0 | AV55: =$F55*I55 -> 0 | AW55: =$F55*J55 -> 0 | AX55: =$F55*K55 -> 0 | AY55: =$F55*L55 -> 0 | AZ55: =$F55*M55 -> 0 | BA55: =$F55*N55 -> 0 | ... CE55: =$F55*AR55 -> 0 | CH55: =F55-SUM(AT55:CG55) -> 0
C56: Chi phí quản lý dự án | E56: 0.01 | F56: =E56*$F$48 -> 0 | H56: =+'2.Tien do'!E50 -> 0 | I56: =+'2.Tien do'!F50 -> 0 | J56: =+'2.Tien do'!G50 -> 0 | K56: =+'2.Tien do'!H50 -> 0 | L56: =+'2.Tien do'!I50 -> 0 | M56: =+'2.Tien do'!J50 -> 0 | N56: =+'2.Tien do'!K50 -> 0 | O56: =+'2.Tien do'!L50 -> 0 | ... AR56: =+'2.Tien do'!AO50 -> 0 | AT56: =$F56*G56 -> 0 | AU56: =$F56*H56 -> 0 | AV56: =$F56*I56 -> 0 | AW56: =$F56*J56 -> 0 | AX56: =$F56*K56 -> 0 | AY56: =$F56*L56 -> 0 | AZ56: =$F56*M56 -> 0 | BA56: =$F56*N56 -> 0 | ... CE56: =$F56*AR56 -> 0 | CH56: =F56-SUM(AT56:CG56) -> 0
C57: Chi phí tư vấn đầu tư xây dựng | E57: 0.04 | F57: =E57*$F$48 -> 0 | H57: =+'2.Tien do'!E51 -> 0 | I57: =+'2.Tien do'!F51 -> 0 | J57: =+'2.Tien do'!G51 -> 0 | K57: =+'2.Tien do'!H51 -> 0 | L57: =+'2.Tien do'!I51 -> 0 | M57: =+'2.Tien do'!J51 -> 0 | N57: =+'2.Tien do'!K51 -> 0 | O57: =+'2.Tien do'!L51 -> 0 | ... AR57: =+'2.Tien do'!AO51 -> 0 | AT57: =$F57*G57 -> 0 | AU57: =$F57*H57 -> 0 | AV57: =$F57*I57 -> 0 | AW57: =$F57*J57 -> 0 | AX57: =$F57*K57 -> 0 | AY57: =$F57*L57 -> 0 | AZ57: =$F57*M57 -> 0 | BA57: =$F57*N57 -> 0 | ... CE57: =$F57*AR57 -> 0 | CH57: =F57-SUM(AT57:CG57) -> 0
C58: Chi phí khác | E58: 0.005 | F58: =E58*$F$48 -> 0 | H58: =+'2.Tien do'!E52 -> 0 | I58: =+'2.Tien do'!F52 -> 0 | J58: =+'2.Tien do'!G52 -> 0 | K58: =+'2.Tien do'!H52 -> 0 | L58: =+'2.Tien do'!I52 -> 0 | M58: =+'2.Tien do'!J52 -> 0 | N58: =+'2.Tien do'!K52 -> 0 | O58: =+'2.Tien do'!L52 -> 0 | ... AR58: =+'2.Tien do'!AO52 -> 0 | AT58: =$F58*G58 -> 0 | AU58: =$F58*H58 -> 0 | AV58: =$F58*I58 -> 0 | AW58: =$F58*J58 -> 0 | AX58: =$F58*K58 -> 0 | AY58: =$F58*L58 -> 0 | AZ58: =$F58*M58 -> 0 | BA58: =$F58*N58 -> 0 | ... CE58: =$F58*AR58 -> 0 | CH58: =F58-SUM(AT58:CG58) -> 0
C59: Chi phí dự phòng | E59: 0.1 | F59: =E59*(SUM(F56:F58)+F48) -> 0 | H59: =+'2.Tien do'!E53 -> 0 | I59: =+'2.Tien do'!F53 -> 0 | J59: =+'2.Tien do'!G53 -> 0 | K59: =+'2.Tien do'!H53 -> 0 | L59: =+'2.Tien do'!I53 -> 0 | M59: =+'2.Tien do'!J53 -> 0 | N59: =+'2.Tien do'!K53 -> 0 | O59: =+'2.Tien do'!L53 -> 0 | ... AR59: =+'2.Tien do'!AO53 -> 0 | AT59: =$F59*G59 -> 0 | AU59: =$F59*H59 -> 0 | AV59: =$F59*I59 -> 0 | AW59: =$F59*J59 -> 0 | AX59: =$F59*K59 -> 0 | AY59: =$F59*L59 -> 0 | AZ59: =$F59*M59 -> 0 | BA59: =$F59*N59 -> 0 | ... CE59: =$F59*AR59 -> 0
E60: 0 | F60: =E60*(SUM(F56:F58)+F48) -> 0 | H60: =+'2.Tien do'!E54 -> 0 | I60: =+'2.Tien do'!F54 -> 0 | J60: =+'2.Tien do'!G54 -> 0 | K60: =+'2.Tien do'!H54 -> 0 | L60: =+'2.Tien do'!I54 -> 0 | M60: =+'2.Tien do'!J54 -> 0 | N60: =+'2.Tien do'!K54 -> 0 | O60: =+'2.Tien do'!L54 -> 0 | ... AR60: =+'2.Tien do'!AO54 -> 0 | AT60: =$F60*G60 -> 0 | AU60: =$F60*H60 -> 0 | AV60: =$F60*I60 -> 0 | AW60: =$F60*J60 -> 0 | AX60: =$F60*K60 -> 0 | AY60: =$F60*L60 -> 0 | AZ60: =$F60*M60 -> 0 | BA60: =$F60*N60 -> 0 | ... CE60: =$F60*AR60 -> 0 | CH60: =F60-SUM(AT60:CG60) -> 0
B61: 2.2 | C61: Khu thấp tầng | D61: =+D62 -> 25975.746 | E61: =IFERROR(F61/D62*10^6,0) -> 7490000 | F61: =+SUM(F62:F69) -> 194558.34 | AT61: =+SUM(AT62:AT69) -> 0 | AU61: =+SUM(AU62:AU69) -> 0 | AV61: =+SUM(AV62:AV69) -> 0 | AW61: =+SUM(AW62:AW69) -> 0 | AX61: =+SUM(AX62:AX69) -> 0 | AY61: =+SUM(AY62:AY69) -> 0 | AZ61: =+SUM(AZ62:AZ69) -> 0 | BA61: =+SUM(BA62:BA69) -> 0 | ... BR61: =+SUM(BR62:BR69) -> 0 | CH61: =F61-SUM(AT61:CG61) -> 0
C62: ='2.Tien do'!C55 -> Nhà phố liên kế | D62: =+'1. thong tin quy hoach'!I38 -> 25975.746 | E62: =+'8.ĐO NHAY'!C17*10^6 -> 7000000 | F62: =+D62*E62/10^6 -> 181830.23 | H62: =+'2.Tien do'!E55 -> 0 | I62: =+'2.Tien do'!F55 -> 0 | J62: =+'2.Tien do'!G55 -> 0 | K62: =+'2.Tien do'!H55 -> 0 | L62: =+'2.Tien do'!I55 -> 0 | M62: =+'2.Tien do'!J55 -> 0 | N62: =+'2.Tien do'!K55 -> 0 | O62: =+'2.Tien do'!L55 -> 0 | ... AR62: =+'2.Tien do'!AO55 -> 0 | AT62: =+$F62*G62 -> 0 | AU62: =+$F62*H62 -> 0 | AV62: =+$F62*I62 -> 0 | AW62: =+$F62*J62 -> 0 | AX62: =+$F62*K62 -> 0 | AY62: =+$F62*L62 -> 0 | AZ62: =+$F62*M62 -> 0 | BA62: =+$F62*N62 -> 0 | ... BR62: =+$F62*AE62 -> 0 | CH62: =F62-SUM(AT62:CG62) -> 0
C63: =+'2.Tien do'!C56 -> 0 | D63: =+'1. thong tin quy hoach'!I39 -> 0 | E63: =+'8.ĐO NHAY'!C17*10^6 -> 7000000 | F63: =+D63*E63/10^6 -> 0 | H63: =+'2.Tien do'!E56 -> 0 | I63: =+'2.Tien do'!F56 -> 0 | J63: =+'2.Tien do'!G56 -> 0 | K63: =+'2.Tien do'!H56 -> 0 | L63: =+'2.Tien do'!I56 -> 0 | M63: =+'2.Tien do'!J56 -> 0 | N63: =+'2.Tien do'!K56 -> 0 | O63: =+'2.Tien do'!L56 -> 0 | ... AR63: =+'2.Tien do'!AO56 -> 0 | AT63: =+$F63*G63 -> 0 | AU63: =+$F63*H63 -> 0 | AV63: =+$F63*I63 -> 0 | AW63: =+$F63*J63 -> 0 | AX63: =+$F63*K63 -> 0 | AY63: =+$F63*L63 -> 0 | AZ63: =+$F63*M63 -> 0 | BA63: =+$F63*N63 -> 0 | ... BR63: =+$F63*AE63 -> 0 | CH63: =F63-SUM(AT63:CG63) -> 0
C64: =+'2.Tien do'!C57 -> 0 | D64: =+'1. thong tin quy hoach'!I40 -> 0 | E64: =+'8.ĐO NHAY'!C17*10^6 -> 7000000 | F64: =+D64*E64/10^6 -> 0 | H64: =+'2.Tien do'!E57 -> 0 | I64: =+'2.Tien do'!F57 -> 0 | J64: =+'2.Tien do'!G57 -> 0 | K64: =+'2.Tien do'!H57 -> 0 | L64: =+'2.Tien do'!I57 -> 0 | M64: =+'2.Tien do'!J57 -> 0 | N64: =+'2.Tien do'!K57 -> 0 | O64: =+'2.Tien do'!L57 -> 0 | ... AR64: =+'2.Tien do'!AO57 -> 0 | AT64: =+$F64*G64 -> 0 | AU64: =+$F64*H64 -> 0 | AV64: =+$F64*I64 -> 0 | AW64: =+$F64*J64 -> 0 | AX64: =+$F64*K64 -> 0 | AY64: =+$F64*L64 -> 0 | AZ64: =+$F64*M64 -> 0 | BA64: =+$F64*N64 -> 0 | ... BR64: =+$F64*AE64 -> 0 | CH64: =F64-SUM(AT64:CG64) -> 0
C65: =+'2.Tien do'!C58 -> 0 | D65: =+'1. thong tin quy hoach'!I41 -> 0 | E65: =+'8.ĐO NHAY'!C18*10^6 -> 0 | F65: =+D65*E65/10^6 -> 0 | H65: =+'2.Tien do'!E58 -> 0 | I65: =+'2.Tien do'!F58 -> 0 | J65: =+'2.Tien do'!G58 -> 0 | K65: =+'2.Tien do'!H58 -> 0 | L65: =+'2.Tien do'!I58 -> 0 | M65: =+'2.Tien do'!J58 -> 0 | N65: =+'2.Tien do'!K58 -> 0 | O65: =+'2.Tien do'!L58 -> 0 | ... AR65: =+'2.Tien do'!AO58 -> 0 | AT65: =+$F65*G65 -> 0 | AU65: =+$F65*H65 -> 0 | AV65: =+$F65*I65 -> 0 | AW65: =+$F65*J65 -> 0 | AX65: =+$F65*K65 -> 0 | AY65: =+$F65*L65 -> 0 | AZ65: =+$F65*M65 -> 0 | BA65: =+$F65*N65 -> 0 | ... BR65: =+$F65*AE65 -> 0 | CH65: =F65-SUM(AT65:CG65) -> 0
C66: Chi phí tư vấn đầu tư xây dựng | F66: =SUM($F$62:$F$64)*E66 -> 0 | M66: =100%/5 -> 0.2 | N66: =100%/5 -> 0.2 | O66: =100%/5 -> 0.2 | P66: =100%/5 -> 0.2 | Q66: =100%/5 -> 0.2 | AT66: =+$F66*G66 -> 0 | AU66: =+$F66*H66 -> 0 | AV66: =+$F66*I66 -> 0 | AW66: =+$F66*J66 -> 0 | AX66: =+$F66*K66 -> 0 | AY66: =+$F66*L66 -> 0 | AZ66: =+$F66*M66 -> 0 | BA66: =+$F66*N66 -> 0 | ... BR66: =+$F66*AE66 -> 0 | CH66: =F66-SUM(AT66:CG66) -> 0
C67: Chi phí khác | F67: =SUM($F$62:$F$64)*E67 -> 0 | M67: =100%/5 -> 0.2 | N67: =100%/5 -> 0.2 | O67: =100%/5 -> 0.2 | P67: =100%/5 -> 0.2 | Q67: =100%/5 -> 0.2 | AT67: =+$F67*G67 -> 0 | AU67: =+$F67*H67 -> 0 | AV67: =+$F67*I67 -> 0 | AW67: =+$F67*J67 -> 0 | AX67: =+$F67*K67 -> 0 | AY67: =+$F67*L67 -> 0 | AZ67: =+$F67*M67 -> 0 | BA67: =+$F67*N67 -> 0 | ... BR67: =+$F67*AE67 -> 0 | CH67: =F67-SUM(AT67:CG67) -> 0
C68: Chi phí phát triển dự án | F68: =SUM($F$62:$F$64)*E68 -> 0 | M68: =100%/5 -> 0.2 | N68: =100%/5 -> 0.2 | O68: =100%/5 -> 0.2 | P68: =100%/5 -> 0.2 | Q68: =100%/5 -> 0.2 | AT68: =+$F68*G68 -> 0 | AU68: =+$F68*H68 -> 0 | AV68: =+$F68*I68 -> 0 | AW68: =+$F68*J68 -> 0 | AX68: =+$F68*K68 -> 0 | AY68: =+$F68*L68 -> 0 | AZ68: =+$F68*M68 -> 0 | BA68: =+$F68*N68 -> 0 | ... BR68: =+$F68*AE68 -> 0 | CH68: =F68-SUM(AT68:CG68) -> 0
C69: Chi phí dự phòng | E69: 0.07 | F69: =SUM($F$62:$F$65)*E69 -> 12728.116 | H69: =+H62 -> 0 | I69: =+I62 -> 0 | J69: =+J62 -> 0 | K69: =+K62 -> 0 | L69: =+L62 -> 0 | M69: =+M62 -> 0 | N69: =+N62 -> 0 | O69: =+O62 -> 0 | ... AR69: =+AR62 -> 0 | AT69: =+$F69*G69 -> 0 | AU69: =+$F69*H69 -> 0 | AV69: =+$F69*I69 -> 0 | AW69: =+$F69*J69 -> 0 | AX69: =+$F69*K69 -> 0 | AY69: =+$F69*L69 -> 0 | AZ69: =+$F69*M69 -> 0 | BA69: =+$F69*N69 -> 0 | ... BR69: =+$F69*AE69 -> 0 | CH69: =F69-SUM(AT69:CG69) -> 0
B70: 2.3 | C70: Công trình công cộng
C71: =+'2.Tien do'!C75 -> 0 | D71: =+'1. thong tin quy hoach'!I44 -> 0
C72: =+'2.Tien do'!C76 -> 0 | D72: =+'1. thong tin quy hoach'!I45 -> 0
C73: =+'2.Tien do'!C77 -> 0 | D73: =+'1. thong tin quy hoach'!I46 -> 0
C74: TMDV-2
C75: Chi phí dự phòng
B77: TỔNG DỰ TOÁN XÂY DỰNG | F77: =SUM(F10,F16) -> 3496025.1 | AT77: =SUM(AT10,AT16) -> 0 | AU77: =SUM(AU10,AU16) -> 0 | AV77: =SUM(AV10,AV16) -> 156000 | AW77: =SUM(AW10,AW16) -> 364000 | AX77: =SUM(AX10,AX16) -> 4263.4453 | AY77: =SUM(AY10,AY16) -> 4263.4453 | AZ77: =SUM(AZ10,AZ16) -> 489001.39 | BA77: =SUM(BA10,BA16) -> 9956.0978 | ... CE77: =SUM(CE10,CE16) -> 0 | CH77: =F77-SUM(AT77:CG77) -> 0
B78: III. LÃI VAY VỐN HÓA | F78: =SUM(AT78:BQ78) -> 108747.29 | AU78: ='6.Vay von'!F49 -> 0 | AV78: ='6.Vay von'!G49 -> 0 | AW78: ='6.Vay von'!H49 -> 0 | AX78: ='6.Vay von'!I49 -> 0 | AY78: ='6.Vay von'!J49 -> 0 | AZ78: ='6.Vay von'!K49 -> 0 | BA78: ='6.Vay von'!L49 -> 10179.497 | BB78: ='6.Vay von'!M49 -> 10209.51 | ... BR78: ='6.Vay von'!AC49 -> 0
B79: TỔNG CỘNG | F79: =F10+F16+F78 -> 3604772.4 | AT79: =AT10+AT16+AT78 -> 0 | AU79: =AU10+AU16+AU78 -> 0 | AV79: =AV10+AV16+AV78 -> 156000 | AW79: =AW10+AW16+AW78 -> 364000 | AX79: =AX10+AX16+AX78 -> 4263.4453 | AY79: =AY10+AY16+AY78 -> 4263.4453 | AZ79: =AZ10+AZ16+AZ78 -> 489001.39 | BA79: =BA10+BA16+BA78 -> 20135.595 | ... CE79: =CE10+CE16+CE78 -> 0
B87: STT | C87: HẠNG MỤC | D87: GIÁ TRỊ (TR.Đ) | E87: =AU8 -> 2026 | F87: =AV8 -> 2026 | G87: =AX8 -> 2026 | H87: =AY8 -> 2027 | I87: =AZ8 -> 2027 | J87: =BA8 -> 2027 | K87: =BB8 -> 2027 | L87: =BC8 -> 2028 | M87: =BD8 -> 2028 | N87: =BE8 -> 2028 | ... AA87: =BR8 -> 2031
E88: =AU9 -> Q1 | F88: =AV9 -> Q2 | G88: =AX9 -> Q4 | H88: =AY9 -> Q1 | I88: =AZ9 -> Q2 | J88: =BA9 -> Q3 | K88: =BB9 -> Q4 | L88: =BC9 -> Q1 | M88: =BD9 -> Q2 | N88: =BE9 -> Q3 | ... AA88: =BR9 -> Q4
B89: 1 | C89: Dòng chi | D89: =SUM(E89:AD89) -> #REF! | E89: =SUM(E90,E93:E98) -> #REF! | F89: =SUM(F90,F93:F98) -> #REF! | G89: =SUM(G90,G93:G98) -> #REF! | H89: =SUM(H90,H93:H98) -> #REF! | I89: =SUM(I90,I93:I98) -> #REF! | J89: =SUM(J90,J93:J98) -> #REF! | K89: =SUM(K90,K93:K98) -> #REF! | L89: =SUM(L90,L93:L98) -> #REF! | ... Y89: =SUM(Y90,Y93:Y98) -> #REF!
B90: 1.1 | C90: Chi phí đất | D90: =SUM(E90:AD90) -> 726006.85 | E90: =SUM(E91:E92) -> 0 | F90: =SUM(F91:F92) -> 156000 | G90: =SUM(G91:G92) -> 4263.4453 | H90: =SUM(H91:H92) -> 4263.4453 | I90: =SUM(I91:I92) -> 489001.39 | J90: =SUM(J91:J92) -> 8526.8906 | K90: =SUM(K91:K92) -> 0 | L90: =SUM(L91:L92) -> 0 | ... Y90: =SUM(Y91:Y92) -> 0
C91: Chi phí nhận chuyển nhượng | D91: =SUM(E91:AD91) -> 640737.94 | E91: =AU11 -> 0 | F91: =AV11 -> 156000 | G91: =AX11 -> 0 | H91: =AY11 -> 0 | I91: =AZ11 -> 484737.94 | J91: =BA11 -> 0 | K91: =BB11 -> 0 | L91: =BC11 -> 0 | M91: =BD11 -> 0 | N91: =BE11 -> 0 | ... Y91: =BP11 -> 0
C92: Pháp lý | D92: =SUM(E92:AD92) -> 85268.906 | E92: =AU15 -> 0 | F92: =AV15 -> 0 | G92: =AX15 -> 4263.4453 | H92: =AY15 -> 4263.4453 | I92: =AZ15 -> 4263.4453 | J92: =BA15 -> 8526.8906 | K92: =BB15 -> 0 | L92: =BC15 -> 0 | M92: =BD15 -> 17053.781 | N92: =BE15 -> 0 | ... Y92: =BP15 -> 0
B93: 1.2 | C93: Chi phí xây dựng | D93: =SUM(E93:AD93) -> 2406018.3 | E93: =AU16 -> 0 | F93: =AV16 -> 0 | G93: =AX16 -> 0 | H93: =AY16 -> 0 | I93: =AZ16 -> 0 | J93: =BA16 -> 1429.2072 | K93: =BB16 -> 49227.63 | L93: =BC16 -> 268023.99 | M93: =BD16 -> 243806.39 | N93: =BE16 -> 160213.03 | ... Y93: =BP16 -> 0
B94: 1.3 | C94: Chi phí bán hàng, Phí bảo lãnh NH | D94: =SUM(E94:AD94) -> 957037.72 | E94: ='4.Chi phi hoat dong'!G10+'4.Chi phi hoat dong'!G16+'4.Chi phi hoat dong'!G20 -> 0 | F94: ='4.Chi phi hoat dong'!H10+'4.Chi phi hoat dong'!H16+'4.Chi phi hoat dong'!H20 -> 0 | G94: ='4.Chi phi hoat dong'!J10+'4.Chi phi hoat dong'!J16+'4.Chi phi hoat dong'!J20 -> 0 | H94: ='4.Chi phi hoat dong'!K10+'4.Chi phi hoat dong'!K16+'4.Chi phi hoat dong'!K20 -> 0 | I94: ='4.Chi phi hoat dong'!L10+'4.Chi phi hoat dong'!L16+'4.Chi phi hoat dong'!L20 -> 0 | J94: ='4.Chi phi hoat dong'!M10+'4.Chi phi hoat dong'!M16+'4.Chi phi hoat dong'!M20 -> 0 | K94: ='4.Chi phi hoat dong'!N10+'4.Chi phi hoat dong'!N16+'4.Chi phi hoat dong'!N20 -> 0 | L94: ='4.Chi phi hoat dong'!O10+'4.Chi phi hoat dong'!O16+'4.Chi phi hoat dong'!O20 -> 0 | M94: ='4.Chi phi hoat dong'!P10+'4.Chi phi hoat dong'!P16+'4.Chi phi hoat dong'!P20 -> 291666.79 | N94: ='4.Chi phi hoat dong'!Q10+'4.Chi phi hoat dong'!Q16+'4.Chi phi hoat dong'!Q20 -> 328224.46 | ... Y94: ='4.Chi phi hoat dong'!AB10+'4.Chi phi hoat dong'!AB16+'4.Chi phi hoat dong'!AB20 -> 0
B95: 1.4 | C95: Chi phí vận hành | D95: =SUM(E95:AD95) -> #REF! | E95: ='4.Chi phi hoat dong'!#REF!+'4.Chi phi hoat dong'!G18 -> #REF! | F95: ='4.Chi phi hoat dong'!#REF!+'4.Chi phi hoat dong'!H18 -> #REF! | G95: ='4.Chi phi hoat dong'!#REF!+'4.Chi phi hoat dong'!J18 -> #REF! | H95: ='4.Chi phi hoat dong'!#REF!+'4.Chi phi hoat dong'!K18 -> #REF! | I95: ='4.Chi phi hoat dong'!#REF!+'4.Chi phi hoat dong'!L18 -> #REF! | J95: ='4.Chi phi hoat dong'!#REF!+'4.Chi phi hoat dong'!M18 -> #REF! | K95: ='4.Chi phi hoat dong'!#REF!+'4.Chi phi hoat dong'!N18 -> #REF! | L95: ='4.Chi phi hoat dong'!#REF!+'4.Chi phi hoat dong'!O18 -> #REF! | M95: ='4.Chi phi hoat dong'!#REF!+'4.Chi phi hoat dong'!P18 -> #REF! | N95: ='4.Chi phi hoat dong'!#REF!+'4.Chi phi hoat dong'!Q18 -> #REF! | ... Y95: ='4.Chi phi hoat dong'!#REF!+'4.Chi phi hoat dong'!AB18 -> #REF!
B96: 1.5 | C96: VAT | D96: =SUM(E96:AD96) -> 129826.61 | E96: ='4.Chi phi hoat dong'!G21 -> 0 | F96: ='4.Chi phi hoat dong'!H21 -> 0 | G96: ='4.Chi phi hoat dong'!J21 -> 0 | H96: ='4.Chi phi hoat dong'!K21 -> 0 | I96: ='4.Chi phi hoat dong'!L21 -> 1.0748574e-12 | J96: ='4.Chi phi hoat dong'!M21 -> 0 | K96: ='4.Chi phi hoat dong'!N21 -> 0 | L96: ='4.Chi phi hoat dong'!O21 -> 0 | M96: ='4.Chi phi hoat dong'!P21 -> 0 | N96: ='4.Chi phi hoat dong'!Q21 -> 0 | ... Y96: ='4.Chi phi hoat dong'!AB21 -> 0
B97: 1.6 | C97: Thuế TNDN | D97: =SUM(E97:AD97) -> 107451.01 | E97: ='7.CF'!F33 -> 0 | F97: ='7.CF'!G33 -> 0 | G97: ='7.CF'!I33 -> 0 | H97: ='7.CF'!J33 -> 0 | I97: ='7.CF'!K33 -> 0 | J97: ='7.CF'!L33 -> 0 | K97: ='7.CF'!M33 -> 0 | L97: ='7.CF'!N33 -> 0 | M97: ='7.CF'!O33 -> 5068.7928 | N97: ='7.CF'!P33 -> 5674.8328 | ... Y97: ='7.CF'!AA33 -> 0
B98: 1.7 | C98: Lãi vay | D98: =SUM(E98:AD98) -> 108747.29 | E98: ='6.Vay von'!F23 -> 0 | F98: ='6.Vay von'!G23 -> 0 | G98: ='6.Vay von'!I23 -> 0 | H98: ='6.Vay von'!J23 -> 0 | I98: ='6.Vay von'!K23 -> 0 | J98: ='6.Vay von'!L23 -> 10179.497 | K98: ='6.Vay von'!M23 -> 10209.51 | L98: ='6.Vay von'!N23 -> 11243.29 | M98: ='6.Vay von'!O23 -> 16871.794 | N98: ='6.Vay von'!P23 -> 18899.442 | ... Y98: ='6.Vay von'!AA23 -> 0
B99: 2 | C99: Dòng thu | D99: =SUM(E99:AD99) -> 4199620.8 | E99: =SUM(E100:E101) -> 0 | F99: =SUM(F100:F101) -> 0 | G99: =SUM(G100:G101) -> 0 | H99: =SUM(H100:H101) -> 0 | I99: =SUM(I100:I101) -> 0 | J99: =SUM(J100:J101) -> 0 | K99: =SUM(K100:K101) -> 472817.72 | L99: =SUM(L100:L101) -> 475700.75 | ... Y99: =SUM(Y100:Y101) -> 0
C100: Thu từ bán hàng | D100: =SUM(E100:AD100) -> 4199620.8 | E100: ='5.Doanh thu'!H15 -> 0 | F100: ='5.Doanh thu'!I15 -> 0 | G100: ='5.Doanh thu'!M15 -> 0 | H100: ='5.Doanh thu'!N15 -> 0 | I100: ='5.Doanh thu'!O15 -> 0 | J100: ='5.Doanh thu'!P15 -> 0 | K100: ='5.Doanh thu'!Q15 -> 472817.72 | L100: ='5.Doanh thu'!R15 -> 475700.75 | M100: ='5.Doanh thu'!S15 -> 125988.62 | N100: ='5.Doanh thu'!T15 -> 442161.45 | ... Y100: ='5.Doanh thu'!AE15 -> 0
C101: Thu từ khai thác cho thuê | D101: =SUM(E101:AD101) -> 0 | E101: ='5.Doanh thu'!H79 -> 0 | F101: ='5.Doanh thu'!I79 -> 0 | G101: ='5.Doanh thu'!M79 -> 0 | H101: ='5.Doanh thu'!N79 -> 0 | I101: ='5.Doanh thu'!O79 -> 0 | J101: ='5.Doanh thu'!P79 -> 0 | K101: ='5.Doanh thu'!Q79 -> 0 | L101: ='5.Doanh thu'!R79 -> 0 | M101: ='5.Doanh thu'!S79 -> 0 | N101: ='5.Doanh thu'!T79 -> 0 | ... Y101: ='5.Doanh thu'!AE79 -> 0
B102: 3 | C102: Dòng tiền ròng | D102: =SUM(E102:AD102) -> #REF! | E102: =E99-E89 -> #REF! | F102: =F99-F89 -> #REF! | G102: =G99-G89 -> #REF! | H102: =H99-H89 -> #REF! | I102: =I99-I89 -> #REF! | J102: =J99-J89 -> #REF! | K102: =K99-K89 -> #REF! | L102: =L99-L89 -> #REF! | ... Y102: =Y99-Y89 -> #REF!
C103: Vay | D103: =SUM(E103:AD103) -> 655683.49 | E103: ='6.Vay von'!F18 -> 0 | F103: ='6.Vay von'!G18 -> 0 | G103: ='6.Vay von'!I18 -> 0 | H103: ='6.Vay von'!J18 -> 0 | I103: ='6.Vay von'!K18 -> 339316.56 | J103: ='6.Vay von'!L18 -> 1000.445 | K103: ='6.Vay von'!M18 -> 34459.341 | L103: ='6.Vay von'!N18 -> 187616.79 | M103: ='6.Vay von'!O18 -> 67588.261 | N103: ='6.Vay von'!P18 -> 0 | ... Y103: ='6.Vay von'!AA18 -> 0
C104: Kế hoạch trả nợ ngân hàng | D104: =SUM(E104:AD104) -> 655683.49 | E104: ='6.Vay von'!F21 -> 0 | F104: ='6.Vay von'!G21 -> 0 | G104: ='6.Vay von'!I21 -> 0 | H104: ='6.Vay von'!J21 -> 0 | I104: ='6.Vay von'!K21 -> 0 | J104: ='6.Vay von'!L21 -> 0 | K104: ='6.Vay von'!M21 -> 0 | L104: ='6.Vay von'!N21 -> 0 | M104: ='6.Vay von'!O21 -> 0 | N104: ='6.Vay von'!P21 -> 54471.517 | ... Y104: ='6.Vay von'!AA21 -> 0
C105: VCSH | D105: =SUM(E105:AD105) -> 449975.15 | E105: ='6.Vay von'!F17 -> 0 | F105: ='6.Vay von'!G17 -> 156000 | G105: ='6.Vay von'!I17 -> 4263.4453 | H105: ='6.Vay von'!J17 -> 4263.4453 | I105: ='6.Vay von'!K17 -> 149684.83 | J105: ='6.Vay von'!L17 -> 19135.149 | K105: ='6.Vay von'!M17 -> 24977.799 | L105: ='6.Vay von'!N17 -> 91650.488 | M105: ='6.Vay von'!O17 -> 0 | N105: ='6.Vay von'!P17 -> 0 | ... Y105: ='6.Vay von'!AA17 -> 0
C106: Lũy kế dòng tiền | F106: =E106+F102 -> #REF! | G106: =#REF!+G102 -> #REF! | H106: =G106+H102 -> #REF! | I106: =H106+I102 -> #REF! | J106: =I106+J102 -> #REF! | K106: =J106+K102 -> #REF! | L106: =K106+L102 -> #REF! | M106: =L106+M102 -> #REF! | N106: =M106+N102 -> #REF! | O106: =N106+O102 -> #REF! | ... Y106: =X106+Y102 -> #REF!

Sheet 5.Doanh thu
C2: =+Summary!B2 -> Dự án Trần Đức 1
C3: Prepared by:
C5: DOANH THU DỰ KIẾN
B7: STT | C7: Hạng mục | D7: ĐVT | E7: Tổng | F7: PA2: Bỏ khối văn phòng | G7: GIÁ TRỊ | H7: ='2.Tien do'!E7 -> 2026 | I7: ='2.Tien do'!F7 -> 2026 | J7: ='2.Tien do'!G7 -> 2026 | K7: ='2.Tien do'!H7 -> 2026 | L7: ='2.Tien do'!I7 -> 2027 | M7: ='2.Tien do'!J7 -> 2027 | N7: ='2.Tien do'!K7 -> 2027 | O7: ='2.Tien do'!L7 -> 2027 | ... AQ7: ='2.Tien do'!AN7 -> 2034 | AR7: =AQ7+1 -> 2035 | AS7: =AR7+1 -> 2036 | AT7: =AS7+1 -> 2037 | AU7: =AT7+1 -> 2038 | AV7: =AU7+1 -> 2039 | AW7: =AV7+1 -> 2040 | AX7: =AW7+1 -> 2041 | AY7: =AX7+1 -> 2042 | ... CJ7: =CI7+1 -> 2079 | CK7: end
H8: ='2.Tien do'!E8 -> Q1 | I8: ='2.Tien do'!F8 -> Q2 | J8: ='2.Tien do'!G8 -> Q3 | K8: ='2.Tien do'!H8 -> Q4 | L8: ='2.Tien do'!I8 -> Q1 | M8: ='2.Tien do'!J8 -> Q2 | N8: ='2.Tien do'!K8 -> Q3 | O8: ='2.Tien do'!L8 -> Q4 | ... AQ8: ='2.Tien do'!AN8 -> Q4 | CK8: end
H9: 3 | I9: 3 | J9: 3 | K9: 3 | L9: 3 | M9: 3 | N9: 3 | O9: 3 | P9: 3 | Q9: 3 | R9: 3 | S9: 3 | T9: 3 | U9: 3 | V9: 3 | W9: 3 | X9: 3 | Y9: 3 | Z9: 3 | AA9: 3 | AB9: 3 | AC9: 3 | AD9: 3 | AE9: 3 | AF9: 3 | AG9: 3 | AH9: 3 | AI9: 3 | AJ9: 3 | AK9: 3 | AL9: 3 | AM9: 3 | AN9: 3 | AO9: 3 | AP9: 3 | AQ9: 3 | AR9: 12 | AS9: 12 | AT9: 12 | AU9: 12 | AV9: 12 | AW9: 12 | AX9: 12 | AY9: 12 | AZ9: 12 | BA9: 12 | BB9: 12 | BC9: 12 | BD9: 12 | BE9: 12 | BF9: 12 | BG9: 12 | BH9: 12 | BI9: 12 | BJ9: 12 | BK9: 12 | BL9: 12 | BM9: 12 | BN9: 12 | BO9: 12 | BP9: 12 | BQ9: 12 | BR9: 12 | BS9: 12 | BT9: 12 | BU9: 12 | BV9: 12 | BW9: 12 | BX9: 12 | BY9: 12 | BZ9: 12 | CA9: 12 | CB9: 12 | CC9: 12 | CD9: 12 | CE9: 12 | CF9: 12 | CG9: 12 | CH9: 12 | CI9: 12 | CJ9: 12 | CK9: end
B10: 1 | C10: =+'2.Tien do'!C65 -> Căn hộ khối tháp | CK10: end
C11: Tỷ lệ kinh doanh | H11: ='2.Tien do'!E65 -> 0 | I11: ='2.Tien do'!F65 -> 0 | J11: ='2.Tien do'!G65 -> 0 | K11: ='2.Tien do'!H65 -> 0 | L11: ='2.Tien do'!I65 -> 0 | M11: ='2.Tien do'!J65 -> 0 | N11: ='2.Tien do'!K65 -> 0 | O11: ='2.Tien do'!L65 -> 0 | ... CJ11: ='2.Tien do'!CG65 -> 0 | CK11: end
C12: Diện tích bán | D12: m² | E12: =+'1. thong tin quy hoach'!K13 -> 81145.098 | F12: 20610 | G12: =SUM(H12:AA12) -> 81145.098 | H12: =$E12*H11 -> 0 | I12: =$E12*I11 -> 0 | J12: =$E12*J11 -> 0 | K12: =$E12*K11 -> 0 | L12: =$E12*L11 -> 0 | M12: =$E12*M11 -> 0 | N12: =$E12*N11 -> 0 | O12: =$E12*O11 -> 0 | ... CJ12: =$E12*CJ11 -> 0 | CK12: end
C13: Giá bán (gồm VAT) | D13: trđ/m² | E13: =+'8.ĐO NHAY'!C8*(1+'8.ĐO NHAY'!$C$22)-'4.Chi phi hoat dong'!$E$54*('8.ĐO NHAY'!$C$22) -> 51.754461 | F13: 26 | H13: =IF(H12>0,$E13,0) -> 0 | I13: =IF(I12>0,$E13,0) -> 0 | J13: =IF(J12>0,$E13,0) -> 0 | K13: =IF(K12>0,$E13,0) -> 0 | L13: =IF(L12>0,$E13,0) -> 0 | M13: =IF(M12>0,$E13,0) -> 0 | N13: =IF(N12>0,$E13,0) -> 0 | O13: =IF(O12>0,$E13,0) -> 0 | ... CJ13: =IF(CJ12>0,$E13,0) -> 0 | CK13: end
C14: Doanh thu | D14: Tr.đ | E14: =E12*E13 -> 4199620.8 | F14: 535860 | G14: =SUM(H14:DL14) -> 4199620.8 | H14: =H12*H13 -> 0 | I14: =I12*I13 -> 0 | J14: =J12*J13 -> 0 | K14: =K12*K13 -> 0 | L14: =L12*L13 -> 0 | M14: =M12*M13 -> 0 | N14: =N12*N13 -> 0 | O14: =O12*O13 -> 0 | ... CJ14: =CJ12*CJ13 -> 0 | CK14: end
C15: Thực thu | D15: Tr.đ | G15: =SUM(H15:DL15) -> 4199620.8 | H15: 0 | I15: =SUM($H$121:H121)*I14+SUM($H$14:I14)*I121 -> 0 | J15: =SUM($H$121:I121)*J14+SUM($H$14:J14)*J121 -> 0 | K15: =SUM($H$121:J121)*K14+SUM($H$14:K14)*K121 -> 0 | L15: =SUM($H$121:K121)*L14+SUM($H$14:L14)*L121 -> 0 | M15: =SUM($H$121:L121)*M14+SUM($H$14:M14)*M121 -> 0 | N15: =SUM($H$121:M121)*N14+SUM($H$14:N14)*N121 -> 0 | O15: =SUM($H$121:N121)*O14+SUM($H$14:O14)*O121 -> 0 | P15: =SUM($H$121:O121)*P14+SUM($H$14:P14)*P121 -> 0 | ... AQ15: =SUM($H$121:AP121)*AQ14+SUM($H$14:AQ14)*AQ121 -> 0 | CK15: end
B16: 2 | C16: =+'2.Tien do'!C66 -> Căn hộ shop TM | CK16: end
C17: Tỷ lệ kinh doanh | D17: m² | H17: =+'2.Tien do'!E66 -> 0 | I17: =+'2.Tien do'!F66 -> 0 | J17: =+'2.Tien do'!G66 -> 0 | K17: =+'2.Tien do'!H66 -> 0 | L17: =+'2.Tien do'!I66 -> 0 | M17: =+'2.Tien do'!J66 -> 0 | N17: =+'2.Tien do'!K66 -> 0 | O17: =+'2.Tien do'!L66 -> 0 | ... CJ17: =+'2.Tien do'!CG66 -> 0 | CK17: end
C18: Diện tích kinh doanh | D18: trđ/m² | E18: =+'1. thong tin quy hoach'!K14 -> 2246.1743 | F18: 4031.2 | G18: =SUM(H18:AA18) -> 2246.1743 | H18: =$E18*H17 -> 0 | I18: =$E18*I17 -> 0 | J18: =$E18*J17 -> 0 | K18: =$E18*K17 -> 0 | L18: =$E18*L17 -> 0 | M18: =$E18*M17 -> 0 | N18: =$E18*N17 -> 0 | O18: =$E18*O17 -> 0 | ... CJ18: =$E18*CJ17 -> 0 | CK18: end
C19: Giá bán (gồm VAT) | D19: Tr.đ | E19: =+'8.ĐO NHAY'!C9*(1+'8.ĐO NHAY'!$C$22)-'4.Chi phi hoat dong'!$E$54*('8.ĐO NHAY'!$C$22) -> 54.504461 | F19: 60 | H19: =IF(H18>0,$E19,0) -> 0 | I19: =IF(I18>0,$E19,0) -> 0 | J19: =IF(J18>0,$E19,0) -> 0 | K19: =IF(K18>0,$E19,0) -> 0 | L19: =IF(L18>0,$E19,0) -> 0 | M19: =IF(M18>0,$E19,0) -> 0 | N19: =IF(N18>0,$E19,0) -> 0 | O19: =IF(O18>0,$E19,0) -> 0 | ... CJ19: =IF(CJ18>0,$E19,0) -> 0 | CK19: end
C20: Doanh thu | D20: Tr.đ | E20: =G20 -> 122426.52 | F20: 241872 | G20: =SUM(H20:XFD20) -> 122426.52 | H20: =H18*H19 -> 0 | I20: =I18*I19 -> 0 | J20: =J18*J19 -> 0 | K20: =K18*K19 -> 0 | L20: =L18*L19 -> 0 | M20: =M18*M19 -> 0 | N20: =N18*N19 -> 0 | O20: =O18*O19 -> 0 | ... CJ20: =CJ18*CJ19 -> 0 | CK20: end
C21: Thực thu | E21: =(G27+G21)/E18 -> 54.504461 | G21: =SUM(H21:XFD21) -> 122426.52 | H21: 0 | I21: =SUM($H$122:H122)*I20+SUM($H$20:I20)*I122 -> 0 | J21: =SUM($H$122:I122)*J20+SUM($H$20:J20)*J122 -> 0 | K21: =SUM($H$122:J122)*K20+SUM($H$20:K20)*K122 -> 0 | L21: =SUM($H$122:K122)*L20+SUM($H$20:L20)*L122 -> 0 | M21: =SUM($H$122:L122)*M20+SUM($H$20:M20)*M122 -> 0 | N21: =SUM($H$122:M122)*N20+SUM($H$20:N20)*N122 -> 0 | O21: =SUM($H$122:N122)*O20+SUM($H$20:O20)*O122 -> 0 | P21: =SUM($H$122:O122)*P20+SUM($H$20:P20)*P122 -> 0 | ... AQ21: =SUM($H$122:AP122)*AQ20+SUM($H$20:AQ20)*AQ122 -> 0 | CK21: end
B22: 3 | C22: =+'2.Tien do'!C67 -> Căn TMDV | CK22: end
C23: Tỷ lệ kinh doanh | D23: m² | H23: ='2.Tien do'!E67 -> 0 | I23: ='2.Tien do'!F67 -> 0 | J23: ='2.Tien do'!G67 -> 0 | K23: ='2.Tien do'!H67 -> 0 | L23: ='2.Tien do'!I67 -> 0 | M23: ='2.Tien do'!J67 -> 0 | N23: ='2.Tien do'!K67 -> 0 | O23: ='2.Tien do'!L67 -> 0 | ... CJ23: ='2.Tien do'!CG67 -> 0 | CK23: end
C24: Diện tích kinh doanh | D24: trđ/m² | E24: 0 | G24: =SUM(H24:AA24) -> 0 | H24: =$E24*H23 -> 0 | I24: =$E24*I23 -> 0 | J24: =$E24*J23 -> 0 | K24: =$E24*K23 -> 0 | L24: =$E24*L23 -> 0 | M24: =$E24*M23 -> 0 | N24: =$E24*N23 -> 0 | O24: =$E24*O23 -> 0 | ... CJ24: =$E24*CJ23 -> 0 | CK24: end
C25: Giá bán (gồm VAT) | D25: Tr.đ | E25: =+'8.ĐO NHAY'!C10*(1+'8.ĐO NHAY'!$C$22)-'4.Chi phi hoat dong'!$E$54*('8.ĐO NHAY'!$C$22) -> -0.49553918 | H25: =IF(H24>0,$E25,0) -> 0 | I25: =IF(I24>0,$E25,0) -> 0 | J25: =IF(J24>0,$E25,0) -> 0 | K25: =IF(K24>0,$E25,0) -> 0 | L25: =IF(L24>0,$E25,0) -> 0 | M25: =IF(M24>0,$E25,0) -> 0 | N25: =IF(N24>0,$E25,0) -> 0 | O25: =IF(O24>0,$E25,0) -> 0 | ... CJ25: =IF(CJ24>0,$E25,0) -> 0 | CK25: end
C26: Doanh thu | D26: Tr.đ | E26: =+G26 -> 0 | G26: =SUM(H26:XFD26) -> 0 | H26: =H24*H25 -> 0 | I26: =I24*I25 -> 0 | J26: =J24*J25 -> 0 | K26: =K24*K25 -> 0 | L26: =L24*L25 -> 0 | M26: =M24*M25 -> 0 | N26: =N24*N25 -> 0 | O26: =O24*O25 -> 0 | ... CJ26: =CJ24*CJ25 -> 0 | CK26: end
C27: Thực thu | G27: =SUM(H27:XFD27) -> 0 | H27: 0 | I27: =SUM($H$123:H123)*I26+SUM($H$26:I26)*I123 -> 0 | J27: =SUM($H$123:I123)*J26+SUM($H$26:J26)*J123 -> 0 | K27: =SUM($H$123:J123)*K26+SUM($H$26:K26)*K123 -> 0 | L27: =SUM($H$123:K123)*L26+SUM($H$26:L26)*L123 -> 0 | M27: =SUM($H$123:L123)*M26+SUM($H$26:M26)*M123 -> 0 | N27: =SUM($H$123:M123)*N26+SUM($H$26:N26)*N123 -> 0 | O27: =SUM($H$123:N123)*O26+SUM($H$26:O26)*O123 -> 0 | P27: =SUM($H$123:O123)*P26+SUM($H$26:P26)*P123 -> 0 | ... AQ27: =SUM($H$123:AP123)*AQ26+SUM($H$26:AQ26)*AQ123 -> 0 | CK27: end
B28: 4 | C28: =+'2.Tien do'!C68 -> Căn officetel | CK28: end
C29: Tỷ lệ kinh doanh | D29: m² | H29: =+'2.Tien do'!E68 -> 0 | I29: =+'2.Tien do'!F68 -> 0 | J29: =+'2.Tien do'!G68 -> 0 | K29: =+'2.Tien do'!H68 -> 0 | L29: =+'2.Tien do'!I68 -> 0 | M29: =+'2.Tien do'!J68 -> 0 | N29: =+'2.Tien do'!K68 -> 0 | O29: =+'2.Tien do'!L68 -> 0 | ... CJ29: =+'2.Tien do'!CG68 -> 0 | CK29: end
C30: Diện tích kinh doanh | D30: trđ/m² | E30: =+'1. thong tin quy hoach'!K15 -> 6156.4232 | G30: =SUM(H30:AA30) -> 6156.4232 | H30: =$E30*H29 -> 0 | I30: =$E30*I29 -> 0 | J30: =$E30*J29 -> 0 | K30: =$E30*K29 -> 0 | L30: =$E30*L29 -> 0 | M30: =$E30*M29 -> 0 | N30: =$E30*N29 -> 0 | O30: =$E30*O29 -> 0 | ... CJ30: =$E30*CJ29 -> 0 | CK30: end
C31: Giá bán | D31: Tr.đ | E31: =+'8.ĐO NHAY'!C11*(1+'8.ĐO NHAY'!$C$22)-'4.Chi phi hoat dong'!$E$54*('8.ĐO NHAY'!$C$22) -> 49.141961 | H31: =IF(H30>0,$E31,0) -> 0 | I31: =IF(I30>0,$E31,0) -> 0 | J31: =IF(J30>0,$E31,0) -> 0 | K31: =IF(K30>0,$E31,0) -> 0 | L31: =IF(L30>0,$E31,0) -> 0 | M31: =IF(M30>0,$E31,0) -> 0 | N31: =IF(N30>0,$E31,0) -> 0 | O31: =IF(O30>0,$E31,0) -> 0 | ... CJ31: =IF(CJ30>0,$E31,0) -> 0 | CK31: end
C32: Doanh thu | D32: Tr.đ | E32: =+G32 -> 302538.71 | G32: =SUM(H32:XFD32) -> 302538.71 | H32: =H30*H31 -> 0 | I32: =I30*I31 -> 0 | J32: =J30*J31 -> 0 | K32: =K30*K31 -> 0 | L32: =L30*L31 -> 0 | M32: =M30*M31 -> 0 | N32: =N30*N31 -> 0 | O32: =O30*O31 -> 0 | ... CJ32: =CJ30*CJ31 -> 0 | CK32: end
C33: Thực thu | G33: =SUM(H33:XFD33) -> 302538.71 | H33: 0 | I33: =SUM($H$124:H124)*I32+SUM($H$32:I32)*I124 -> 0 | J33: =SUM($H$124:I124)*J32+SUM($H$32:J32)*J124 -> 0 | K33: =SUM($H$124:J124)*K32+SUM($H$32:K32)*K124 -> 0 | L33: =SUM($H$124:K124)*L32+SUM($H$32:L32)*L124 -> 0 | M33: =SUM($H$124:L124)*M32+SUM($H$32:M32)*M124 -> 0 | N33: =SUM($H$124:M124)*N32+SUM($H$32:N32)*N124 -> 0 | O33: =SUM($H$124:N124)*O32+SUM($H$32:O32)*O124 -> 0 | P33: =SUM($H$124:O124)*P32+SUM($H$32:P32)*P124 -> 0 | ... AQ33: =SUM($H$124:AP124)*AQ32+SUM($H$32:AQ32)*AQ124 -> 0 | CK33: end
B34: 5 | C34: 0 | CK34: end
C35: Tỷ lệ kinh doanh | H35: =+'2.Tien do'!E69 -> 0 | I35: =+'2.Tien do'!F69 -> 0 | J35: =+'2.Tien do'!G69 -> 0 | K35: =+'2.Tien do'!H69 -> 0 | L35: =+'2.Tien do'!I69 -> 0 | M35: =+'2.Tien do'!J69 -> 0 | N35: =+'2.Tien do'!K69 -> 0 | O35: =+'2.Tien do'!L69 -> 0 | ... CJ35: =+'2.Tien do'!CG69 -> 0 | CK35: end
C36: Diện tích bán | D36: m² | E36: 0 | F36: 20610 | G36: =SUM(H36:AA36) -> 0 | H36: =$E36*H35 -> 0 | I36: =$E36*I35 -> 0 | J36: =$E36*J35 -> 0 | K36: =$E36*K35 -> 0 | L36: =$E36*L35 -> 0 | M36: =$E36*M35 -> 0 | N36: =$E36*N35 -> 0 | O36: =$E36*O35 -> 0 | ... CJ36: =$E36*CJ35 -> 0 | CK36: end
C37: Giá bán | D37: trđ/m² | E37: =+'8.ĐO NHAY'!C8 -> 47.5 | F37: 26 | H37: =IF(H36>0,$E37,0) -> 0 | I37: =IF(I36>0,$E37,0) -> 0 | J37: =IF(J36>0,$E37,0) -> 0 | K37: =IF(K36>0,$E37,0) -> 0 | L37: =IF(L36>0,$E37,0) -> 0 | M37: =IF(M36>0,$E37,0) -> 0 | N37: =IF(N36>0,$E37,0) -> 0 | O37: =IF(O36>0,$E37,0) -> 0 | ... CJ37: =IF(CJ36>0,$E37,0) -> 0 | CK37: end
C38: Doanh thu | D38: Tr.đ | E38: =E36*E37 -> 0 | F38: 535860 | G38: =SUM(H38:DL38) -> 0 | H38: =H36*H37 -> 0 | I38: =I36*I37 -> 0 | J38: =J36*J37 -> 0 | K38: =K36*K37 -> 0 | L38: =L36*L37 -> 0 | M38: =M36*M37 -> 0 | N38: =N36*N37 -> 0 | O38: =O36*O37 -> 0 | ... CJ38: =CJ36*CJ37 -> 0 | CK38: end
C39: Thực thu | D39: Tr.đ | G39: =SUM(H39:DL39) -> 0 | H39: 0 | I39: =SUM($H$125:H125)*I38+SUM($H$38:I38)*I125 -> 0 | J39: =SUM($H$125:I125)*J38+SUM($H$38:J38)*J125 -> 0 | K39: =SUM($H$125:J125)*K38+SUM($H$38:K38)*K125 -> 0 | L39: =SUM($H$125:K125)*L38+SUM($H$38:L38)*L125 -> 0 | M39: =SUM($H$125:L125)*M38+SUM($H$38:M38)*M125 -> 0 | N39: =SUM($H$125:M125)*N38+SUM($H$38:N38)*N125 -> 0 | O39: =SUM($H$125:N125)*O38+SUM($H$38:O38)*O125 -> 0 | P39: =SUM($H$125:O125)*P38+SUM($H$38:P38)*P125 -> 0 | ... AQ39: =SUM($H$125:AP125)*AQ38+SUM($H$38:AQ38)*AQ125 -> 0 | CK39: end
B40: 6 | C40: 0 | CK40: end
C41: Tỷ lệ kinh doanh | D41: m² | H41: =+'2.Tien do'!E70 -> 0 | I41: =+'2.Tien do'!F70 -> 0 | J41: =+'2.Tien do'!G70 -> 0 | K41: =+'2.Tien do'!H70 -> 0 | L41: =+'2.Tien do'!I70 -> 0 | M41: =+'2.Tien do'!J70 -> 0 | N41: =+'2.Tien do'!K70 -> 0 | O41: =+'2.Tien do'!L70 -> 0 | ... CJ41: =+'2.Tien do'!CG70 -> 0 | CK41: end
C42: Diện tích kinh doanh | D42: trđ/m² | E42: 0 | F42: 4031.2 | G42: =SUM(H42:AA42) -> 0 | H42: =$E42*H41 -> 0 | I42: =$E42*I41 -> 0 | J42: =$E42*J41 -> 0 | K42: =$E42*K41 -> 0 | L42: =$E42*L41 -> 0 | M42: =$E42*M41 -> 0 | N42: =$E42*N41 -> 0 | O42: =$E42*O41 -> 0 | ... CJ42: =$E42*CJ41 -> 0 | CK42: end
C43: Giá bán | D43: Tr.đ | E43: 80 | F43: 60 | H43: =IF(H42>0,$E43,0) -> 0 | I43: =IF(I42>0,$E43,0) -> 0 | J43: =IF(J42>0,$E43,0) -> 0 | K43: =IF(K42>0,$E43,0) -> 0 | L43: =IF(L42>0,$E43,0) -> 0 | M43: =IF(M42>0,$E43,0) -> 0 | N43: =IF(N42>0,$E43,0) -> 0 | O43: =IF(O42>0,$E43,0) -> 0 | ... CJ43: =IF(CJ42>0,$E43,0) -> 0 | CK43: end
C44: Doanh thu | D44: Tr.đ | E44: =G44 -> 0 | F44: 241872 | G44: =SUM(H44:XFD44) -> 0 | H44: =H42*H43 -> 0 | I44: =I42*I43 -> 0 | J44: =J42*J43 -> 0 | K44: =K42*K43 -> 0 | L44: =L42*L43 -> 0 | M44: =M42*M43 -> 0 | N44: =N42*N43 -> 0 | O44: =O42*O43 -> 0 | ... CJ44: =CJ42*CJ43 -> 0 | CK44: end
C45: Thực thu | G45: =SUM(H45:XFD45) -> 0 | H45: 0 | I45: =SUM($H$126:H126)*I44+SUM($H$44:I44)*I126 -> 0 | J45: =SUM($H$126:I126)*J44+SUM($H$44:J44)*J126 -> 0 | K45: =SUM($H$126:J126)*K44+SUM($H$44:K44)*K126 -> 0 | L45: =SUM($H$126:K126)*L44+SUM($H$44:L44)*L126 -> 0 | M45: =SUM($H$126:L126)*M44+SUM($H$44:M44)*M126 -> 0 | N45: =SUM($H$126:M126)*N44+SUM($H$44:N44)*N126 -> 0 | O45: =SUM($H$126:N126)*O44+SUM($H$44:O44)*O126 -> 0 | P45: =SUM($H$126:O126)*P44+SUM($H$44:P44)*P126 -> 0 | ... AQ45: =SUM($H$126:AP126)*AQ44+SUM($H$44:AQ44)*AQ126 -> 0 | CK45: end
B46: 7 | C46: 0 | CK46: end
C47: Tỷ lệ kinh doanh | D47: m² | H47: =+'2.Tien do'!E71 -> 0 | I47: =+'2.Tien do'!F71 -> 0 | J47: =+'2.Tien do'!G71 -> 0 | K47: =+'2.Tien do'!H71 -> 0 | L47: =+'2.Tien do'!I71 -> 0 | M47: =+'2.Tien do'!J71 -> 0 | N47: =+'2.Tien do'!K71 -> 0 | O47: =+'2.Tien do'!L71 -> 0 | ... CJ47: =+'2.Tien do'!CG71 -> 0 | CK47: end
C48: Diện tích kinh doanh | D48: trđ/m² | E48: 0 | F48: 4031.2 | G48: =SUM(H48:AA48) -> 0 | H48: =$E48*H47 -> 0 | I48: =$E48*I47 -> 0 | J48: =$E48*J47 -> 0 | K48: =$E48*K47 -> 0 | L48: =$E48*L47 -> 0 | M48: =$E48*M47 -> 0 | N48: =$E48*N47 -> 0 | O48: =$E48*O47 -> 0 | ... CJ48: =$E48*CJ47 -> 0 | CK48: end
C49: Giá bán | D49: Tr.đ | E49: =+'8.ĐO NHAY'!C11 -> 45.125 | F49: 60 | H49: =IF(H48>0,$E49,0) -> 0 | I49: =IF(I48>0,$E49,0) -> 0 | J49: =IF(J48>0,$E49,0) -> 0 | K49: =IF(K48>0,$E49,0) -> 0 | L49: =IF(L48>0,$E49,0) -> 0 | M49: =IF(M48>0,$E49,0) -> 0 | N49: =IF(N48>0,$E49,0) -> 0 | O49: =IF(O48>0,$E49,0) -> 0 | ... CJ49: =IF(CJ48>0,$E49,0) -> 0 | CK49: end
C50: Doanh thu | D50: Tr.đ | E50: =G50 -> 0 | F50: 241872 | G50: =SUM(H50:XFD50) -> 0 | H50: =H48*H49 -> 0 | I50: =I48*I49 -> 0 | J50: =J48*J49 -> 0 | K50: =K48*K49 -> 0 | L50: =L48*L49 -> 0 | M50: =M48*M49 -> 0 | N50: =N48*N49 -> 0 | O50: =O48*O49 -> 0 | ... CJ50: =CJ48*CJ49 -> 0 | CK50: end
C51: Thực thu | G51: =SUM(H51:XFD51) -> 0 | H51: 0 | I51: =SUM($H$127:H127)*I50+SUM($H$50:I50)*I127 -> 0 | J51: =SUM($H$127:I127)*J50+SUM($H$50:J50)*J127 -> 0 | K51: =SUM($H$127:J127)*K50+SUM($H$50:K50)*K127 -> 0 | L51: =SUM($H$127:K127)*L50+SUM($H$50:L50)*L127 -> 0 | M51: =SUM($H$127:L127)*M50+SUM($H$50:M50)*M127 -> 0 | N51: =SUM($H$127:M127)*N50+SUM($H$50:N50)*N127 -> 0 | O51: =SUM($H$127:N127)*O50+SUM($H$50:O50)*O127 -> 0 | P51: =SUM($H$127:O127)*P50+SUM($H$50:P50)*P127 -> 0 | ... AQ51: =SUM($H$127:AP127)*AQ50+SUM($H$50:AQ50)*AQ127 -> 0 | CK51: end
B52: 8 | C52: =+'2.Tien do'!C72 -> 0 | CK52: end
C53: Tỷ lệ kinh doanh | D53: m² | H53: ='2.Tien do'!E72 -> 0 | I53: ='2.Tien do'!F72 -> 0 | J53: ='2.Tien do'!G72 -> 0 | K53: ='2.Tien do'!H72 -> 0 | L53: ='2.Tien do'!I72 -> 0 | M53: ='2.Tien do'!J72 -> 0 | N53: ='2.Tien do'!K72 -> 0 | O53: ='2.Tien do'!L72 -> 0 | ... CJ53: ='2.Tien do'!CG72 -> 0 | CK53: end
C54: Diện tích kinh doanh | D54: trđ/m² | E54: =+'1. thong tin quy hoach'!J39 -> 0 | F54: 4031.2 | G54: =SUM(H54:AA54) -> 0 | H54: =$E54*H53 -> 0 | I54: =$E54*I53 -> 0 | J54: =$E54*J53 -> 0 | K54: =$E54*K53 -> 0 | L54: =$E54*L53 -> 0 | M54: =$E54*M53 -> 0 | N54: =$E54*N53 -> 0 | O54: =$E54*O53 -> 0 | ... CJ54: =$E54*CJ53 -> 0 | CK54: end
C55: Giá bán | D55: Tr.đ | E55: =+'8.ĐO NHAY'!C12 -> 80 | F55: 60 | H55: =IF(H54>0,$E55,0) -> 0 | I55: =IF(I54>0,$E55,0) -> 0 | J55: =IF(J54>0,$E55,0) -> 0 | K55: =IF(K54>0,$E55,0) -> 0 | L55: =IF(L54>0,$E55,0) -> 0 | M55: =IF(M54>0,$E55,0) -> 0 | N55: =IF(N54>0,$E55,0) -> 0 | O55: =IF(O54>0,$E55,0) -> 0 | ... CJ55: =IF(CJ54>0,$E55,0) -> 0 | CK55: end
C56: Doanh thu | D56: Tr.đ | E56: =G56 -> 0 | F56: 241872 | G56: =SUM(H56:XFD56) -> 0 | H56: =H54*H55 -> 0 | I56: =I54*I55 -> 0 | J56: =J54*J55 -> 0 | K56: =K54*K55 -> 0 | L56: =L54*L55 -> 0 | M56: =M54*M55 -> 0 | N56: =N54*N55 -> 0 | O56: =O54*O55 -> 0 | ... CJ56: =CJ54*CJ55 -> 0 | CK56: end
C57: Thực thu | G57: =SUM(H57:XFD57) -> 0 | H57: 0 | I57: =SUM($H$128:H128)*I56+SUM($H$56:I56)*I128 -> 0 | J57: =SUM($H$128:I128)*J56+SUM($H$56:J56)*J128 -> 0 | K57: =SUM($H$128:J128)*K56+SUM($H$56:K56)*K128 -> 0 | L57: =SUM($H$128:K128)*L56+SUM($H$56:L56)*L128 -> 0 | M57: =SUM($H$128:L128)*M56+SUM($H$56:M56)*M128 -> 0 | N57: =SUM($H$128:M128)*N56+SUM($H$56:N56)*N128 -> 0 | O57: =SUM($H$128:N128)*O56+SUM($H$56:O56)*O128 -> 0 | P57: =SUM($H$128:O128)*P56+SUM($H$56:P56)*P128 -> 0 | ... AQ57: =SUM($H$128:AP128)*AQ56+SUM($H$56:AQ56)*AQ128 -> 0 | CK57: end
B58: 9 | C58: =+'2.Tien do'!C73 -> 0 | CK58: end
C59: Tỷ lệ kinh doanh | D59: m² | H59: ='2.Tien do'!E73 -> 0 | I59: ='2.Tien do'!F73 -> 0 | J59: ='2.Tien do'!G73 -> 0 | K59: ='2.Tien do'!H73 -> 0 | L59: ='2.Tien do'!I73 -> 0 | M59: ='2.Tien do'!J73 -> 0 | N59: ='2.Tien do'!K73 -> 0 | O59: ='2.Tien do'!L73 -> 0 | ... CJ59: ='2.Tien do'!CG73 -> 0 | CK59: end
C60: Diện tích kinh doanh | D60: trđ/m² | E60: =+'1. thong tin quy hoach'!J40 -> 0 | F60: 4031.2 | G60: =SUM(H60:AA60) -> 0 | H60: =$E60*H59 -> 0 | I60: =$E60*I59 -> 0 | J60: =$E60*J59 -> 0 | K60: =$E60*K59 -> 0 | L60: =$E60*L59 -> 0 | M60: =$E60*M59 -> 0 | N60: =$E60*N59 -> 0 | O60: =$E60*O59 -> 0 | ... CJ60: =$E60*CJ59 -> 0 | CK60: end
C61: Giá bán | D61: Tr.đ | E61: =+'8.ĐO NHAY'!C13 -> 0 | F61: 60 | H61: =IF(H60>0,$E61,0) -> 0 | I61: =IF(I60>0,$E61,0) -> 0 | J61: =IF(J60>0,$E61,0) -> 0 | K61: =IF(K60>0,$E61,0) -> 0 | L61: =IF(L60>0,$E61,0) -> 0 | M61: =IF(M60>0,$E61,0) -> 0 | N61: =IF(N60>0,$E61,0) -> 0 | O61: =IF(O60>0,$E61,0) -> 0 | ... CJ61: =IF(CJ60>0,$E61,0) -> 0 | CK61: end
C62: Doanh thu | D62: Tr.đ | E62: =G62 -> 0 | F62: 241872 | G62: =SUM(H62:XFD62) -> 0 | H62: =H60*H61 -> 0 | I62: =I60*I61 -> 0 | J62: =J60*J61 -> 0 | K62: =K60*K61 -> 0 | L62: =L60*L61 -> 0 | M62: =M60*M61 -> 0 | N62: =N60*N61 -> 0 | O62: =O60*O61 -> 0 | ... CJ62: =CJ60*CJ61 -> 0 | CK62: end
C63: Thực thu | G63: =SUM(H63:XFD63) -> 0 | H63: 0 | I63: =SUM($H$129:H129)*I62+SUM($H$62:I62)*I129 -> 0 | J63: =SUM($H$129:I129)*J62+SUM($H$62:J62)*J129 -> 0 | K63: =SUM($H$129:J129)*K62+SUM($H$62:K62)*K129 -> 0 | L63: =SUM($H$129:K129)*L62+SUM($H$62:L62)*L129 -> 0 | M63: =SUM($H$129:L129)*M62+SUM($H$62:M62)*M129 -> 0 | N63: =SUM($H$129:M129)*N62+SUM($H$62:N62)*N129 -> 0 | O63: =SUM($H$129:N129)*O62+SUM($H$62:O62)*O129 -> 0 | P63: =SUM($H$129:O129)*P62+SUM($H$62:P62)*P129 -> 0 | ... AQ63: =SUM($H$129:AP129)*AQ62+SUM($H$62:AQ62)*AQ129 -> 0 | CK63: end
B64: 10 | C64: =+'2.Tien do'!C74 -> 0 | CK64: end
C65: Tỷ lệ kinh doanh | D65: m² | H65: ='2.Tien do'!E74 -> 0 | I65: ='2.Tien do'!F74 -> 0 | J65: ='2.Tien do'!G74 -> 0 | K65: ='2.Tien do'!H74 -> 0 | L65: ='2.Tien do'!I74 -> 0 | M65: ='2.Tien do'!J74 -> 0 | N65: ='2.Tien do'!K74 -> 0 | O65: ='2.Tien do'!L74 -> 0 | ... CJ65: ='2.Tien do'!CG74 -> 0 | CK65: end
C66: Diện tích kinh doanh | D66: trđ/m² | E66: =+'1. thong tin quy hoach'!J41 -> 0 | F66: 4031.2 | G66: =SUM(H66:AA66) -> 0 | H66: =$E66*H65 -> 0 | I66: =$E66*I65 -> 0 | J66: =$E66*J65 -> 0 | K66: =$E66*K65 -> 0 | L66: =$E66*L65 -> 0 | M66: =$E66*M65 -> 0 | N66: =$E66*N65 -> 0 | O66: =$E66*O65 -> 0 | ... CJ66: =$E66*CJ65 -> 0 | CK66: end
C67: Giá bán | D67: Tr.đ | E67: =+'8.ĐO NHAY'!C14 -> 0 | F67: 60 | H67: =IF(H66>0,$E67,0) -> 0 | I67: =IF(I66>0,$E67,0) -> 0 | J67: =IF(J66>0,$E67,0) -> 0 | K67: =IF(K66>0,$E67,0) -> 0 | L67: =IF(L66>0,$E67,0) -> 0 | M67: =IF(M66>0,$E67,0) -> 0 | N67: =IF(N66>0,$E67,0) -> 0 | O67: =IF(O66>0,$E67,0) -> 0 | ... CJ67: =IF(CJ66>0,$E67,0) -> 0 | CK67: end
C68: Doanh thu | D68: Tr.đ | E68: =G68 -> 0 | F68: 241872 | G68: =SUM(H68:XFD68) -> 0 | H68: =H66*H67 -> 0 | I68: =I66*I67 -> 0 | J68: =J66*J67 -> 0 | K68: =K66*K67 -> 0 | L68: =L66*L67 -> 0 | M68: =M66*M67 -> 0 | N68: =N66*N67 -> 0 | O68: =O66*O67 -> 0 | ... CJ68: =CJ66*CJ67 -> 0 | CK68: end
C69: Thực thu | G69: =SUM(H69:XFD69) -> 0 | H69: 0 | I69: =SUM($H$130:H130)*I68+SUM($H$68:I68)*I130 -> 0 | J69: =SUM($H$130:I130)*J68+SUM($H$68:J68)*J130 -> 0 | K69: =SUM($H$130:J130)*K68+SUM($H$68:K68)*K130 -> 0 | L69: =SUM($H$130:K130)*L68+SUM($H$68:L68)*L130 -> 0 | M69: =SUM($H$130:L130)*M68+SUM($H$68:M68)*M130 -> 0 | N69: =SUM($H$130:M130)*N68+SUM($H$68:N68)*N130 -> 0 | O69: =SUM($H$130:N130)*O68+SUM($H$68:O68)*O130 -> 0 | P69: =SUM($H$130:O130)*P68+SUM($H$68:P68)*P130 -> 0 | ... AQ69: =SUM($H$130:AP130)*AQ68+SUM($H$68:AQ68)*AQ130 -> 0 | CK69: end
CK70: end
C71: Thực thu lũy kế doanh thu bán hàng | H71: =SUM($H$15:H15,$H$21:H21,$H$27:H27,$H$33:H33,$H$39:H39,$H$45:H45,$H$51:H51,$H$57:H57,$H$63:H63,$H$69:H69) -> 0 | I71: =SUM($H$15:I15,$H$21:I21,$H$27:I27,$H$33:I33,$H$39:I39,$H$45:I45,$H$51:I51,$H$57:I57,$H$63:I63,$H$69:I69) -> 0 | J71: =SUM($H$15:J15,$H$21:J21,$H$27:J27,$H$33:J33,$H$39:J39,$H$45:J45,$H$51:J51,$H$57:J57,$H$63:J63,$H$69:J69) -> 0 | K71: =SUM($H$15:K15,$H$21:K21,$H$27:K27,$H$33:K33,$H$39:K39,$H$45:K45,$H$51:K51,$H$57:K57,$H$63:K63,$H$69:K69) -> 0 | L71: =SUM($H$15:L15,$H$21:L21,$H$27:L27,$H$33:L33,$H$39:L39,$H$45:L45,$H$51:L51,$H$57:L57,$H$63:L63,$H$69:L69) -> 0 | M71: =SUM($H$15:M15,$H$21:M21,$H$27:M27,$H$33:M33,$H$39:M39,$H$45:M45,$H$51:M51,$H$57:M57,$H$63:M63,$H$69:M69) -> 0 | N71: =SUM($H$15:N15,$H$21:N21,$H$27:N27,$H$33:N33,$H$39:N39,$H$45:N45,$H$51:N51,$H$57:N57,$H$63:N63,$H$69:N69) -> 0 | O71: =SUM($H$15:O15,$H$21:O21,$H$27:O27,$H$33:O33,$H$39:O39,$H$45:O45,$H$51:O51,$H$57:O57,$H$63:O63,$H$69:O69) -> 0 | ... CJ71: =SUM($H$15:CJ15,$H$21:CJ21,$H$27:CJ27,$H$33:CJ33,$H$39:CJ39,$H$45:CJ45,$H$51:CJ51,$H$57:CJ57,$H$63:CJ63,$H$69:CJ69) -> 4624586 | CK71: end
C72: Chi phí bảo lãnh ngân hàng dự kiến | D72: 1.5%/năm | G72: =SUM(H72:AD72) -> 46994.827 | H72: =IF(H71>($E$14+$E$20+$E$26+$E$32+$E$38+$E$44+$E$50+$E$56+$E$62+$E$68)*0.7,0,H71*1.5%/4) -> 0 | I72: =IF(I71>($E$14+$E$20+$E$26+$E$32+$E$38+$E$44+$E$50+$E$56+$E$62+$E$68)*0.7,0,I71*1.5%/4) -> 0 | J72: =IF(J71>($E$14+$E$20+$E$26+$E$32+$E$38+$E$44+$E$50+$E$56+$E$62+$E$68)*0.7,0,J71*1.5%/4) -> 0 | K72: =IF(K71>($E$14+$E$20+$E$26+$E$32+$E$38+$E$44+$E$50+$E$56+$E$62+$E$68)*0.7,0,K71*1.5%/4) -> 0 | L72: =IF(L71>($E$14+$E$20+$E$26+$E$32+$E$38+$E$44+$E$50+$E$56+$E$62+$E$68)*0.7,0,L71*1.5%/4) -> 0 | M72: =IF(M71>($E$14+$E$20+$E$26+$E$32+$E$38+$E$44+$E$50+$E$56+$E$62+$E$68)*0.7,0,M71*1.5%/4) -> 0 | N72: =IF(N71>($E$14+$E$20+$E$26+$E$32+$E$38+$E$44+$E$50+$E$56+$E$62+$E$68)*0.7,0,N71*1.5%/4) -> 0 | O72: =IF(O71>($E$14+$E$20+$E$26+$E$32+$E$38+$E$44+$E$50+$E$56+$E$62+$E$68)*0.7,0,O71*1.5%/4) -> 0 | ... CJ72: =IF(CJ71>($E$14+$E$20+$E$26+$E$32+$E$38+$E$44+$E$50+$E$56+$E$62+$E$68)*0.7,0,CJ71*1.5%/4) -> 0 | CK72: end
CK73: end
B74: 11 | C74: =+'2.Tien do'!C75 -> 0 | CK74: end
C75: Tỷ lệ kinh doanh | D75: /3 năm | E75: 0.1 | F75: 0.05 | H75: ='2.Tien do'!E75 -> 0 | I75: ='2.Tien do'!F75 -> 0 | J75: ='2.Tien do'!G75 -> 0 | K75: ='2.Tien do'!H75 -> 0 | L75: ='2.Tien do'!I75 -> 0 | M75: ='2.Tien do'!J75 -> 0 | N75: ='2.Tien do'!K75 -> 0 | O75: ='2.Tien do'!L75 -> 0 | ... CJ75: ='2.Tien do'!CG75 -> 0 | CK75: end
C76: Diện tích kinh doanh | D76: m² | E76: =+'1. thong tin quy hoach'!D44 -> 0 | F76: 1966 | H76: =$E76*H75 -> 0 | I76: =$E76*I75 -> 0 | J76: =$E76*J75 -> 0 | K76: =$E76*K75 -> 0 | L76: =$E76*L75 -> 0 | M76: =$E76*M75 -> 0 | N76: =$E76*N75 -> 0 | O76: =$E76*O75 -> 0 | ... CJ76: =$E76*CJ75 -> 0 | CK76: end
C77: Giá bán quy đổi | D77: trđ/m² | E77: =+'8.ĐO NHAY'!J11*0.34 -> 0 | F77: 12 | H77: =IF(H76>0,$E77,0) -> 0 | I77: =IF(I76>0,$E77,0) -> 0 | J77: =IF(J76>0,$E77,0) -> 0 | K77: =IF(K76>0,$E77,0) -> 0 | L77: =IF(L76>0,$E77,0) -> 0 | M77: =IF(M76>0,$E77,0) -> 0 | N77: =IF(N76>0,$E77,0) -> 0 | O77: =IF(O76>0,$E77,0) -> 0 | ... CJ77: =IF(CJ76>0,$E77,0) -> 0 | CK77: end
C78: Doanh thu | D78: Tr.đ | E78: =G78 -> 0 | F78: 2548590.7 | G78: =SUM(H78:DL78) -> 0 | H78: =H77*H76 -> 0 | I78: =I77*I76 -> 0 | J78: =J77*J76 -> 0 | K78: =K77*K76 -> 0 | L78: =L77*L76 -> 0 | M78: =M77*M76 -> 0 | N78: =N77*N76 -> 0 | O78: =O77*O76 -> 0 | ... CJ78: =CJ77*CJ76 -> 0 | CK78: end
C79: Thực thu | D79: Tr.đ | G79: =SUM(H79:DL79) -> 0 | H79: 0 | I79: =SUM($H$131:H131)*I78+SUM($H$78:I78)*I131 -> 0 | J79: =SUM($H$131:I131)*J78+SUM($H$78:J78)*J131 -> 0 | K79: =SUM($H$131:J131)*K78+SUM($H$78:K78)*K131 -> 0 | L79: =SUM($H$131:K131)*L78+SUM($H$78:L78)*L131 -> 0 | M79: =SUM($H$131:L131)*M78+SUM($H$78:M78)*M131 -> 0 | N79: =SUM($H$131:M131)*N78+SUM($H$78:N78)*N131 -> 0 | O79: =SUM($H$131:N131)*O78+SUM($H$78:O78)*O131 -> 0 | P79: =SUM($H$131:O131)*P78+SUM($H$78:P78)*P131 -> 0 | ... CJ79: =SUM($H$131:CI131)*CJ78+SUM($H$78:CJ78)*CJ131 -> 0 | CK79: end
H80: =G79-G78 -> 0 | CK80: end
B81: 12 | C81: =+'2.Tien do'!C76 -> 0 | CK81: end
C82: Tỷ lệ kinh doanh | D82: /3 năm | E82: 0.1 | F82: 0.05 | H82: ='2.Tien do'!E76 -> 0 | I82: ='2.Tien do'!F76 -> 0 | J82: ='2.Tien do'!G76 -> 0 | K82: ='2.Tien do'!H76 -> 0 | L82: ='2.Tien do'!I76 -> 0 | M82: ='2.Tien do'!J76 -> 0 | N82: ='2.Tien do'!K76 -> 0 | O82: ='2.Tien do'!L76 -> 0 | ... CJ82: ='2.Tien do'!CG76 -> 0 | CK82: end
C83: Diện tích kinh doanh | D83: m² | E83: =+'1. thong tin quy hoach'!D45 -> 0 | F83: 1966 | H83: =$E83*H82 -> 0 | I83: =$E83*I82 -> 0 | J83: =$E83*J82 -> 0 | K83: =$E83*K82 -> 0 | L83: =$E83*L82 -> 0 | M83: =$E83*M82 -> 0 | N83: =$E83*N82 -> 0 | O83: =$E83*O82 -> 0 | ... CJ83: =$E83*CJ82 -> 0 | CK83: end
C84: Giá bán quy đổi | D84: trđ/m² | E84: =+E77 -> 0 | F84: 12 | H84: =IF(H83>0,$E84,0) -> 0 | I84: =IF(I83>0,$E84,0) -> 0 | J84: =IF(J83>0,$E84,0) -> 0 | K84: =IF(K83>0,$E84,0) -> 0 | L84: =IF(L83>0,$E84,0) -> 0 | M84: =IF(M83>0,$E84,0) -> 0 | N84: =IF(N83>0,$E84,0) -> 0 | O84: =IF(O83>0,$E84,0) -> 0 | ... CJ84: =IF(CJ83>0,$E84,0) -> 0 | CK84: end
C85: Doanh thu | D85: Tr.đ | E85: =G85 -> 0 | F85: 2548590.7 | G85: =SUM(H85:DL85) -> 0 | H85: =H84*H83 -> 0 | I85: =I84*I83 -> 0 | J85: =J84*J83 -> 0 | K85: =K84*K83 -> 0 | L85: =L84*L83 -> 0 | M85: =M84*M83 -> 0 | N85: =N84*N83 -> 0 | O85: =O84*O83 -> 0 | ... CJ85: =CJ84*CJ83 -> 0 | CK85: end
C86: Thực thu | D86: Tr.đ | G86: =SUM(H86:DL86) -> 0 | H86: 0 | I86: =SUM($H$132:H132)*I85+SUM($H$85:I85)*I132 -> 0 | J86: =SUM($H$132:I132)*J85+SUM($H$85:J85)*J132 -> 0 | K86: =SUM($H$132:J132)*K85+SUM($H$85:K85)*K132 -> 0 | L86: =SUM($H$132:K132)*L85+SUM($H$85:L85)*L132 -> 0 | M86: =SUM($H$132:L132)*M85+SUM($H$85:M85)*M132 -> 0 | N86: =SUM($H$132:M132)*N85+SUM($H$85:N85)*N132 -> 0 | O86: =SUM($H$132:N132)*O85+SUM($H$85:O85)*O132 -> 0 | P86: =SUM($H$132:O132)*P85+SUM($H$85:P85)*P132 -> 0 | ... CJ86: =SUM($H$132:CI132)*CJ85+SUM($H$85:CJ85)*CJ132 -> 0 | CK86: end
CK87: end
B88: 13 | C88: =+'2.Tien do'!C77 -> 0 | CK88: end
C89: Tỷ lệ kinh doanh | D89: /3 năm | E89: 0.1 | F89: 0.05 | H89: =+'2.Tien do'!E77 -> 0 | I89: =+'2.Tien do'!F77 -> 0 | J89: =+'2.Tien do'!G77 -> 0 | K89: =+'2.Tien do'!H77 -> 0 | L89: =+'2.Tien do'!I77 -> 0 | M89: =+'2.Tien do'!J77 -> 0 | N89: =+'2.Tien do'!K77 -> 0 | O89: =+'2.Tien do'!L77 -> 0 | ... CJ89: =+'2.Tien do'!CG77 -> 0 | CK89: end
C90: Diện tích kinh doanh | D90: m² | E90: =+'1. thong tin quy hoach'!D46 -> 0 | F90: 1966 | H90: =$E90*H89 -> 0 | I90: =$E90*I89 -> 0 | J90: =$E90*J89 -> 0 | K90: =$E90*K89 -> 0 | L90: =$E90*L89 -> 0 | M90: =$E90*M89 -> 0 | N90: =$E90*N89 -> 0 | O90: =$E90*O89 -> 0 | ... CJ90: =$E90*CJ89 -> 0 | CK90: end
C91: Giá bán quy đổi | D91: trđ/m² | E91: =+E77 -> 0 | F91: 12 | H91: =IF(H90>0,$E91,0) -> 0 | I91: =IF(I90>0,$E91,0) -> 0 | J91: =IF(J90>0,$E91,0) -> 0 | K91: =IF(K90>0,$E91,0) -> 0 | L91: =IF(L90>0,$E91,0) -> 0 | M91: =IF(M90>0,$E91,0) -> 0 | N91: =IF(N90>0,$E91,0) -> 0 | O91: =IF(O90>0,$E91,0) -> 0 | ... CJ91: =IF(CJ90>0,$E91,0) -> 0 | CK91: end
C92: Doanh thu | D92: Tr.đ | E92: =G92 -> 0 | F92: 2548590.7 | G92: =SUM(H92:DL92) -> 0 | H92: =H91*H90 -> 0 | I92: =I91*I90 -> 0 | J92: =J91*J90 -> 0 | K92: =K91*K90 -> 0 | L92: =L91*L90 -> 0 | M92: =M91*M90 -> 0 | N92: =N91*N90 -> 0 | O92: =O91*O90 -> 0 | ... CJ92: =CJ91*CJ90 -> 0 | CK92: end
C93: Thực thu | D93: Tr.đ | G93: =SUM(H93:DL93) -> 0 | H93: 0 | I93: =SUM($H$133:H133)*I92+SUM($H$92:I92)*I133 -> 0 | J93: =SUM($H$133:I133)*J92+SUM($H$92:J92)*J133 -> 0 | K93: =SUM($H$133:J133)*K92+SUM($H$92:K92)*K133 -> 0 | L93: =SUM($H$133:K133)*L92+SUM($H$92:L92)*L133 -> 0 | M93: =SUM($H$133:L133)*M92+SUM($H$92:M92)*M133 -> 0 | N93: =SUM($H$133:M133)*N92+SUM($H$92:N92)*N133 -> 0 | O93: =SUM($H$133:N133)*O92+SUM($H$92:O92)*O133 -> 0 | P93: =SUM($H$133:O133)*P92+SUM($H$92:P92)*P133 -> 0 | ... CJ93: =SUM($H$133:CI133)*CJ92+SUM($H$92:CJ92)*CJ133 -> 0 | CK93: end
CK94: end
B95: 14 | C95: =+'2.Tien do'!C71 -> Nhà phố liên kế | CK95: end
C96: Tỷ lệ kinh doanh | D96: /3 năm | E96: 0.1 | F96: 0.05 | H96: ='2.Tien do'!E71 -> 0 | I96: ='2.Tien do'!F71 -> 0 | J96: ='2.Tien do'!G71 -> 0 | K96: ='2.Tien do'!H71 -> 0 | L96: ='2.Tien do'!I71 -> 0 | M96: ='2.Tien do'!J71 -> 0 | N96: ='2.Tien do'!K71 -> 0 | O96: ='2.Tien do'!L71 -> 0 | ... CJ96: ='2.Tien do'!CG71 -> 0 | CK96: end
C97: Diện tích kinh doanh | D97: m² | E97: =+'1. thong tin quy hoach'!J38 -> 6572.61 | F97: 1966 | H97: =$E97*H96 -> 0 | I97: =$E97*I96 -> 0 | J97: =$E97*J96 -> 0 | K97: =$E97*K96 -> 0 | L97: =$E97*L96 -> 0 | M97: =$E97*M96 -> 0 | N97: =$E97*N96 -> 0 | O97: =$E97*O96 -> 0 | ... CJ97: =$E97*CJ96 -> 0 | CK97: end
C98: Giá bán quy đổi | D98: trđ/m² | E98: =+'8.ĐO NHAY'!C12*(1+'8.ĐO NHAY'!$C$22)-'4.Chi phi hoat dong'!$E$54*('8.ĐO NHAY'!$C$22) -> 87.504461 | F98: 12 | H98: =IF(H97>0,$E98,0) -> 0 | I98: =IF(I97>0,$E98,0) -> 0 | J98: =IF(J97>0,$E98,0) -> 0 | K98: =IF(K97>0,$E98,0) -> 0 | L98: =IF(L97>0,$E98,0) -> 0 | M98: =IF(M97>0,$E98,0) -> 0 | N98: =IF(N97>0,$E98,0) -> 0 | O98: =IF(O97>0,$E98,0) -> 0 | ... CJ98: =IF(CJ97>0,$E98,0) -> 0 | CK98: end
C99: Doanh thu | D99: Tr.đ | E99: =G99 -> 575132.69 | F99: 2548590.7 | G99: =SUM(H99:DL99) -> 575132.69 | H99: =H98*H97 -> 0 | I99: =I98*I97 -> 0 | J99: =J98*J97 -> 0 | K99: =K98*K97 -> 0 | L99: =L98*L97 -> 0 | M99: =M98*M97 -> 0 | N99: =N98*N97 -> 0 | O99: =O98*O97 -> 0 | ... CJ99: =CJ98*CJ97 -> 0 | CK99: end
C100: Thực thu | D100: Tr.đ | G100: =SUM(H100:DL100) -> 575132.69 | H100: 0 | I100: =SUM($H$127:H127)*I99+SUM($H$99:I99)*I127 -> 0 | J100: =SUM($H$127:I127)*J99+SUM($H$99:J99)*J127 -> 0 | K100: =SUM($H$127:J127)*K99+SUM($H$99:K99)*K127 -> 0 | L100: =SUM($H$127:K127)*L99+SUM($H$99:L99)*L127 -> 0 | M100: =SUM($H$127:L127)*M99+SUM($H$99:M99)*M127 -> 0 | N100: =SUM($H$127:M127)*N99+SUM($H$99:N99)*N127 -> 0 | O100: =SUM($H$127:N127)*O99+SUM($H$99:O99)*O127 -> 0 | P100: =SUM($H$127:O127)*P99+SUM($H$99:P99)*P127 -> 0 | ... CJ100: =SUM($H$127:CI127)*CJ99+SUM($H$99:CJ99)*CJ127 -> 0 | CK100: end
CK101: end
B102: 15 | C102: =+'2.Tien do'!C69 -> TMDV tập trung | CK102: end
C103: Tỷ lệ kinh doanh | D103: /3 năm | E103: 0.1 | F103: 0.05 | H103: ='2.Tien do'!E69 -> 0 | I103: ='2.Tien do'!F69 -> 0 | J103: ='2.Tien do'!G69 -> 0 | K103: ='2.Tien do'!H69 -> 0 | L103: ='2.Tien do'!I69 -> 0 | M103: ='2.Tien do'!J69 -> 0 | N103: ='2.Tien do'!K69 -> 0 | O103: ='2.Tien do'!L69 -> 0 | ... CJ103: ='2.Tien do'!CG69 -> 0 | CK103: end
...

Sheet 4.Chi phi hoat dong
C2: =+Summary!B2 -> Dự án Trần Đức 1
C3: Prepared by:
B5: A. | C5: CHI PHÍ HOẠT ĐỘNG VÀ THUẾ
B7: STT | C7: KHOẢN MỤC CHI PHÍ | D7: Tỷ lệ %/doanh thu bán hàng | E7: Tổng | F7: CHI PHÍ BÁN HÀNG PHÂN BỔ THEO QUÝ VÀ NĂM
F8: CBĐT | G8: ='5.Doanh thu'!H7 -> 2026 | H8: ='5.Doanh thu'!I7 -> 2026 | I8: ='5.Doanh thu'!J7 -> 2026 | J8: ='5.Doanh thu'!K7 -> 2026 | K8: ='5.Doanh thu'!L7 -> 2027 | L8: ='5.Doanh thu'!M7 -> 2027 | M8: ='5.Doanh thu'!N7 -> 2027 | N8: ='5.Doanh thu'!O7 -> 2027 | ... CI8: ='5.Doanh thu'!CJ7 -> 2079
G9: ='5.Doanh thu'!H8 -> Q1 | H9: ='5.Doanh thu'!I8 -> Q2 | I9: ='5.Doanh thu'!J8 -> Q3 | J9: ='5.Doanh thu'!K8 -> Q4 | K9: ='5.Doanh thu'!L8 -> Q1 | L9: ='5.Doanh thu'!M8 -> Q2 | M9: ='5.Doanh thu'!N8 -> Q3 | N9: ='5.Doanh thu'!O8 -> Q4 | ... AD9: ='5.Doanh thu'!AE8 -> Q4
B10: 1 | C10: Chi phí bán hàng, tiếp thị và DVKH | D10: =+E10/SUM(D33:D36,D39) -> 0.17501772 | E10: =SUM(F10:XFD10) -> 910042.9 | F10: =SUM(F11:F15) -> 0 | G10: =SUM(G11:G17) -> 0 | H10: =SUM(H11:H17) -> 0 | I10: =SUM(I11:I17) -> 0 | J10: =SUM(J11:J17) -> 0 | K10: =SUM(K11:K17) -> 0 | L10: =SUM(L11:L17) -> 0 | M10: =SUM(M11:M17) -> 0 | N10: =SUM(N11:N17) -> 0 | ... CI10: =SUM(CI11:CI17) -> 0
C11: Chi phí Môi Giới (%doanh thu) | D11: 0.07 | E11: =SUM(F11:XFD11) -> 363980.31 | G11: =$D11*SUM(G$33:G$36,G$39) -> 0 | H11: =$D11*SUM(H$33:H$36,H$39) -> 0 | I11: =$D11*SUM(I$33:I$36,I$39) -> 0 | J11: =$D11*SUM(J$33:J$36,J$39) -> 0 | K11: =$D11*SUM(K$33:K$36,K$39) -> 0 | L11: =$D11*SUM(L$33:L$36,L$39) -> 0 | M11: =$D11*SUM(M$33:M$36,M$39) -> 0 | N11: =$D11*SUM(N$33:N$36,N$39) -> 0 | ... CI11: =$D11*SUM(CI$33:CI$36,CI$39) -> 0
C12: Chi phí tiếp thị (%doanh thu) | D12: 0.02 | E12: =SUM(F12:XFD12) -> 103994.37 | G12: =$D12*SUM(G$33:G$36,G$39) -> 0 | H12: =$D12*SUM(H$33:H$36,H$39) -> 0 | I12: =$D12*SUM(I$33:I$36,I$39) -> 0 | J12: =$D12*SUM(J$33:J$36,J$39) -> 0 | K12: =$D12*SUM(K$33:K$36,K$39) -> 0 | L12: =$D12*SUM(L$33:L$36,L$39) -> 0 | M12: =$D12*SUM(M$33:M$36,M$39) -> 0 | N12: =$D12*SUM(N$33:N$36,N$39) -> 0 | ... CI12: =$D12*SUM(CI$33:CI$36,CI$39) -> 0
C13: Chi phí Push Sale (%doanh thu) | D13: 0.067 | E13: =SUM(F13:XFD13) -> 348381.15 | G13: =$D13*SUM(G$33:G$36,G$39) -> 0 | H13: =$D13*SUM(H$33:H$36,H$39) -> 0 | I13: =$D13*SUM(I$33:I$36,I$39) -> 0 | J13: =$D13*SUM(J$33:J$36,J$39) -> 0 | K13: =$D13*SUM(K$33:K$36,K$39) -> 0 | L13: =$D13*SUM(L$33:L$36,L$39) -> 0 | M13: =$D13*SUM(M$33:M$36,M$39) -> 0 | N13: =$D13*SUM(N$33:N$36,N$39) -> 0 | ... CI13: =$D13*SUM(CI$33:CI$36,CI$39) -> 0
C14: Chi phí Nhà mẫu (%doanh thu) | D14: 0.01 | E14: =SUM(F14:XFD14) -> 51997.187 | G14: =$D14*SUM(G$33:G$36,G$39) -> 0 | H14: =$D14*SUM(H$33:H$36,H$39) -> 0 | I14: =$D14*SUM(I$33:I$36,I$39) -> 0 | J14: =$D14*SUM(J$33:J$36,J$39) -> 0 | K14: =$D14*SUM(K$33:K$36,K$39) -> 0 | L14: =$D14*SUM(L$33:L$36,L$39) -> 0 | M14: =$D14*SUM(M$33:M$36,M$39) -> 0 | N14: =$D14*SUM(N$33:N$36,N$39) -> 0 | ... CI14: =$D14*SUM(CI$33:CI$36,CI$39) -> 0
C15: Chi phí dịch vụ khách hàng (%thực thu) | D15: 0.005 | E15: =SUM(F15:XFD15) -> 25998.593 | G15: =$D15*SUM(G$43:G$46,G$49) -> 0 | H15: =$D15*SUM(H$43:H$46,H$49) -> 0 | I15: =$D15*SUM(I$43:I$46,I$49) -> 0 | J15: =$D15*SUM(J$43:J$46,J$49) -> 0 | K15: =$D15*SUM(K$43:K$46,K$49) -> 0 | L15: =$D15*SUM(L$43:L$46,L$49) -> 0 | M15: =$D15*SUM(M$43:M$46,M$49) -> 0 | N15: =$D15*SUM(N$43:N$46,N$49) -> 0 | ... CI15: =$D15*SUM(CI$43:CI$46,CI$49) -> 0
C16: Chi phí hoa hồng kinh doanh tiếp thị (doanh thu) | D16: 0 | E16: =SUM(F16:XFD16) -> 0 | G16: =$D16*SUM(G$33:G$36) -> 0 | H16: =$D16*SUM(H$33:H$36) -> 0 | I16: =$D16*SUM(I$33:I$36) -> 0 | J16: =$D16*SUM(J$33:J$36) -> 0 | K16: =$D16*SUM(K$33:K$36) -> 0 | L16: =$D16*SUM(L$33:L$36) -> 0 | M16: =$D16*SUM(M$33:M$36) -> 0 | N16: =$D16*SUM(N$33:N$36) -> 0 | ... CI16: =$D16*SUM(CI$33:CI$36) -> 0
C17: Chi phí dự phòng bán hàng(doanh thu) | D17: 0.003 | E17: =SUM(F17:XFD17) -> 15691.282 | G17: =$D17*SUM(G$33:G$39) -> 0 | H17: =$D17*SUM(H$33:H$39) -> 0 | I17: =$D17*SUM(I$33:I$39) -> 0 | J17: =$D17*SUM(J$33:J$39) -> 0 | K17: =$D17*SUM(K$33:K$39) -> 0 | L17: =$D17*SUM(L$33:L$39) -> 0 | M17: =$D17*SUM(M$33:M$39) -> 0 | N17: =$D17*SUM(N$33:N$39) -> 0 | ... CI17: =$D17*SUM(CI$33:CI$39) -> 0
B18: 2 | C18: Chi phí Bảo Trì, MG cho TMDV & Nhà tre | D18: 0.05 | E18: =SUM(F18:XFD18) -> 1535.4283 | G18: =$D$18*SUM(G37:G38) -> 0 | H18: =$D$18*SUM(H37:H38) -> 0 | I18: =$D$18*SUM(I37:I38) -> 0 | J18: =$D$18*SUM(J37:J38) -> 0 | K18: =$D$18*SUM(K37:K38) -> 0 | L18: =$D$18*SUM(L37:L38) -> 0 | M18: =$D$18*SUM(M37:M38) -> 0 | N18: =$D$18*SUM(N37:N38) -> 0 | ... CI18: =$D$18*SUM(CI37:CI38) -> 0
B19: 3 | C19: Chi phí lãi vay hỗ trợ khách hàng | E19: =SUM(F19:XFD19) -> 0 | G19: ='6.Vay von'!F23-'3.Du toan'!AU78 -> 0 | H19: ='6.Vay von'!G23-'3.Du toan'!AV78 -> 0 | I19: ='6.Vay von'!H23-'3.Du toan'!AW78 -> 0 | J19: ='6.Vay von'!I23-'3.Du toan'!AX78 -> 0 | K19: ='6.Vay von'!J23-'3.Du toan'!AY78 -> 0 | L19: ='6.Vay von'!K23-'3.Du toan'!AZ78 -> 0 | M19: ='6.Vay von'!L23-'3.Du toan'!BA78 -> 0 | N19: ='6.Vay von'!M23-'3.Du toan'!BB78 -> 0 | ... CI19: ='6.Vay von'!CH23-'3.Du toan'!DW78 -> 0
B20: 4 | C20: Chi phí bảo lãnh ngân hàng | E20: =SUM(F20:XFD20) -> 46994.827 | G20: ='5.Doanh thu'!H72 -> 0 | H20: ='5.Doanh thu'!I72 -> 0 | I20: ='5.Doanh thu'!J72 -> 0 | J20: ='5.Doanh thu'!K72 -> 0 | K20: ='5.Doanh thu'!L72 -> 0 | L20: ='5.Doanh thu'!M72 -> 0 | M20: ='5.Doanh thu'!N72 -> 0 | N20: ='5.Doanh thu'!O72 -> 0 | ... CI20: ='5.Doanh thu'!CJ72 -> 0
B21: 5 | C21: Thuế VAT | E21: =SUM(F21:XFD21) -> 129826.61 | F21: 0 | G21: =IF(SUM($F$22:G22)-SUM($F$21:F21)>0,SUM($F$22:G22)-SUM($F$21:F21),0) -> 0 | H21: =IF(SUM($F$22:H22)-SUM($F$21:G21)>0,SUM($F$22:H22)-SUM($F$21:G21),0) -> 0 | I21: =IF(SUM($F$22:I22)-SUM($F$21:H21)>0,SUM($F$22:I22)-SUM($F$21:H21),0) -> 0 | J21: =IF(SUM($F$22:J22)-SUM($F$21:I21)>0,SUM($F$22:J22)-SUM($F$21:I21),0) -> 0 | K21: =IF(SUM($F$22:K22)-SUM($F$21:J21)>0,SUM($F$22:K22)-SUM($F$21:J21),0) -> 0 | L21: =IF(SUM($F$22:L22)-SUM($F$21:K21)>0,SUM($F$22:L22)-SUM($F$21:K21),0) -> 1.0748574e-12 | M21: =IF(SUM($F$22:M22)-SUM($F$21:L21)>0,SUM($F$22:M22)-SUM($F$21:L21),0) -> 0 | N21: =IF(SUM($F$22:N22)-SUM($F$21:M21)>0,SUM($F$22:N22)-SUM($F$21:M21),0) -> 0 | ... CI21: =IF(SUM($F$22:CI22)-SUM($F$21:CH21)>0,SUM($F$22:CI22)-SUM($F$21:CH21),0) -> 0
C22: Chênh lệch VAT | D22: 0.1 | E22: =SUM(F22:XFD22) -> 129826.61 | F22: =F24-F23 -> 0 | G22: =G24-G23 -> 0 | H22: =H24-H23 -> 0 | I22: =I24-I23 -> 0 | J22: =J24-J23 -> 0 | K22: =K24-K23 -> 0 | L22: =L24-L23 -> 1.0748574e-12 | M22: =M24-M23 -> -129.92793 | ... CI22: =CI24-CI23 -> 0
C23: VAT đầu vào | D23: 0.1 | E23: =SUM(F23:XFD23) -> 301599.69 | F23: =('3.Du toan'!AT77-'3.Du toan'!AT13-'3.Du toan'!AT12+F10+F18)/1.1*0.1 -> 0 | G23: =('3.Du toan'!AU77-'3.Du toan'!AU13-'3.Du toan'!AU12-'3.Du toan'!AU14-'3.Du toan'!AU15+G10+G18)/1.1*0.1 -> 0 | H23: =('3.Du toan'!AV77-'3.Du toan'!AV13-'3.Du toan'!AV12-'3.Du toan'!AV14-'3.Du toan'!AV15+H10+H18)/1.1*0.1 -> 0 | I23: =('3.Du toan'!AW77-'3.Du toan'!AW13-'3.Du toan'!AW12-'3.Du toan'!AW14-'3.Du toan'!AW15+I10+I18)/1.1*0.1 -> 0 | J23: =('3.Du toan'!AX77-'3.Du toan'!AX13-'3.Du toan'!AX12-'3.Du toan'!AX14-'3.Du toan'!AX15+J10+J18)/1.1*0.1 -> 0 | K23: =('3.Du toan'!AY77-'3.Du toan'!AY13-'3.Du toan'!AY12-'3.Du toan'!AY14-'3.Du toan'!AY15+K10+K18)/1.1*0.1 -> 0 | L23: =('3.Du toan'!AZ77-'3.Du toan'!AZ13-'3.Du toan'!AZ12-'3.Du toan'!AZ14-'3.Du toan'!AZ15+L10+L18)/1.1*0.1 -> -1.0748574e-12 | M23: =('3.Du toan'!BA77-'3.Du toan'!BA13-'3.Du toan'!BA12-'3.Du toan'!BA14-'3.Du toan'!BA15+M10+M18)/1.1*0.1 -> 129.92793 | N23: =('3.Du toan'!BB77-'3.Du toan'!BB13-'3.Du toan'!BB12-'3.Du toan'!BB14-'3.Du toan'!BB15+N10+N18)/1.1*0.1 -> 4475.2391 | ... BX23: =('3.Du toan'!DL77-'3.Du toan'!DL13-'3.Du toan'!DL12-'3.Du toan'!DL14-'3.Du toan'!DL15+BX10+BX18)/1.1*0.1 -> 0 | BY23: =('3.Du toan'!DM77-'3.Du toan'!DM11+BY10+BY16++BY18)/1.1*0.1 -> 0 | BZ23: =('3.Du toan'!DN77-'3.Du toan'!DN13-'3.Du toan'!DN12-'3.Du toan'!DN14-'3.Du toan'!DN15+BZ10+BZ18)/1.1*0.1 -> 0 | CA23: =('3.Du toan'!DO77-'3.Du toan'!DO13-'3.Du toan'!DO12-'3.Du toan'!DO14-'3.Du toan'!DO15+CA10+CA18)/1.1*0.1 -> 0 | CB23: =('3.Du toan'!DP77-'3.Du toan'!DP13-'3.Du toan'!DP12-'3.Du toan'!DP14-'3.Du toan'!DP15+CB10+CB18)/1.1*0.1 -> 0 | CC23: =('3.Du toan'!DQ77-'3.Du toan'!DQ13-'3.Du toan'!DQ12-'3.Du toan'!DQ14-'3.Du toan'!DQ15+CC10+CC18)/1.1*0.1 -> 0 | CD23: =('3.Du toan'!DR77-'3.Du toan'!DR13-'3.Du toan'!DR12-'3.Du toan'!DR14-'3.Du toan'!DR15+CD10+CD18)/1.1*0.1 -> 0 | CE23: =('3.Du toan'!DS77-'3.Du toan'!DS13-'3.Du toan'!DS12-'3.Du toan'!DS14-'3.Du toan'!DS15+CE10+CE18)/1.1*0.1 -> 0 | CF23: =('3.Du toan'!DT77-'3.Du toan'!DT13-'3.Du toan'!DT12-'3.Du toan'!DT14-'3.Du toan'!DT15+CF10+CF18)/1.1*0.1 -> 0 | CG23: =('3.Du toan'!DU77-'3.Du toan'!DU13-'3.Du toan'!DU12-'3.Du toan'!DU14-'3.Du toan'!DU15+CG10+CG18)/1.1*0.1 -> 0 | ... CI23: =('3.Du toan'!DW77-'3.Du toan'!DW13-'3.Du toan'!DW12-'3.Du toan'!DW14-'3.Du toan'!DW15+CI10+CI18)/1.1*0.1 -> 0
C24: VAT đầu ra | E24: =SUM(F24:XFD24) -> 431426.3 | F24: =F66 -> 0 | G24: =G66 -> 0 | H24: =H66 -> 0 | I24: =I66 -> 0 | J24: =J66 -> 0 | K24: =K66 -> 0 | L24: =L66 -> 0 | M24: =M66 -> 0 | ... CI24: =CI66 -> 0
B25: Tổng cộng | E25: =SUM(E10,E18:E21) -> 1088399.8 | F25: =SUM(F10,F18:F21) -> 0 | G25: =SUM(G10,G18:G21) -> 0 | H25: =SUM(H10,H18:H21) -> 0 | I25: =SUM(I10,I18:I21) -> 0 | J25: =SUM(J10,J18:J21) -> 0 | K25: =SUM(K10,K18:K21) -> 0 | L25: =SUM(L10,L18:L21) -> 1.0748574e-12 | ... CI25: =SUM(CI10,CI18:CI21) -> 0
B26: Tổng cộng theo năm | F26: =F25 -> 0 | G26: =SUM(G25:J25) -> 0 | K26: =SUM(K25:N25) -> 1.0748574e-12 | O26: =SUM(O25:R25) -> 734684.8 | S26: =SUM(S25:V25) -> 250632.5
B27: Tỷ lệ | E27: =D10*'5.Doanh thu'!G116 -> 915417.44 | F27: =F26/$E$25 -> 0 | G27: =G26/$E$25 -> 0 | K27: =K26/$E$25 -> 9.8755753e-19 | O27: =O26/$E$25 -> 0.67501375 | S27: =S26/$E$25 -> 0.23027614
C28: =E25-SUM(F25:XFD25) -> 0 | D28: =E21-E22 -> 0 | E28: =E25-E19 -> 1088399.8
D29: =E21-E29 -> 0 | E29: =('5.Doanh thu'!G116-'3.Du toan'!F77+'3.Du toan'!F15+'3.Du toan'!F12-'4.Chi phi hoat dong'!E10-'4.Chi phi hoat dong'!E18)/1.1*0.1 -> 129826.61
B31: B. | C31: TÍNH TOÁN PHÂN BỔ VAT CHO CÁC SẢN PHẨM
C32: DOANH THU
C33: =+'5.Doanh thu'!C10 -> Căn hộ khối tháp | D33: =SUM(F33:XFD33) -> 4199620.8 | G33: ='5.Doanh thu'!H14 -> 0 | H33: ='5.Doanh thu'!I14 -> 0 | I33: ='5.Doanh thu'!J14 -> 0 | J33: ='5.Doanh thu'!K14 -> 0 | K33: ='5.Doanh thu'!L14 -> 0 | L33: ='5.Doanh thu'!M14 -> 0 | M33: ='5.Doanh thu'!N14 -> 0 | N33: ='5.Doanh thu'!O14 -> 0 | ... CI33: ='5.Doanh thu'!CJ14 -> 0
C34: =+'5.Doanh thu'!C16 -> Căn hộ shop TM | D34: =SUM(F34:XFD34) -> 122426.52 | G34: =+'5.Doanh thu'!H20 -> 0 | H34: =+'5.Doanh thu'!I20 -> 0 | I34: =+'5.Doanh thu'!J20 -> 0 | J34: =+'5.Doanh thu'!K20 -> 0 | K34: =+'5.Doanh thu'!L20 -> 0 | L34: =+'5.Doanh thu'!M20 -> 0 | M34: =+'5.Doanh thu'!N20 -> 0 | N34: =+'5.Doanh thu'!O20 -> 0 | ... CI34: =+'5.Doanh thu'!CJ20 -> 0
C35: =+'5.Doanh thu'!C22 -> Căn TMDV | D35: =SUM(F35:XFD35) -> 0 | G35: =+'5.Doanh thu'!H26 -> 0 | H35: =+'5.Doanh thu'!I26 -> 0 | I35: =+'5.Doanh thu'!J26 -> 0 | J35: =+'5.Doanh thu'!K26 -> 0 | K35: =+'5.Doanh thu'!L26 -> 0 | L35: =+'5.Doanh thu'!M26 -> 0 | M35: =+'5.Doanh thu'!N26 -> 0 | N35: =+'5.Doanh thu'!O26 -> 0 | ... CI35: =+'5.Doanh thu'!CJ26 -> 0
C36: =+'5.Doanh thu'!C28 -> Căn officetel | D36: =SUM(F36:XFD36) -> 302538.71 | G36: =+'5.Doanh thu'!H32 -> 0 | H36: =+'5.Doanh thu'!I32 -> 0 | I36: =+'5.Doanh thu'!J32 -> 0 | J36: =+'5.Doanh thu'!K32 -> 0 | K36: =+'5.Doanh thu'!L32 -> 0 | L36: =+'5.Doanh thu'!M32 -> 0 | M36: =+'5.Doanh thu'!N32 -> 0 | N36: =+'5.Doanh thu'!O32 -> 0 | ... CI36: =+'5.Doanh thu'!CJ32 -> 0
C37: Trung tâm thương mại | D37: =SUM(F37:XFD37) -> 0 | G37: =+'5.Doanh thu'!H106 -> 0 | H37: =+'5.Doanh thu'!I106 -> 0 | I37: =+'5.Doanh thu'!J106 -> 0 | J37: =+'5.Doanh thu'!K106 -> 0 | K37: =+'5.Doanh thu'!L106 -> 0 | L37: =+'5.Doanh thu'!M106 -> 0 | M37: =+'5.Doanh thu'!N106 -> 0 | N37: =+'5.Doanh thu'!O106 -> 0 | ... CI37: =+'5.Doanh thu'!CJ106 -> 0
C38: Nhà trẻ | D38: =SUM(F38:XFD38) -> 30708.567 | G38: =+'5.Doanh thu'!H113 -> 0 | H38: =+'5.Doanh thu'!I113 -> 0 | I38: =+'5.Doanh thu'!J113 -> 0 | J38: =+'5.Doanh thu'!K113 -> 0 | K38: =+'5.Doanh thu'!L113 -> 0 | L38: =+'5.Doanh thu'!M113 -> 0 | M38: =+'5.Doanh thu'!N113 -> 0 | N38: =+'5.Doanh thu'!O113 -> 0 | ... CI38: =+'5.Doanh thu'!CJ113 -> 0
C39: =+'5.Doanh thu'!C95 -> Nhà phố liên kế | D39: =SUM(F39:XFD39) -> 575132.69 | G39: =+'5.Doanh thu'!H99 -> 0 | H39: =+'5.Doanh thu'!I99 -> 0 | I39: =+'5.Doanh thu'!J99 -> 0 | J39: =+'5.Doanh thu'!K99 -> 0 | K39: =+'5.Doanh thu'!L99 -> 0 | L39: =+'5.Doanh thu'!M99 -> 0 | M39: =+'5.Doanh thu'!N99 -> 0 | N39: =+'5.Doanh thu'!O99 -> 0 | ... CI39: =+'5.Doanh thu'!CJ99 -> 0
C40: TỔNG CỘNG | D40: =SUM(D33:D39) -> 5230427.3 | E40: =D40-'5.Doanh thu'!G116 -> 0 | G40: =SUM(G33:G39) -> 0 | H40: =SUM(H33:H39) -> 0 | I40: =SUM(I33:I39) -> 0 | J40: =SUM(J33:J39) -> 0 | K40: =SUM(K33:K39) -> 0 | L40: =SUM(L33:L39) -> 0 | M40: =SUM(M33:M39) -> 0 | N40: =SUM(N33:N39) -> 0 | ... CI40: =SUM(CI33:CI39) -> 0
C42: THỰC THU
C43: =C33 -> Căn hộ khối tháp | D43: =SUM(F43:XFD43) -> 4199620.8 | G43: =+'5.Doanh thu'!H15 -> 0 | H43: =+'5.Doanh thu'!I15 -> 0 | I43: =+'5.Doanh thu'!J15 -> 0 | J43: =+'5.Doanh thu'!K15 -> 0 | K43: =+'5.Doanh thu'!L15 -> 0 | L43: =+'5.Doanh thu'!M15 -> 0 | M43: =+'5.Doanh thu'!N15 -> 0 | N43: =+'5.Doanh thu'!O15 -> 0 | ... CI43: =+'5.Doanh thu'!CJ15 -> 0
C44: =C34 -> Căn hộ shop TM | D44: =SUM(F44:XFD44) -> 122426.52 | G44: =+'5.Doanh thu'!H21 -> 0 | H44: =+'5.Doanh thu'!I21 -> 0 | I44: =+'5.Doanh thu'!J21 -> 0 | J44: =+'5.Doanh thu'!K21 -> 0 | K44: =+'5.Doanh thu'!L21 -> 0 | L44: =+'5.Doanh thu'!M21 -> 0 | M44: =+'5.Doanh thu'!N21 -> 0 | N44: =+'5.Doanh thu'!O21 -> 0 | ... CI44: =+'5.Doanh thu'!CJ21 -> 0
C45: =C35 -> Căn TMDV | D45: =SUM(F45:XFD45) -> 0 | G45: =+'5.Doanh thu'!H27 -> 0 | H45: =+'5.Doanh thu'!I27 -> 0 | I45: =+'5.Doanh thu'!J27 -> 0 | J45: =+'5.Doanh thu'!K27 -> 0 | K45: =+'5.Doanh thu'!L27 -> 0 | L45: =+'5.Doanh thu'!M27 -> 0 | M45: =+'5.Doanh thu'!N27 -> 0 | N45: =+'5.Doanh thu'!O27 -> 0 | ... CI45: =+'5.Doanh thu'!CJ27 -> 0
C46: =C36 -> Căn officetel | D46: =SUM(F46:XFD46) -> 302538.71 | G46: =+'5.Doanh thu'!H33 -> 0 | H46: =+'5.Doanh thu'!I33 -> 0 | I46: =+'5.Doanh thu'!J33 -> 0 | J46: =+'5.Doanh thu'!K33 -> 0 | K46: =+'5.Doanh thu'!L33 -> 0 | L46: =+'5.Doanh thu'!M33 -> 0 | M46: =+'5.Doanh thu'!N33 -> 0 | N46: =+'5.Doanh thu'!O33 -> 0 | ... CI46: =+'5.Doanh thu'!CJ33 -> 0
C47: =C37 -> Trung tâm thương mại | D47: =SUM(F47:XFD47) -> 0 | G47: =+'5.Doanh thu'!H107 -> 0 | H47: =+'5.Doanh thu'!I107 -> 0 | I47: =+'5.Doanh thu'!J107 -> 0 | J47: =+'5.Doanh thu'!K107 -> 0 | K47: =+'5.Doanh thu'!L107 -> 0 | L47: =+'5.Doanh thu'!M107 -> 0 | M47: =+'5.Doanh thu'!N107 -> 0 | N47: =+'5.Doanh thu'!O107 -> 0 | ... CI47: =+'5.Doanh thu'!CJ107 -> 0
C48: =C38 -> Nhà trẻ | D48: =SUM(F48:XFD48) -> 30708.567 | G48: ='5.Doanh thu'!H114 -> 0 | H48: ='5.Doanh thu'!I114 -> 0 | I48: ='5.Doanh thu'!J114 -> 0 | J48: ='5.Doanh thu'!K114 -> 0 | K48: ='5.Doanh thu'!L114 -> 0 | L48: ='5.Doanh thu'!M114 -> 0 | M48: ='5.Doanh thu'!N114 -> 0 | N48: ='5.Doanh thu'!O114 -> 0 | ... CI48: ='5.Doanh thu'!CJ114 -> 0
C49: =+C39 -> Nhà phố liên kế | D49: =SUM(F49:XFD49) -> 575132.69 | G49: =+'5.Doanh thu'!H100 -> 0 | H49: =+'5.Doanh thu'!I100 -> 0 | I49: =+'5.Doanh thu'!J100 -> 0 | J49: =+'5.Doanh thu'!K100 -> 0 | K49: =+'5.Doanh thu'!L100 -> 0 | L49: =+'5.Doanh thu'!M100 -> 0 | M49: =+'5.Doanh thu'!N100 -> 0 | N49: =+'5.Doanh thu'!O100 -> 0 | ... CI49: =+'5.Doanh thu'!CJ100 -> 0
C50: TỔNG CỘNG | D50: =SUM(D43:D49) -> 5230427.3 | E50: =D50-'5.Doanh thu'!G117 -> 0 | G50: =SUM(G43:G49) -> 0 | H50: =SUM(H43:H49) -> 0 | I50: =SUM(I43:I49) -> 0 | J50: =SUM(J43:J49) -> 0 | K50: =SUM(K43:K49) -> 0 | L50: =SUM(L43:L49) -> 0 | M50: =SUM(M43:M49) -> 0 | N50: =SUM(N43:N49) -> 0 | ... CI50: =SUM(CI43:CI49) -> 0
C52: Thuế TNDN tạm tính 1% phải nộp cho phần căn hộ và shop | G52: =SUM(G43:G49)*1% -> 0 | H52: =SUM(H43:H49)*1% -> 0 | I52: =SUM(I43:I49)*1% -> 0 | J52: =SUM(J43:J49)*1% -> 0 | K52: =SUM(K43:K49)*1% -> 0 | L52: =SUM(L43:L49)*1% -> 0 | M52: =SUM(M43:M49)*1% -> 0 | N52: =SUM(N43:N49)*1% -> 0 | ... AL52: =SUM(AL43:AL49)*1% -> 0
C54: Đơn giá LUR được khấu trừ vào giá bán tính VAT | E54: =('3.Du toan'!F13/'1. thong tin quy hoach'!K10) -> 4.9553918
C55: DOANH THU
C56: Sales (including VAT) - Căn hộ | D56: =+SUM(D33:D39) -> 5230427.3 | E56: =D56-SUM(F56:XFD56) -> 0 | G56: ='5.Doanh thu'!H116 -> 0 | H56: ='5.Doanh thu'!I116 -> 0 | I56: ='5.Doanh thu'!J116 -> 0 | J56: ='5.Doanh thu'!K116 -> 0 | K56: ='5.Doanh thu'!L116 -> 0 | L56: ='5.Doanh thu'!M116 -> 0 | M56: ='5.Doanh thu'!N116 -> 0 | N56: ='5.Doanh thu'!O116 -> 0 | ... CI56: ='5.Doanh thu'!CJ116 -> 0
C57: deductible Land cost | D57: =+'3.Du toan'!F13 -> 484737.94 | E57: =D57-SUM(F57:XFD57) -> 0 | G57: =G56*$D$57/$D$56 -> 0 | H57: =H56*$D$57/$D$56 -> 0 | I57: =I56*$D$57/$D$56 -> 0 | J57: =J56*$D$57/$D$56 -> 0 | K57: =K56*$D$57/$D$56 -> 0 | L57: =L56*$D$57/$D$56 -> 0 | M57: =M56*$D$57/$D$56 -> 0 | N57: =N56*$D$57/$D$56 -> 0 | ... CI57: =CI56*$D$57/$D$56 -> 0
C58: Sales (including VAT & excluding land cost) | D58: =SUM(F58:XFD58) -> 4745689.3 | E58: =D58-SUM(F58:XFD58) -> 0 | G58: =G56-G57 -> 0 | H58: =H56-H57 -> 0 | I58: =I56-I57 -> 0 | J58: =J56-J57 -> 0 | K58: =K56-K57 -> 0 | L58: =L56-L57 -> 0 | M58: =M56-M57 -> 0 | N58: =N56-N57 -> 0 | ... CI58: =CI56-CI57 -> 0
C59: Output 10%VAT - NOTM | D59: =SUM(F59:XFD59) -> 431426.3 | E59: =D59-SUM(F59:XFD59) -> 0 | G59: =G58/1.1*0.1 -> 0 | H59: =H58/1.1*0.1 -> 0 | I59: =I58/1.1*0.1 -> 0 | J59: =J58/1.1*0.1 -> 0 | K59: =K58/1.1*0.1 -> 0 | L59: =L58/1.1*0.1 -> 0 | M59: =M58/1.1*0.1 -> 0 | N59: =N58/1.1*0.1 -> 0 | ... CI59: =CI58/1.1*0.1 -> 0
C60: Sales (excluding VAT) | D60: =SUM(F60:XFD60) -> 4799001 | E60: =D60-SUM(F60:XFD60) -> 0 | G60: =G56-G59 -> 0 | H60: =H56-H59 -> 0 | I60: =I56-I59 -> 0 | J60: =J56-J59 -> 0 | K60: =K56-K59 -> 0 | L60: =L56-L59 -> 0 | M60: =M56-M59 -> 0 | N60: =N56-N59 -> 0 | ... CI60: =CI56-CI59 -> 0
D61: =+D60*1.1 -> 5278901.1
C62: THỰC THU
C63: Sales (including VAT) - Căn hộ | D63: =+SUM(D43:D49) -> 5230427.3 | E63: =D63-SUM(F63:XFD63) -> 0 | G63: ='5.Doanh thu'!H117 -> 0 | H63: ='5.Doanh thu'!I117 -> 0 | I63: ='5.Doanh thu'!J117 -> 0 | J63: ='5.Doanh thu'!K117 -> 0 | K63: ='5.Doanh thu'!L117 -> 0 | L63: ='5.Doanh thu'!M117 -> 0 | M63: ='5.Doanh thu'!N117 -> 0 | N63: ='5.Doanh thu'!O117 -> 0 | ... CI63: ='5.Doanh thu'!CJ117 -> 0
C64: deductible Land cost | D64: =D57 -> 484737.94 | E64: =D64-SUM(F64:XFD64) -> 0 | G64: =G63*$D$64/$D$63 -> 0 | H64: =H63*$D$64/$D$63 -> 0 | I64: =I63*$D$64/$D$63 -> 0 | J64: =J63*$D$64/$D$63 -> 0 | K64: =K63*$D$64/$D$63 -> 0 | L64: =L63*$D$64/$D$63 -> 0 | M64: =M63*$D$64/$D$63 -> 0 | N64: =N63*$D$64/$D$63 -> 0 | ... CI64: =CI63*$D$64/$D$63 -> 0
C65: Sales (including VAT & excluding land cost) | D65: =SUM(F65:XFD65) -> 4745689.3 | E65: =D65-SUM(F65:XFD65) -> 0 | G65: =G63-G64 -> 0 | H65: =H63-H64 -> 0 | I65: =I63-I64 -> 0 | J65: =J63-J64 -> 0 | K65: =K63-K64 -> 0 | L65: =L63-L64 -> 0 | M65: =M63-M64 -> 0 | N65: =N63-N64 -> 0 | ... CI65: =CI63-CI64 -> 0
C66: Output 10%VAT - NOTM | D66: =SUM(F66:XFD66) -> 431426.3 | E66: =D66-SUM(F66:XFD66) -> 0 | G66: =G65/1.1*0.1 -> 0 | H66: =H65/1.1*0.1 -> 0 | I66: =I65/1.1*0.1 -> 0 | J66: =J65/1.1*0.1 -> 0 | K66: =K65/1.1*0.1 -> 0 | L66: =L65/1.1*0.1 -> 0 | M66: =M65/1.1*0.1 -> 0 | N66: =N65/1.1*0.1 -> 0 | ... CI66: =CI65/1.1*0.1 -> 0
C67: Sales (excluding VAT) | D67: =SUM(F67:XFD67) -> 4799001 | E67: =D67-SUM(F67:XFD67) -> 0 | G67: =G63-G66 -> 0 | H67: =H63-H66 -> 0 | I67: =I63-I66 -> 0 | J67: =J63-J66 -> 0 | K67: =K63-K66 -> 0 | L67: =L63-L66 -> 0 | M67: =M63-M66 -> 0 | N67: =N63-N66 -> 0 | ... CI67: =CI63-CI66 -> 0
D68: =+D67*1.1 -> 5278901.1
C69: Phân bổ doanh thu chưa VAT
C70: =+C33 -> Căn hộ khối tháp | D70: =('5.Doanh thu'!E13+'4.Chi phi hoat dong'!$E$54*'8.ĐO NHAY'!$C$22)/(1+'8.ĐO NHAY'!$C$22)*'5.Doanh thu'!E12 -> 3854392.1 | E70: =+D70-SUM(G70:CI70) -> 3854392.1
C71: =+C34 -> Căn hộ shop TM | D71: =('5.Doanh thu'!E19+'4.Chi phi hoat dong'!$E$54*'8.ĐO NHAY'!$C$22)/(1+'8.ĐO NHAY'!$C$22)*'5.Doanh thu'!E18 -> 112308.71 | E71: =+D71-SUM(G71:CI71) -> 112308.71
C72: =+C35 -> Căn TMDV | D72: =('5.Doanh thu'!E25+'4.Chi phi hoat dong'!$E$54*'8.ĐO NHAY'!$C$22)/(1+'8.ĐO NHAY'!$C$22)*'5.Doanh thu'!E24 -> 0 | E72: =+D72-SUM(G72:CI72) -> 0
C73: =+C36 -> Căn officetel | D73: =('5.Doanh thu'!E31+'4.Chi phi hoat dong'!$E$54*'8.ĐO NHAY'!$C$22)/(1+'8.ĐO NHAY'!$C$22)*'5.Doanh thu'!E30 -> 277808.6 | E73: =+D73-SUM(G73:CI73) -> 277808.6
C74: =+C37 -> Trung tâm thương mại | D74: =('5.Doanh thu'!E105+'4.Chi phi hoat dong'!$E$54*'8.ĐO NHAY'!$C$22)/(1+'8.ĐO NHAY'!$C$22)*'5.Doanh thu'!E104 -> 0 | E74: =+D74-SUM(G74:CI74) -> 0
C75: =+C38 -> Nhà trẻ | D75: =('5.Doanh thu'!E112+'4.Chi phi hoat dong'!$E$54*'8.ĐO NHAY'!$C$22)/(1+'8.ĐO NHAY'!$C$22)*'5.Doanh thu'!E111 -> 28682.712 | E75: =+D75-SUM(G75:CI75) -> 28682.712
C76: =+C39 -> Nhà phố liên kế | D76: =('5.Doanh thu'!E98+'4.Chi phi hoat dong'!$E$54*'8.ĐO NHAY'!$C$22)/(1+'8.ĐO NHAY'!$C$22)*'5.Doanh thu'!E97 -> 525808.8 | E76: =+D76-SUM(G76:CI76) -> 525808.8
C77: Doanh thu chưa VAT | D77: =SUM(D70:D76) -> 4799001 | G77: =SUM(G70:G76) -> 0 | H77: =SUM(H70:H76) -> 0 | I77: =SUM(I70:I76) -> 0 | J77: =SUM(J70:J76) -> 0 | K77: =SUM(K70:K76) -> 0 | L77: =SUM(L70:L76) -> 0 | M77: =SUM(M70:M76) -> 0 | N77: =SUM(N70:N76) -> 0 | ... CI77: =SUM(CI70:CI76) -> 0
C78: Doanh thu gồm VAT | D78: =D77+E24 -> 5230427.3

Sheet 6.Vay von
B2: =+Summary!B2 -> Dự án Trần Đức 1
B3: Prepared by:
B5: CƠ CẤU VỐN
B7: Lãi suất vay hàng năm
B8: Hạng mục | C8: Cơ sở tính | E8: CBĐT | F8: =F14 -> 2026 | G8: =G14 -> 2026 | H8: =H14 -> 2026 | I8: =I14 -> 2026 | J8: =J14 -> 2027 | K8: =K14 -> 2027 | L8: =L14 -> 2027 | M8: =M14 -> 2027 | ... CH8: =CH14 -> 2079
F9: Q1 | G9: Q2 | H9: Q3 | I9: Q4 | J9: Q1 | K9: Q2 | L9: Q3 | M9: Q4 | N9: Q1 | O9: Q2 | P9: Q3 | Q9: Q4 | R9: Q1 | S9: Q2 | T9: Q3 | U9: Q4 | V9: Q1 | W9: Q2 | X9: Q3 | Y9: Q4 | Z9: Q1 | AA9: Q2 | AB9: Q3 | AC9: Q4
B11: Lãi suất | C11: 0.12 | E11: =$C$11/4 -> 0.03 | F11: =E11 -> 0.03 | G11: =F11 -> 0.03 | H11: =G11 -> 0.03 | I11: =H11 -> 0.03 | J11: =I11 -> 0.03 | K11: =J11 -> 0.03 | L11: =K11 -> 0.03 | M11: =L11 -> 0.03 | ... AC11: =AB11 -> 0.03 | AD11: =AC11*4 -> 0.12 | AE11: =AD11 -> 0.12 | AF11: =AE11 -> 0.12 | AG11: =AF11 -> 0.12 | AH11: =AG11 -> 0.12 | AI11: =AH11 -> 0.12 | AJ11: =AI11 -> 0.12 | AK11: =AJ11 -> 0.12 | AL11: =AK11 -> 0.12 | ... CH11: =CG11 -> 0.12
B13: TỔNG CHI PHÍ
B14: Hạng mục | C14: Tổng cộng | D14: Tỷ trọng | E14: CBĐT | F14: ='5.Doanh thu'!H7 -> 2026 | G14: ='5.Doanh thu'!I7 -> 2026 | H14: ='5.Doanh thu'!J7 -> 2026 | I14: ='5.Doanh thu'!K7 -> 2026 | J14: ='5.Doanh thu'!L7 -> 2027 | K14: ='5.Doanh thu'!M7 -> 2027 | L14: ='5.Doanh thu'!N7 -> 2027 | M14: ='5.Doanh thu'!O7 -> 2027 | ... CH14: ='5.Doanh thu'!CJ7 -> 2079
F15: ='5.Doanh thu'!H8 -> Q1 | G15: ='5.Doanh thu'!I8 -> Q2 | H15: ='5.Doanh thu'!J8 -> Q3 | I15: ='5.Doanh thu'!K8 -> Q4 | J15: ='5.Doanh thu'!L8 -> Q1 | K15: ='5.Doanh thu'!M8 -> Q2 | L15: ='5.Doanh thu'!N8 -> Q3 | M15: ='5.Doanh thu'!O8 -> Q4 | ... AO15: ='5.Doanh thu'!AQ8 -> Q4
B16: CƠ CẤU VỐN TÀI TRỢ | C16: =SUM(C17:C19) -> 4800623.2
B17: Vốn tự có | C17: =SUM(E17:BZ17) -> 813975.15 | D17: =C17/$C$16 -> 0.16955614 | E17: =E32+E63+E72+E33 -> 0 | F17: =F32+F63+F72+F33 -> 0 | G17: =G32+G63+G72+G33 -> 156000 | H17: =H32+H63+H72+H33 -> 364000 | I17: =I32+I63+I72+I33 -> 4263.4453 | J17: =J32+J63+J72+J33 -> 4263.4453 | K17: =K32+K63+K72+K33 -> 149684.83 | L17: =L32+L63+L72+L33 -> 19135.149 | ... CH17: =CH32+CH63+CH72+CH33 -> 0
B18: Vay ngân hàng | C18: =SUM(E18:BZ18) -> 655683.49 | D18: =C18/$C$16 -> 0.13658299 | E18: =E35+E64+E73 -> 0 | F18: =F35+F64+F73 -> 0 | G18: =G35+G64+G73 -> 0 | H18: =H35+H64+H73 -> 0 | I18: =I35+I64+I73 -> 0 | J18: =J35+J64+J73 -> 0 | K18: =K35+K64+K73 -> 339316.56 | L18: =L35+L64+L73 -> 1000.445 | ... CH18: =CH35+CH64+CH73 -> 0
B19: Huy động từ khách hàng | C19: =SUM(E19:BZ19) -> 3330964.6 | D19: =C19/$C$16 -> 0.69386086 | E19: =E30+E65+E74 -> 0 | F19: =F30+F65+F74 -> 0 | G19: =G30+G65+G74 -> 0 | H19: =H30+H65+H74 -> 0 | I19: =I30+I65+I74 -> 0 | J19: =J30+J65+J74 -> 0 | K19: =K30+K65+K74 -> 0 | L19: =L30+L65+L74 -> 0 | ... CH19: =CH30+CH65+CH74 -> 0
B20: KẾ HOẠCH TRẢ NỢ | C20: =SUM(E20:XFD20) -> 0
B21: Trả vốn vay ngân hàng | C21: =SUM(E21:BZ21) -> 655683.49 | E21: =E46 -> 0 | F21: =F46 -> 0 | G21: =G46 -> 0 | H21: =H46 -> 0 | I21: =I46 -> 0 | J21: =J46 -> 0 | K21: =K46 -> 0 | L21: =L46 -> 0 | ... CH21: =CH46 -> 0
B22: Dư nợ vay | C22: =SUM(E22:BZ22) -> 3624909.8 | E22: =E48 -> 0 | F22: =F48 -> 0 | G22: =G48 -> 0 | H22: =H48 -> 0 | I22: =I48 -> 0 | J22: =J48 -> 0 | K22: =K48 -> 339316.56 | L22: =L48 -> 340317 | ... CH22: =CH48 -> 0
B23: Trả lãi vay ngân hàng | C23: =SUM(E23:BZ23) -> 108747.29 | F23: =F49+F55 -> 0 | G23: =G49+G55 -> 0 | H23: =H49+H55 -> 0 | I23: =I49+I55 -> 0 | J23: =J49+J55 -> 0 | K23: =K49+K55 -> 0 | L23: =L49+L55 -> 10179.497 | M23: =M49+M55 -> 10209.51 | ... Y23: =Y49+Y55 -> 0
B25: CHI PHÍ ĐẦU TƯ | D25: WACC | E25: =C32/(C32+C35)*15%+C35/(C32+C35)*11%*(1-20%) -> 0.12173044
B26: Tỷ lệ sử dụng vốn huy động từ khách hàng | E26: 1
B27: =B16 -> CƠ CẤU VỐN TÀI TRỢ | C27: =C32+C35+C30+C33 -> 3604772.4 | D27: =C27-C37 -> 0
B28: DT còn lại sau đóng thuế, CPHĐ, CPĐT | E28: =E66-E30 -> 0 | F28: =F66-F30 -> 0 | G28: =G66-G30 -> 0 | H28: =H66-H30 -> 0 | I28: =I66-I30 -> 0 | J28: =J66-J30 -> 0 | K28: =K66-K30 -> 0 | L28: =L66-L30 -> 0 | ... CH28: =CH66-CH30 -> 1243779.2
B29: Huy động từ khác hàng
B30: Huy động từ khách hàng | C30: =SUM(E30:BZ30) -> 2135113.8 | D30: =C30/$C$27 -> 0.59230196 | E30: =IF(E66>E37,E37,IF(E66>0,E66,0)) -> 0 | F30: =IF(F66>F37,F37,IF(F66>0,F66*$E$26,0)) -> 0 | G30: =IF(G66>G37,G37,IF(G66>0,G66*$E$26,0)) -> 0 | H30: =IF(H66>H37,H37,IF(H66>0,H66*$E$26,0)) -> 0 | I30: =IF(I66>I37,I37,IF(I66>0,I66*$E$26,0)) -> 0 | J30: =IF(J66>J37,J37,IF(J66>0,J66*$E$26,0)) -> 0 | K30: =IF(K66>K37,K37,IF(K66>0,K66*$E$26,0)) -> 0 | L30: =IF(L66>L37,L37,IF(L66>0,L66*$E$26,0)) -> 0 | M30: =IF(M66>M37,M37,IF(M66>0,M66*$E$26,0)) -> 0 | ... CH30: =IF(CH66>CH37,CH37,IF(CH66>0,CH66*$E$26,0)) -> 0
B31: Vốn tự có
B32: Vốn tự có | C32: =SUM(E32:BZ32) -> 782342.86 | D32: =C32/$C$27 -> 0.21702975 | E32: =E37-E35-E30-E33 -> 0 | F32: =F37-F35-F30-F33 -> 0 | G32: =G37-G35-G30-G33 -> 156000 | H32: =H37-H35-H30-H33 -> 364000 | I32: =I37-I35-I30-I33 -> 4263.4453 | J32: =J37-J35-J30-J33 -> 4263.4453 | K32: =K37-K35-K30-K33 -> 149684.83 | L32: =L37-L35-L30-L33 -> 8955.6528 | ... CH32: =CH37-CH35-CH30-CH33 -> 0
B33: Vốn tự có cho lãi vay vốn hoá | C33: =SUM(E33:BZ33) -> 31632.297 | D33: =C33/$C$27 -> 0.0087751162 | F33: =IF((F43-F55)>F30,(F43-F55-F30),0) -> 0 | G33: =IF((G43-G55)>G30,(G43-G55-G30),0) -> 0 | H33: =IF((H43-H55)>H30,(H43-H55-H30),0) -> 0 | I33: =IF((I43-I55)>I30,(I43-I55-I30),0) -> 0 | J33: =IF((J43-J55)>J30,(J43-J55-J30),0) -> 0 | K33: =IF((K43-K55)>K30,(K43-K55-K30),0) -> 0 | L33: =IF((L43-L55)>L30,(L43-L55-L30),0) -> 10179.497 | M33: =IF((M43-M55)>M30,(M43-M55-M30),0) -> 10209.51 | ... CH33: =IF((CH43-CH55)>CH30,(CH43-CH55-CH30),0) -> 0
B34: Vốn vay
B35: Vay ngân hàng | C35: =SUM(E35:BZ35) -> 655683.49 | D35: =C35/$C$27 -> 0.18189317 | E35: =IF(AND(E37>(E30+E33),E37>E38),(E37-E30-E33)*0.7,0) -> 0 | F35: =IF((F37-F30-F33)>F36,F36,IF(F37-F33-F30>0,F37-F33-F30,0)) -> 0 | G35: =IF((G37-G30-G33)>G36,G36,IF(G37-G33-G30>0,G37-G33-G30,0)) -> 0 | H35: =IF((H37-H30-H33)>H36,H36,IF(H37-H33-H30>0,H37-H33-H30,0)) -> 0 | I35: =IF((I37-I30-I33)>I36,I36,IF(I37-I33-I30>0,I37-I33-I30,0)) -> 0 | J35: =IF((J37-J30-J33)>J36,J36,IF(J37-J33-J30>0,J37-J33-J30,0)) -> 0 | K35: =IF((K37-K30-K33)>K36,K36,IF(K37-K33-K30>0,K37-K33-K30,0)) -> 339316.56 | L35: =IF((L37-L30-L33)>L36,L36,IF(L37-L33-L30>0,L37-L33-L30,0)) -> 1000.445 | M35: =IF((M37-M30-M33)>M36,M36,IF(M37-M33-M30>0,M37-M33-M30,0)) -> 34459.341 | ... CH35: =IF((CH37-CH30-CH33)>CH36,CH36,IF(CH37-CH33-CH30>0,CH37-CH33-CH30,0)) -> 0
B36: Vỗn vay trong Tổng Vốn đầu tư | C36: =SUM(E36:BZ36) -> 2023529.4 | E36: =SUMPRODUCT($D$38:$D$42,E38:E42) -> 0 | F36: =SUMPRODUCT($D$38:$D$42,F38:F42) -> 0 | G36: =SUMPRODUCT($D$38:$D$42,G38:G42) -> 0 | H36: =SUMPRODUCT($D$38:$D$42,H38:H42) -> 0 | I36: =SUMPRODUCT($D$38:$D$42,I38:I42) -> 0 | J36: =SUMPRODUCT($D$38:$D$42,J38:J42) -> 0 | K36: =SUMPRODUCT($D$38:$D$42,K38:K42) -> 339316.56 | L36: =SUMPRODUCT($D$38:$D$42,L38:L42) -> 1000.445 | ... CH36: =SUMPRODUCT($D$38:$D$42,CH38:CH42) -> 0
B37: Vốn đầu tư | C37: =SUM(E37:BZ37) -> 3604772.4 | D37: % Vay | E37: ='3.Du toan'!AT79 -> 0 | F37: ='3.Du toan'!AU79 -> 0 | G37: ='3.Du toan'!AV79 -> 156000 | H37: ='3.Du toan'!AW79 -> 364000 | I37: ='3.Du toan'!AX79 -> 4263.4453 | J37: ='3.Du toan'!AY79 -> 4263.4453 | K37: ='3.Du toan'!AZ79 -> 489001.39 | L37: ='3.Du toan'!BA79 -> 20135.595 | ... CH37: ='3.Du toan'!DW79 -> 0
B38: Chi phi giá vốn | C38: =SUM(E38:BZ38) -> 520000 | D38: 0 | E38: =SUM('3.Du toan'!AT12) -> 0 | F38: =SUM('3.Du toan'!AU12) -> 0 | G38: =SUM('3.Du toan'!AV12) -> 156000 | H38: =SUM('3.Du toan'!AW12) -> 364000 | I38: =SUM('3.Du toan'!AX12) -> 0 | J38: =SUM('3.Du toan'!AY12) -> 0 | K38: =SUM('3.Du toan'!AZ12) -> 0 | L38: =SUM('3.Du toan'!BA12) -> 0 | ... CH38: =SUM('3.Du toan'!DW12) -> 0
B39: LUR | C39: =SUM(E39:BZ39) -> 484737.94 | D39: 0.7 | E39: =SUM('3.Du toan'!AT13) -> 0 | F39: =SUM('3.Du toan'!AU13) -> 0 | G39: =SUM('3.Du toan'!AV13) -> 0 | H39: =SUM('3.Du toan'!AW13) -> 0 | I39: =SUM('3.Du toan'!AX13) -> 0 | J39: =SUM('3.Du toan'!AY13) -> 0 | K39: =SUM('3.Du toan'!AZ13) -> 484737.94 | L39: =SUM('3.Du toan'!BA13) -> 0 | ... CH39: =SUM('3.Du toan'!DW13) -> 0
B40: Chi phí pháp lý | C40: =SUM(E40:BZ40) -> 85268.906 | D40: 0 | E40: =SUM('3.Du toan'!AT15) -> 0 | F40: =SUM('3.Du toan'!AU15) -> 0 | G40: =SUM('3.Du toan'!AV15) -> 0 | H40: =SUM('3.Du toan'!AW15) -> 0 | I40: =SUM('3.Du toan'!AX15) -> 4263.4453 | J40: =SUM('3.Du toan'!AY15) -> 4263.4453 | K40: =SUM('3.Du toan'!AZ15) -> 4263.4453 | L40: =SUM('3.Du toan'!BA15) -> 8526.8906 | ... CH40: =SUM('3.Du toan'!DW15) -> 0
B41: Chi phí xây lắp và thiết bị | C41: =SUM(E41:BZ41) -> 2406018.3 | D41: 0.7 | E41: =+SUM('3.Du toan'!AT21:AT27) -> 0 | F41: =+'3.Du toan'!AU16 -> 0 | G41: =+'3.Du toan'!AV16 -> 0 | H41: =+'3.Du toan'!AW16 -> 0 | I41: =+'3.Du toan'!AX16 -> 0 | J41: =+'3.Du toan'!AY16 -> 0 | K41: =+'3.Du toan'!AZ16 -> 0 | L41: =+'3.Du toan'!BA16 -> 1429.2072 | M41: =+'3.Du toan'!BB16 -> 49227.63 | ... CH41: =+'3.Du toan'!DW16 -> 0
B42: Chi phí QLDA. TVTB, Khac, DPP | C42: =SUM(E42:BZ42) -> 0 | D42: 0.7 | E42: =+SUM('3.Du toan'!AT28:AT32) -> 0
B43: Lãi vay (vốn hóa) | C43: =C37-SUM(C38:C42) -> 108747.29 | E43: =E37-SUM(E38:E42) -> 0 | F43: =F37-SUM(F38:F42) -> 0 | G43: =G37-SUM(G38:G42) -> 0 | H43: =H37-SUM(H38:H42) -> 0 | I43: =I37-SUM(I38:I42) -> 0 | J43: =J37-SUM(J38:J42) -> 0 | K43: =K37-SUM(K38:K42) -> 0 | L43: =L37-SUM(L38:L42) -> 10179.497 | ... CH43: =CH37-SUM(CH38:CH42) -> 0
B45: =B20 -> KẾ HOẠCH TRẢ NỢ
B46: Trả gốc vay | C46: =SUM(E46:BZ46) -> 655683.49 | D46: =D28 -> 0 | E46: =E28 -> 0 | F46: =IF(E48>F28,F28,IF(E48>0,E48,0)) -> 0 | G46: =IF(F48>G28,G28,IF(F48>0,F48,0)) -> 0 | H46: =IF(G48>H28,H28,IF(G48>0,G48,0)) -> 0 | I46: =IF(H48>I28,I28,IF(H48>0,H48,0)) -> 0 | J46: =IF(I48>J28,J28,IF(I48>0,I48,0)) -> 0 | K46: =IF(J48>K28,K28,IF(J48>0,J48,0)) -> 0 | L46: =IF(K48>L28,L28,IF(K48>0,K48,0)) -> 0 | M46: =IF(L48>M28,M28,IF(L48>0,L48,0)) -> 0 | ... CH46: =IF(CG48>CH28,CH28,IF(CG48>0,CG48,0)) -> 0
B47: DT còn lại sau đóng thuế, CPHĐ, CPĐT& trả nợ gốc | E47: =E28-E46 -> 0 | F47: =F28-F46 -> 0 | G47: =G28-G46 -> 0 | H47: =H28-H46 -> 0 | I47: =I28-I46 -> 0 | J47: =J28-J46 -> 0 | K47: =K28-K46 -> 0 | L47: =L28-L46 -> 0 | ... CH47: =CH28-CH46 -> 1243779.2
B48: =B22 -> Dư nợ vay | E48: =+D48+E35-E46 -> 0 | F48: =+E48+F35-F46 -> 0 | G48: =+F48+G35-G46 -> 0 | H48: =+G48+H35-H46+H64 -> 0 | I48: =+H48+I35-I46+I64 -> 0 | J48: =+I48+J35-J46+J64 -> 0 | K48: =+J48+K35-K46+K64 -> 339316.56 | L48: =+K48+L35-L46+L64 -> 340317 | M48: =+L48+M35-M46+M64 -> 374776.34 | N48: =+M48+N35-N46+N64 -> 562393.14 | O48: =+N48+O35-O46+O64 -> 629981.4 | ... CH48: =+CG48+CH35-CH46+CH64 -> 0
B49: =B23 -> Trả lãi vay ngân hàng | C49: =SUM(E49:BZ49) -> 108747.29 | E49: =E48*E11 -> 0 | F49: =E48*F11 -> 0 | G49: =F48*G11 -> 0 | H49: =G48*H11 -> 0 | I49: =H48*I11 -> 0 | J49: =I48*J11 -> 0 | K49: =J48*K11 -> 0 | L49: =K48*L11 -> 10179.497 | M49: =L48*M11 -> 10209.51 | ... S49: =R48*S11 -> 6042.1042
M51: =871*0.2 -> 174.2
B52: Tính toán hỗ trợ lãi suất cho khách hàng
B53: Lãi suất hỗ trợ | C53: 0.095
B54: Số lượng KH tham gia hỗ trợ lãi suất | C54: 0
B55: Lãi vay | C55: =SUM(E55:Z55) -> 0 | K55: =$C$53*SUM($E$56:K56)*3/12*$C$54 -> 0 | L55: =$C$53*SUM($E$56:L56)*3/12*$C$54 -> 0 | M55: =$C$53*SUM($E$56:M56)*3/12*$C$54 -> 0
B56: Dư nợ vay cho chương trình | C56: =SUM(E56:Z56) -> 0 | E56: =+E57+E58 -> 0 | F56: =+F57+F58 -> 0 | G56: =+G57+G58 -> 0 | H56: =+H57+H58 -> 0 | I56: =+I57+I58 -> 0 | J56: =+J57+J58 -> 0 | K56: =+K57+K58 -> 0 | L56: =+L57+L58 -> 0 | ... O56: =+O57+O58 -> 0
B57: Dự nợ hỗ trợ lãi vay nhà phố | C57: =SUM(E57:Z57) -> 0 | L57: =+'5.Doanh thu'!N21 -> 0 | M57: =+'5.Doanh thu'!O21 -> 0
B58: Dư nợ hỗ trợ lãi vay BT song lập | C58: =SUM(E58:Z58) -> 0 | M58: =+'5.Doanh thu'!P27 -> 0
B61: CHI PHÍ HOẠT ĐỘNG VÀ THUẾ VAT
B62: CƠ CẤU VỐN TÀI TRỢ | C62: =SUM(C63:C65) -> 1088399.8
B63: Vốn tự có | C63: =SUM(E63:BZ63) -> 3.2245721e-13 | D63: =C63/$C$62 -> 2.9626726e-19 | E63: =IF(E67-E65-E64>0,E67-E65-E64,0) -> 0 | F63: =IF(F67-F65-F64>0,F67-F65-F64,0) -> 0 | G63: =IF(G67-G65-G64>0,G67-G65-G64,0) -> 0 | H63: =IF(H67-H65-H64>0,H67-H65-H64,0) -> 0 | I63: =IF(I67-I65-I64>0,I67-I65-I64,0) -> 0 | J63: =IF(J67-J65-J64>0,J67-J65-J64,0) -> 0 | K63: =IF(K67-K65-K64>0,K67-K65-K64,0) -> 3.2245721e-13 | L63: =IF(L67-L65-L64>0,L67-L65-L64,0) -> 0 | ... CH63: =IF(CH67-CH65-CH64>0,CH67-CH65-CH64,0) -> 0
B64: Vay ngân hàng | C64: =SUM(E64:BZ64) -> 7.5240016e-13 | D64: =C64/$C$62 -> 6.9129027e-19 | E64: =IF(E67>E65,(E67-E65)*0.7,0) -> 0 | F64: =IF(F67>F65,(F67-F65)*0.7,0) -> 0 | G64: =IF(G67>G65,(G67-G65)*0.7,0) -> 0 | H64: =IF(H67>H65,(H67-H65)*0.7,0) -> 0 | I64: =IF(I67>I65,(I67-I65)*0.7,0) -> 0 | J64: =IF(J67>J65,(J67-J65)*0.7,0) -> 0 | K64: =IF(K67>K65,(K67-K65)*0.7,0) -> 7.5240016e-13 | L64: =IF(L67>L65,(L67-L65)*0.7,0) -> 0 | ... CH64: =IF(CH67>CH65,(CH67-CH65)*0.7,0) -> 0
B65: Huy động từ khách hàng | C65: =SUM(E65:BZ65) -> 1088399.8 | D65: =C65/$C$62 -> 1 | E65: =IF(E76>E67,E67,IF(E76>0,E76,0)) -> 0 | F65: =IF(F76>F67,F67,IF(F76>0,F76,0)) -> 0 | G65: =IF(G76>G67,G67,IF(G76>0,G76,0)) -> 0 | H65: =IF(H76>H67,H67,IF(H76>0,H76,0)) -> 0 | I65: =IF(I76>I67,I67,IF(I76>0,I76,0)) -> 0 | J65: =IF(J76>J67,J67,IF(J76>0,J76,0)) -> 0 | K65: =IF(K76>K67,K67,IF(K76>0,K76,0)) -> 0 | L65: =IF(L76>L67,L67,IF(L76>0,L76,0)) -> 0 | ... CH65: =IF(CH76>CH67,CH67,IF(CH76>0,CH76,0)) -> 0
B66: DT còn lại sau đóng thuế &CPHĐ | E66: =E76-E65 -> 0 | F66: =F76-F65 -> 0 | G66: =G76-G65 -> 0 | H66: =H76-H65 -> 0 | I66: =I76-I65 -> 0 | J66: =J76-J65 -> 0 | K66: =K76-K65 -> 0 | L66: =L76-L65 -> 0 | ... CH66: =CH76-CH65 -> 1243779.2
B67: CPHĐ (ko gồm KH) | C67: =SUM(E67:BZ67) -> 1088399.8 | D67: =C67-'4.Chi phi hoat dong'!E25 -> 0 | E67: ='4.Chi phi hoat dong'!F25 -> 0 | F67: ='4.Chi phi hoat dong'!G25 -> 0 | G67: ='4.Chi phi hoat dong'!H25 -> 0 | H67: ='4.Chi phi hoat dong'!I25 -> 0 | I67: ='4.Chi phi hoat dong'!J25 -> 0 | J67: ='4.Chi phi hoat dong'!K25 -> 0 | K67: ='4.Chi phi hoat dong'!L25 -> 1.0748574e-12 | L67: ='4.Chi phi hoat dong'!M25 -> 0 | ... CH67: ='4.Chi phi hoat dong'!CI25 -> 0
C68: =SUM(C63:C65)-C67 -> 0
B70: CHI PHÍ THUẾ TNDN
B71: CƠ CẤU VỐN TÀI TRỢ | C71: =SUM(C72:C74) -> 107451.01
B72: Vốn tự có | C72: =SUM(E72:BZ72) -> 0 | D72: =C72/$C$71 -> 0
B73: Vay ngân hàng | C73: =SUM(E73:BZ73) -> 0 | D73: =C73/$C$71 -> 0
B74: Huy động từ khách hàng | C74: =SUM(E74:BZ74) -> 107451.01 | D74: =C74/$C$71 -> 1 | F74: =F75 -> 0 | G74: =G75 -> 0 | H74: =H75 -> 0 | I74: =I75 -> 0 | J74: =J75 -> 0 | K74: =K75 -> 0 | L74: =L75 -> 0 | M74: =M75 -> 0 | ... CH74: =CH75 -> 0
B75: Thuế TNDN | C75: =SUM(E75:BZ75) -> 107451.01 | D75: =C75-'7.CF'!D33 -> 0 | F75: ='7.CF'!F33 -> 0 | G75: ='7.CF'!G33 -> 0 | H75: ='7.CF'!H33 -> 0 | I75: ='7.CF'!I33 -> 0 | J75: ='7.CF'!J33 -> 0 | K75: ='7.CF'!K33 -> 0 | L75: ='7.CF'!L33 -> 0 | M75: ='7.CF'!M33 -> 0 | ... CH75: ='7.CF'!CH33 -> 0
B76: DT còn lại sau đóng thuế | F76: ='5.Doanh thu'!H117-F74+E47 -> 0 | G76: ='5.Doanh thu'!I117-G74+F47 -> 0 | H76: ='5.Doanh thu'!J117-H74+G47 -> 0 | I76: ='5.Doanh thu'!K117-I74+H47 -> 0 | J76: ='5.Doanh thu'!L117-J74+I47 -> 0 | K76: ='5.Doanh thu'!M117-K74+J47 -> 0 | L76: ='5.Doanh thu'!N117-L74+K47 -> 0 | M76: ='5.Doanh thu'!O117-M74+L47 -> 0 | ... CH76: ='5.Doanh thu'!CJ117-CH74+CG47 -> 1243779.2

Sheet 7.CF
C2: =+Summary!B2 -> Dự án Trần Đức 1
C3: Prepared by:
C5: DÒNG TIỀN DỰ ÁN VÀ HIỆU QUẢ
B7: STT | C7: HẠNG MỤC | D7: TỔNG CỘNG | E7: CBĐT | F7: ='5.Doanh thu'!H7 -> 2026 | G7: ='5.Doanh thu'!I7 -> 2026 | H7: ='5.Doanh thu'!J7 -> 2026 | I7: ='5.Doanh thu'!K7 -> 2026 | J7: ='5.Doanh thu'!L7 -> 2027 | K7: ='5.Doanh thu'!M7 -> 2027 | L7: ='5.Doanh thu'!N7 -> 2027 | M7: ='5.Doanh thu'!O7 -> 2027 | ... CH7: ='5.Doanh thu'!CJ7 -> 2079
F8: ='5.Doanh thu'!H8 -> Q1 | G8: ='5.Doanh thu'!I8 -> Q2 | H8: ='5.Doanh thu'!J8 -> Q3 | I8: ='5.Doanh thu'!K8 -> Q4 | J8: ='5.Doanh thu'!L8 -> Q1 | K8: ='5.Doanh thu'!M8 -> Q2 | L8: ='5.Doanh thu'!N8 -> Q3 | M8: ='5.Doanh thu'!O8 -> Q4 | ... AO8: ='5.Doanh thu'!AQ8 -> Q4
B9: 1 | C9: Dòng tiền từ hoạt động đầu tư - kinh doanh | D9: =SUM(E9:CT9) -> 460951.34 | E9: =E10-E12 -> 0 | F9: =F10-F12 -> 0 | G9: =G10-G12 -> -156000 | H9: =H10-H12 -> -364000 | I9: =I10-I12 -> -4263.4453 | J9: =J10-J12 -> -4263.4453 | K9: =K10-K12 -> -489001.39 | L9: =L10-L12 -> -9956.0978 | ... CH9: =CH10-CH12 -> 0
B10: - | C10: Dòng vào: | D10: =SUM(E10:CT10) -> 5230427.3 | E10: =E11 -> 0 | F10: =F11 -> 0 | G10: =G11 -> 0 | H10: =H11 -> 0 | I10: =I11 -> 0 | J10: =J11 -> 0 | K10: =K11 -> 0 | L10: =L11 -> 0 | ... CH10: =CH11 -> 0
C11: + Doanh thu | D11: =SUM(E11:CT11) -> 5230427.3 | F11: ='5.Doanh thu'!H117 -> 0 | G11: ='5.Doanh thu'!I117 -> 0 | H11: ='5.Doanh thu'!J117 -> 0 | I11: ='5.Doanh thu'!K117 -> 0 | J11: ='5.Doanh thu'!L117 -> 0 | K11: ='5.Doanh thu'!M117 -> 0 | L11: ='5.Doanh thu'!N117 -> 0 | M11: ='5.Doanh thu'!O117 -> 0 | ... CH11: ='5.Doanh thu'!CJ117 -> 0
B12: - | C12: Dòng ra: | D12: =SUM(E12:CT12) -> 4769475.9 | E12: =E16+E13+E17 -> 0 | F12: =F16+F13+F17+F18 -> 0 | G12: =G16+G13+G17+G18 -> 156000 | H12: =H16+H13+H17+H18 -> 364000 | I12: =I16+I13+I17+I18 -> 4263.4453 | J12: =J16+J13+J17+J18 -> 4263.4453 | K12: =K16+K13+K17+K18 -> 489001.39 | L12: =L16+L13+L17+L18 -> 9956.0978 | M12: =M16+M13+M17+M18 -> 49227.63 | ... CH12: =CH16+CH13+CH17+CH18 -> 0
C13: + Chi phí đầu tư & xây dựng (không gồm lãi vay) | D13: =SUM(E13:CT13) -> 3496025.1 | E13: ='3.Du toan'!AT77 -> 0 | F13: ='3.Du toan'!AU77 -> 0 | G13: ='3.Du toan'!AV77 -> 156000 | H13: ='3.Du toan'!AW77 -> 364000 | I13: ='3.Du toan'!AX77 -> 4263.4453 | J13: ='3.Du toan'!AY77 -> 4263.4453 | K13: ='3.Du toan'!AZ77 -> 489001.39 | L13: ='3.Du toan'!BA77 -> 9956.0978 | ... CH13: ='3.Du toan'!DW77 -> 0
C14: - Giá chuyển nhượng đến hiện trạng | D14: =SUM(E14:CT14) -> 520000 | F14: =+'3.Du toan'!AU12 -> 0 | G14: =+'3.Du toan'!AV12 -> 156000 | H14: =+'3.Du toan'!AW12 -> 364000 | I14: =+'3.Du toan'!AX12 -> 0 | J14: =+'3.Du toan'!AY12 -> 0 | K14: =+'3.Du toan'!AZ12 -> 0 | L14: =+'3.Du toan'!BA12 -> 0 | M14: =+'3.Du toan'!BB12 -> 0 | ... CH14: =+'3.Du toan'!DW12 -> 0
C15: - Chi phí xây dựng và pháp lý khác | D15: =SUM(E15:CT15) -> 2976025.1 | F15: =+F13-F14 -> 0 | G15: =+G13-G14 -> 0 | H15: =+H13-H14 -> 0 | I15: =+I13-I14 -> 4263.4453 | J15: =+J13-J14 -> 4263.4453 | K15: =+K13-K14 -> 489001.39 | L15: =+L13-L14 -> 9956.0978 | M15: =+M13-M14 -> 49227.63 | ... CH15: =+CH13-CH14 -> 0
C16: + Chi phí hoạt động, thuế VAT và phí khác | D16: =SUM(E16:CT16) -> 1088399.8 | E16: ='4.Chi phi hoat dong'!F25-'4.Chi phi hoat dong'!F19 -> 0 | F16: ='4.Chi phi hoat dong'!G25-'4.Chi phi hoat dong'!G19 -> 0 | G16: ='4.Chi phi hoat dong'!H25-'4.Chi phi hoat dong'!H19 -> 0 | H16: ='4.Chi phi hoat dong'!I25-'4.Chi phi hoat dong'!I19 -> 0 | I16: ='4.Chi phi hoat dong'!J25-'4.Chi phi hoat dong'!J19 -> 0 | J16: ='4.Chi phi hoat dong'!K25-'4.Chi phi hoat dong'!K19 -> 0 | K16: ='4.Chi phi hoat dong'!L25-'4.Chi phi hoat dong'!L19 -> 1.0748574e-12 | L16: ='4.Chi phi hoat dong'!M25-'4.Chi phi hoat dong'!M19 -> 0 | ... CH16: ='4.Chi phi hoat dong'!CI25-'4.Chi phi hoat dong'!CI19 -> 0
C17: + Chi phí thuế TNDN | D17: =SUM(E17:CT17) -> 107451.01 | F17: =F33 -> 0 | G17: =G33 -> 0 | H17: =H33 -> 0 | I17: =I33 -> 0 | J17: =J33 -> 0 | K17: =K33 -> 0 | L17: =L33 -> 0 | M17: =M33 -> 0 | ... AB17: =AB33 -> 0
C18: + Tác động thuế TNDN do chênh giá vốn | D18: =SUM(E18:CT18) -> 77600 | S18: 0 | T18: 0 | Y18: =+(D54-D55)*0.2 -> 77600
B19: 2 | C19: Dòng tiền từ hoạt động tài chính | D19: =SUM(E19:CT19) -> 705227.86 | E19: =E20-E23 -> 0 | F19: =F20-F23 -> 0 | G19: =G20-G23 -> 156000 | H19: =H20-H23 -> 364000 | I19: =I20-I23 -> 4263.4453 | J19: =J20-J23 -> 4263.4453 | K19: =K20-K23 -> 489001.39 | L19: =L20-L23 -> 9956.0978 | ... CH19: =CH20-CH23 -> 0
B20: - | C20: Dòng vào: | D20: =SUM(E20:CT20) -> 1469658.6 | E20: =E21+E22 -> 0 | F20: =F21+F22 -> 0 | G20: =G21+G22 -> 156000 | H20: =H21+H22 -> 364000 | I20: =I21+I22 -> 4263.4453 | J20: =J21+J22 -> 4263.4453 | K20: =K21+K22 -> 489001.39 | L20: =L21+L22 -> 20135.595 | ... CH20: =CH21+CH22 -> 0
C21: + Vay | D21: =SUM(E21:CT21) -> 655683.49 | E21: ='6.Vay von'!E35 -> 0 | F21: ='6.Vay von'!F35+'6.Vay von'!F64 -> 0 | G21: ='6.Vay von'!G35+'6.Vay von'!G64 -> 0 | H21: ='6.Vay von'!H35+'6.Vay von'!H64 -> 0 | I21: ='6.Vay von'!I35+'6.Vay von'!I64 -> 0 | J21: ='6.Vay von'!J35+'6.Vay von'!J64 -> 0 | K21: ='6.Vay von'!K35+'6.Vay von'!K64 -> 339316.56 | L21: ='6.Vay von'!L35+'6.Vay von'!L64 -> 1000.445 | M21: ='6.Vay von'!M35+'6.Vay von'!M64 -> 34459.341 | ... CH21: ='6.Vay von'!CH35+'6.Vay von'!CH64 -> 0
C22: + Vốn chủ sở hữu | D22: =SUM(E22:CT22) -> 813975.15 | E22: ='6.Vay von'!E17 -> 0 | F22: ='6.Vay von'!F17 -> 0 | G22: ='6.Vay von'!G17 -> 156000 | H22: ='6.Vay von'!H17 -> 364000 | I22: ='6.Vay von'!I17 -> 4263.4453 | J22: ='6.Vay von'!J17 -> 4263.4453 | K22: ='6.Vay von'!K17 -> 149684.83 | L22: ='6.Vay von'!L17 -> 19135.149 | ... CH22: ='6.Vay von'!CH17 -> 0
B23: - | C23: Dòng ra: | D23: =SUM(E23:CT23) -> 764430.78 | E23: =E24+E25+E26 -> 0 | F23: =F24+F25+F26 -> 0 | G23: =G24+G25+G26 -> 0 | H23: =H24+H25+H26 -> 0 | I23: =I24+I25+I26 -> 0 | J23: =J24+J25+J26 -> 0 | K23: =K24+K25+K26 -> 0 | L23: =L24+L25+L26 -> 10179.497 | ... CH23: =CH24+CH25+CH26 -> 0
C24: + Trả nợ gốc: | D24: =SUM(E24:CT24) -> 655683.49 | E24: ='6.Vay von'!E21 -> 0 | F24: ='6.Vay von'!F21 -> 0 | G24: ='6.Vay von'!G21 -> 0 | H24: ='6.Vay von'!H21 -> 0 | I24: ='6.Vay von'!I21 -> 0 | J24: ='6.Vay von'!J21 -> 0 | K24: ='6.Vay von'!K21 -> 0 | L24: ='6.Vay von'!L21 -> 0 | ... CH24: ='6.Vay von'!CH21 -> 0
C25: + Trả lãi vay: | D25: =SUM(E25:CT25) -> 108747.29 | E25: ='6.Vay von'!E23 -> 0 | F25: ='6.Vay von'!F23 -> 0 | G25: ='6.Vay von'!G23 -> 0 | H25: ='6.Vay von'!H23 -> 0 | I25: ='6.Vay von'!I23 -> 0 | J25: ='6.Vay von'!J23 -> 0 | K25: ='6.Vay von'!K23 -> 0 | L25: ='6.Vay von'!L23 -> 10179.497 | ... CH25: ='6.Vay von'!CH23 -> 0
C26: + LNCP | D26: =SUM(E26:CT26) -> 0 | E26: 0 | F26: 0 | G26: 0 | H26: 0 | I26: 0 | J26: 0 | K26: 0 | L26: 0 | M26: 0 | N26: 0 | O26: 0 | P26: 0 | Q26: 0 | R26: 0 | S26: 0 | T26: 0 | U26: 0 | V26: 0 | W26: 0 | X26: 0 | Y26: 0 | Z26: 0 | AA26: 0 | AB26: 0 | AC26: 0 | AD26: 0 | AE26: 0 | AF26: 0 | AG26: 0 | AH26: 0 | AI26: 0 | AJ26: 0 | AK26: 0 | AL26: 0 | AM26: 0 | AN26: 0 | AO26: 0 | AP26: 0 | AQ26: 0 | AR26: 0 | AS26: 0 | AT26: 0 | AU26: 0 | AV26: 0 | AW26: 0 | AX26: 0 | AY26: 0 | AZ26: 0 | BA26: 0 | BB26: 0 | BC26: 0 | BD26: 0 | BE26: 0 | BF26: 0 | BG26: 0 | BH26: 0 | BI26: 0 | BJ26: 0 | BK26: 0 | BL26: 0 | BM26: 0 | BN26: 0 | BO26: 0 | BP26: 0 | BQ26: 0 | BR26: 0 | BS26: 0 | BT26: 0 | BU26: 0 | BV26: 0 | BW26: 0 | BX26: 0 | BY26: 0 | BZ26: 0 | CA26: 0 | CB26: 0 | CC26: 0 | CD26: 0 | CE26: 0 | CF26: 0 | CG26: 0 | CH26: 0
B27: 3 | C27: Chênh lệch dòng tiền (Net cash flow) | D27: =SUM(E27:CT27) -> 1166179.2 | E27: =E9+E19 -> 0 | F27: =F9+F19 -> 0 | G27: =G9+G19 -> 0 | H27: =H9+H19 -> 0 | I27: =I9+I19 -> 0 | J27: =J9+J19 -> 0 | K27: =K9+K19 -> 0 | L27: =L9+L19 -> 0 | ... CH27: =CH9+CH19 -> 0
B28: 4 | C28: FCFE | D28: =SUM(E28:CT28) -> 352204.05 | E28: =E27-E22 -> 0 | F28: =F27-F22 -> 0 | G28: =G27-G22 -> -156000 | H28: =H27-H22 -> -364000 | I28: =I27-I22 -> -4263.4453 | J28: =J27-J22 -> -4263.4453 | K28: =K27-K22 -> -149684.83 | L28: =L27-L22 -> -19135.149 | ... CH28: =CH27-CH22 -> 0
B29: 5 | C29: Dòng lợi nhuận trước thuế và lãi vay | D29: =SUM(E29:CT29) -> 646002.36 | E29: =E11-E13-E16 -> 0 | F29: =F11-F13-F16 -> 0 | G29: =G11-G13-G16 -> -156000 | H29: =H11-H13-H16 -> -364000 | I29: =I11-I13-I16 -> -4263.4453 | J29: =J11-J13-J16 -> -4263.4453 | K29: =K11-K13-K16 -> -489001.39 | L29: =L11-L13-L16 -> -9956.0978 | ... CH29: =CH11-CH13-CH16 -> 0
C30: Dòng lãi vay | D30: =SUM(E30:CT30) -> 108747.29 | E30: =E25 -> 0 | F30: =F25 -> 0 | G30: =G25 -> 0 | H30: =H25 -> 0 | I30: =I25 -> 0 | J30: =J25 -> 0 | K30: =K25 -> 0 | L30: =L25 -> 10179.497 | ... CH30: =CH25 -> 0
B31: 6 | C31: Dòng lợi nhuận trước thuế | D31: =SUM(E31:CT31) -> 537255.06 | E31: =E29-E30 -> 0 | F31: =F29-F30 -> 0 | G31: =G29-G30 -> -156000 | H31: =H29-H30 -> -364000 | I31: =I29-I30 -> -4263.4453 | J31: =J29-J30 -> -4263.4453 | K31: =K29-K30 -> -489001.39 | L31: =L29-L30 -> -20135.595 | ... CH31: =CH29-CH30 -> 0
B32: 7 | C32: Dòng lợi nhuận trước thuế có điều chỉnh tax impact | D32: =SUM(E32:CT32) -> 440255.06 | F32: =+F31-F18/0.8 -> 0 | G32: =+G31-G18/0.8 -> -156000 | H32: =+H31-H18/0.8 -> -364000 | I32: =+I31-I18/0.8 -> -4263.4453 | J32: =+J31-J18/0.8 -> -4263.4453 | K32: =+K31-K18/0.8 -> -489001.39 | L32: =+L31-L18/0.8 -> -20135.595 | M32: =+M31-M18/0.8 -> -59437.14 | ... CH32: =+CH31-CH18/0.8 -> 0
C33: Thuế TNDN | D33: =SUM(E33:CT33) -> 107451.01 | F33: ='4.Chi phi hoat dong'!G52 -> 0 | G33: ='4.Chi phi hoat dong'!H52 -> 0 | H33: ='4.Chi phi hoat dong'!I52 -> 0 | I33: ='4.Chi phi hoat dong'!J52 -> 0 | J33: ='4.Chi phi hoat dong'!K52 -> 0 | K33: ='4.Chi phi hoat dong'!L52 -> 0 | L33: ='4.Chi phi hoat dong'!M52 -> 0 | M33: ='4.Chi phi hoat dong'!N52 -> 0 | ... X33: ='4.Chi phi hoat dong'!Y52 -> 0 | Y33: =0.2*D31-SUM(F33:X33) -> 57459.033
C34: Tác động thuế TNDN do chênh giá vốn | D34: =SUM(E34:CT34) -> 77600 | G34: =+G18 -> 0 | H34: =+H18 -> 0 | I34: =+I18 -> 0 | J34: =+J18 -> 0 | K34: =+K18 -> 0 | L34: =+L18 -> 0 | M34: =+M18 -> 0 | N34: =+N18 -> 0 | ... Y34: =+Y18 -> 77600
B35: 8 | C35: Dòng lợi nhuận sau thuế | D35: =SUM(E35:CT35) -> 352204.05 | E35: =E31-E33 -> 0 | F35: =F31-F33-F34 -> 0 | G35: =G31-G33-G34 -> -156000 | H35: =H31-H33-H34 -> -364000 | I35: =I31-I33-I34 -> -4263.4453 | J35: =J31-J33-J34 -> -4263.4453 | K35: =K31-K33-K34 -> -489001.39 | L35: =L31-L33-L34 -> -20135.595 | M35: =M31-M33-M34 -> -59437.14 | ... CH35: =CH31-CH33-CH34 -> 0
C36: =D31-D33 -> 429804.05 | D36: =+D31*0.8-D35 -> 77600 | E36: 0 | F36: 2026 | G36: =F36+1 -> 2027 | H36: =G36+1 -> 2028 | I36: =H36+1 -> 2029 | J36: =I36+1 -> 2030 | K36: =J36+1 -> 2031 | L36: =K36+1 -> 2032 | M36: =L36+1 -> 2033 | N36: =M36+1 -> 2034 | ... BN36: =BM36+1 -> 2086
C37: FCFE tính theo năm | D37: =SUM(E37:BH37) -> 352204.05 | E37: =SUMIFS(28:28,7:7,E7) -> 0 | F37: =SUMIFS(28:28,7:7,F36) -> -524263.45 | G37: =SUMIFS(28:28,7:7,G36) -> -198061.22 | H37: =SUMIFS(28:28,7:7,H36) -> -91650.488 | I37: =SUMIFS(28:28,7:7,I36) -> 273934.65 | J37: =SUMIFS(28:28,7:7,J36) -> 892244.56 | K37: =SUMIFS(28:28,7:7,K36) -> 0 | L37: =SUMIFS(28:28,7:7,L36) -> 0 | M37: =SUMIFS(28:28,7:7,M36) -> 0 | ... BN37: =SUMIFS(28:28,7:7,BN36) -> 0
C38: Thời điểm hoàn vốn (yes= năm hoàn vốn) | E38: =IF(AND(E37>0,D37<=0),"Yes","No") -> No | F38: =IF(AND(F37>0,E37<=0),"Yes","No") -> No | G38: =IF(AND(G37>0,F37<=0),"Yes","No") -> No | H38: =IF(AND(H37>0,G37<=0),"Yes","No") -> No | I38: =IF(AND(I37>0,H37<=0),"Yes","No") -> Yes | J38: =IF(AND(J37>0,I37<=0),"Yes","No") -> No | K38: =IF(AND(K37>0,J37<=0),"Yes","No") -> No | L38: =IF(AND(L37>0,K37<=0),"Yes","No") -> No | ... BN38: =IF(AND(BN37>0,BM37<=0),"Yes","No") -> No
C40: Hệ số chiết khấu (%/năm) | D40: 0.11
C41: HIỆU QUẢ DỰ ÁN | D41: Giá trị | F41: =+D35-D28 -> 0
C43: LNTT (tr.đồng) | D43: =D31 -> 537255.06
C44: LNTT điều chỉnh tax (tr.đồng) | D44: =+D32 -> 440255.06
C45: NPV (tr.đồng) | D45: =NPV('7.CF'!$D$40,'7.CF'!$G$37:$BN$37)+'7.CF'!$F$37 -> 10965.21
C46: IRR (%) | D46: =IRR(F37:BN37) -> 0.11468721
C47: Tỷ suất lợi nhuận trên doanh thu (%) | D47: =D31/D11 -> 0.10271724
C48: LNTT/TMĐT (%) | D48: =D43/(D13+D30) -> 0.14903994
C49: LNTT/TMĐT (%) có điều chỉnh tax | D49: =D44/(D13+D30) -> 0.12213117
C50: Tỷ suất lợi nhuận trên vốn chủ sở hữu (%) | D50: =D31/D22 -> 0.66003865
C51: Thời gian hoàn vốn (năm) | D51: {=MAX(IF(38:38="Yes",36:36,0))-F36+1} -> 4
C52: NPV/TMĐT | D52: =D45/'3.Du toan'!F79 -> 0.003041859
C54: Giá trị định giá | D54: =+'8.ĐO NHAY'!C20 -> 520000
C55: Giá trị vốn điều lệ ghi nhận | D55: 132000
C58: Check bảng tính
C59: NPV và LNST | D59: =+D35-D28 -> 0
C60: LNTT | D60: =ROUND(('5.Doanh thu'!G116-'3.Du toan'!F79-'4.Chi phi hoat dong'!E25)-D43,4)=0 -> TRUE
C61: Dòng tiền ròng và cơ sở tính vay vốn | D61: ='6.Vay von'!CH28-D27 -> 77600
C62: Thuế TNDN | D62: =D33/D31=20% -> TRUE
C63: NPV quý và năm | D63: =D37-D28 -> 0

Sheet TSDĐ
A2: BƯỚC 1: KHẢO SÁT THÔNG TIN VỀ THỬA ĐẤT CẦN ĐỊNH GIÁ VÀ CÁC THÔNG TIN THỊ TRƯỜNG LIÊN QUAN
A4: A. BẢNG 1: THÔNG TIN VỀ THỬA ĐẤT XÁC ĐỊNH GIÁ
A5: STT | B5: THÔNG TIN | F5: SỐ LƯỢNG | G5: ĐVT
A6: I | B6: DIỆN TÍCH KHU ĐẤT (PHÙ HỢP QUY HOẠCH) | F6: =+'1. thong tin quy hoach'!D9 -> 26556 | G6: m2
A7: 1 | B7: Mật độ xây dựng toàn khu | F7: ='1. thong tin quy hoach'!D64 -> 0
A8: 2 | B8: Diện tích đất ngoài nhóm ở | F8: =+SUM(F9:F12) -> 0 | G8: m2
A9: 2.1 | B9: Diện tích cây xanh công cộng cấp đơn vị ở | F9: 0 | G9: m2
A10: 2.2 | B10: Diện tích cây xanh ven rạch | F10: 0 | G10: m2
A11: 2.3 | B11: Diện tích đất giao thông cấp đơn vị ở | F11: 0 | G11: m2
A12: 2.4 | B12: Diện tích đất công trình hạ tầng kỹ thuật | F12: 0 | G12: m2
A13: 3 | B13: Diện tích đất nhóm ở | F13: =SUM(F14+F17+F18) -> 26556 | G13: m2
A14: 3.1 | B14: Diện tích đất ở | F14: =SUM(F15:F16) -> 21178.41 | G14: m2
B15: Diện tích đất nhà ở chung cư | F15: =+'1. thong tin quy hoach'!D11 -> 14605.8 | G15: m2
B16: Diện tích đất nhà ở thấp tầng (liên kế, biệt thự) | F16: =+'1. thong tin quy hoach'!D37 -> 6572.61 | G16: m2
A17: 3.2 | B17: Diện tích đất giao thông nội bộ | F17: =+'1. thong tin quy hoach'!D48 -> 5377.59 | G17: m2
A18: 3.3 | B18: Diện tích đất cây xanh | F18: =+'1. thong tin quy hoach'!D47 -> 0 | G18: m2
A19: 4 | B19: Đất cở sở hạ tầng chung | F19: =+F17 -> 5377.59 | G19: m2
A20: 4.1 | B20: Đất cở sở hạ tầng chung phân bổ cho đất ở chung cư | F20: =F21*F19 -> 3708.6828 | G20: m2
B21: Tỷ lệ phân bổ cho đất ở chung cư | F21: =F15/($F$15+$F$16) -> 0.68965517
A22: 4.2 | B22: Đất cở sở hạ tầng chung phân bổ cho đất ở thấp tầng | F22: =F23*F19 -> 1668.9072 | G22: m2
B23: Tỷ lệ phân bổ cho đất ở thấp tầng | F23: =F16/(F15+F16) -> 0.31034483
A26: Theo bản đồ quy hoạch chi tiết tiết đô thị 1/500
A27: A. BẢNG 1.1: THÔNG TIN VỀ ĐẤT NHÓM Ở - CHUNG CƯ PHỨC HỢP TM-DV VÀ NHÀ Ở
A28: STT | B28: THÔNG TIN | F28: SỐ LƯỢNG | G28: ĐVT | H28: Ghi chú
A29: I | B29: DIỆN TÍCH ĐẤT CHUNG CƯ | F29: =+F15 -> 14605.8 | G29: m2
A30: 1 | B30: Mật độ xây dựng
A31: - | B31: Khối đế
A32: - | B32: Khối tháp
A33: 2 | B33: Diện tích xây dựng công trình | F33: =+'1. thong tin quy hoach'!H11 -> 7302.9 | G33: m2
A34: 3 | B34: Diện tích đất giao thông nội bộ | F34: 2359.485 | G34: m2
A35: 4 | B35: Diện tích đất cây xanh | F35: 1572.99 | G35: m2
A36: 5 | B36: Hệ số sử dụng đất (chung cư) | F36: =SUM(F37:F39) -> 0 | G36: lần
A37: - | B37: Nhà ở | F37: 0 | G37: lần
A38: - | B38: Officetel | F38: 0 | G38: lần
A39: - | B39: Thương mại, dịch vụ, văn phòng, giáo dục, để xe | F39: 0 | G39: lần
A40: II | B40: TỔNG DIỆN TÍCH SÀN XÂY DỰNG (BAO GỒM TẦNG HẦM) | F40: =SUM(F41:F46) -> 146585.35 | G40: m2
A41: 1 | B41: Tầng hầm | F41: =+'1. thong tin quy hoach'!I19 -> 18987.54 | G41: m2 | H41: 2 | I41: Số tầng hầm
A42: 2 | B42: Diện tích sàn để xe tầng nổi | F42: 0 | G42: m2
A43: 3 | B43: Diện tích sàn xây dựng căn hộ | F43: =+'1. thong tin quy hoach'!I13 -> 103768.6 | G43: m2
A44: 4 | B44: Diện tích sàn xây dựng Officetel | F44: =+'1. thong tin quy hoach'!I15 -> 8219.248 | G44: m2
A45: 5 | B45: Diện tích sàn xây dựng thương mại - văn phòng - nhà trẻ | F45: =+SUM('1. thong tin quy hoach'!I14,'1. thong tin quy hoach'!I16) -> 4321.0467 | G45: m2
A46: 6 | B46: Diện tích kỹ thuật & diện tích khác | F46: =+'1. thong tin quy hoach'!I20+'1. thong tin quy hoach'!I17 -> 11288.92 | G46: m2
A49: A. BẢNG 1.2: THÔNG TIN VỀ ĐẤT NHÓM Ở - NHÀ Ở THẤP TẦNG
A50: STT | B50: THÔNG TIN | F50: SỐ LƯỢNG | G50: ĐVT | H50: GHI CHÚ | I50: DIỆN TÍCH XÂY DỰNG NGOÀI RANH KHU ĐẤT
A51: I | B51: DIỆN TÍCH ĐẤT NHÀ THẤP TẦNG | F51: =+'1. thong tin quy hoach'!D37 -> 6572.61 | G51: m2
A52: 1 | B52: Diện tích đất | F52: =SUM(F53:F54) -> 6572.61 | G52: m2
A53: - | B53: Diện tích đất nhà ở liên kế | F53: =+'1. thong tin quy hoach'!D38 -> 6572.61 | G53: m2
A54: - | B54: Diện tích đất nhà ở biệt thự | F54: 0 | G54: m2
A55: 2 | B55: Diện tích xây dựng công trình | F55: =+'1. thong tin quy hoach'!H38 -> 4929.4575 | G55: m2
A56: 3 | B56: Tầng cao | F56: =+'1. thong tin quy hoach'!G38 -> 3 | G56: Tầng
A57: 4 | B57: Tầng hầm (bán hầm) | F57: 0 | G57: Tầng
A58: 5 | B58: Tổng số lô | F58: =+'1. thong tin quy hoach'!L38 -> 73.029 | G58: Lô
A61: B. BẢNG 2: THÔNG TIN KHẢO SÁT THỊ TRƯỜNG VỀ CHI PHÍ | K61: Trường hợp tỷ lệ diện tích mặt bằng đất xây dựng tầng hầm và diện tích mặt bằng đất xây dựng tầng nổi (Nmbxd hầm/Nmbxd nổi) | L61: Hệ số điều chỉnh
A62: STT | B62: CÁC KHOẢN CHI | F62: SỐ LƯỢNG | G62: ĐVT | H62: GHI CHÚ | L62: 1 | M62: 2
B63: CHI PHÍ XÂY DỰNG CÔNG TRÌNH | K63: Hệ số điều chỉnh (Kđc) | L63: 1 | M63: 0.92
A64: I | B64: CHI ĐẦU TƯ CƠ SỞ HẠ TẦNG | K64: Định mức Kdc cần tính | L64: =IF(AND(L69>L62,L69<=M62),(L68-(L68-L67)/(L66-L65)*(L66-L69)),0) -> 0.976
A65: 1 | B65: Chi đầu tư cơ sở hạ tầng cho chung cư | K65: Tỷ lệ diện tích xây dựng hầm/diện tích xây dựng nổi cận dưới (Ga) | L65: =L62 -> 1
A66: 1.1 | B66: Diện tích | F66: =F20+F29 -> 18314.483 | G66: m2 | H66: Bằng diện tích đất chung cư + diện tích đất cơ sở hạ tầng phân bổ cho đất ở chung cư – diện tích xây dựng công trình | K66: Tỷ lệ diện tích xây dựng hầm/diện tích xây dựng nổi cận trên (Gb) | L66: =M62 -> 2
A67: 1.2 | B67: Đơn giá | F67: =+L73 -> 981242 | G67: đ/m2 | H67: Tính theo QĐ 425/BXD cho khu đô thị | K67: Hệ số điều chỉnh (Kđc) tương ứng Ga | L67: =L63 -> 1
A68: 1.3 | B68: Tiến độ thi công | G68: % | H68: Xem cột (2) Bảng 4 bên dưới | K68: Hệ số điều chỉnh (Kđc) tương ứng Gb | L68: =M63 -> 0.92
A69: 2 | B69: Chi đầu tư cơ sở hạ tầng cho nhà thấp tầng | K69: Tỷ lệ đất xd hầm/tỷ lệ đất xây dựng nổi thực tế | L69: =+(F41/H41)/F33 -> 1.3
A70: 2.1 | B70: Diện tích | F70: =F22+F51 -> 8241.5172 | G70: m2 | H70: Bằng diện tích đất ở thấp tầng+ diện tích đất cơ sở hạ tầng phân bổ cho đất ở thấp tầng
A71: 2.2 | B71: Đơn giá | F71: =L73 -> 981242 | G71: đ/m2 | H71: Tính theo QĐ 425/BXD cho khu đô thị | K71: Công trình hạ tầng kỹ thuật khu đô thị 20-50ha (nhỏ nhất) | L71: 925700
A72: 2.3 | B72: Tiến độ thi công | G72: % | H72: Xem cột (2) Bảng 4 bên dưới | K72: Hệ số điều chỉnh Bình Dương (vùng 8) | L72: 1.06
A73: II | B73: CHI XÂY LẮP VÀ THIẾT BỊ | L73: =L71*L72 -> 981242
A74: 1 | B74: Chi xây lắp thiết bị chung cư
B75: Diện tích sàn xây dựng trong chỉ giới | F75: =F40-F41+L83 -> 142203.61 | G75: m2
B76: Diện tích sàn xây dựng hầm ngoài chỉ giới | F76: =L84 -> 4381.74
B77: Đơn giá xây lắp (bao gồm VAT) | F77: =L82 -> 15368913 | G77: đ/m2 | H77: Tính theo QĐ 425/QĐ-BXD
B78: Đơn giá xây lắp phần hầm mở rộng | F78: =IF(L88<0,0,L88) -> 16526607 | G78: đ/m2 | H78: Tính theo QĐ 425/QĐ-BXD
B79: Tiến độ thi công | G79: % | H79: Xem cột (3) Bảng 4 bên dưới | K79: Chung cư 30 tầng 1 tầng hầm
A80: 2 | B80: Chi xây lắp thiết bị thấp tầng | K80: =K79 -> Chung cư 30 tầng 1 tầng hầm | L80: 14679000
B81: Diện tích sàn xây dựng | F81: =+'1. thong tin quy hoach'!I38 -> 25975.746 | K81: Hệ số điều chỉnh Bình Dương (vùng 8) | L81: 1.047
B82: Đơn giá xây lắp (bao gồm VAT) | F82: 8370000 | H82: Tính theo QĐ 425/QĐ-BXD | K82: Suất vốn đầu tư sau điều chỉnh | L82: =L80*L81 -> 15368913
B83: Đơn giá xây lắp phần hầm mở rộng | K83: Diện tích sàn tầng hầm trong chỉ giới | L83: =F33*H41 -> 14605.8
B84: Tiến độ thi công | K84: Diện tích sàn tầng hầm tăng thêm | L84: =F41-F33*H41 -> 4381.74
A85: III | B85: CÁC CHI PHÍ KHÁC | K85: Suất vốn đầu tư chung cư tương ứng không hầm | L85: 14508000
A86: 1 | B86: Chi phí khác cho chung cư | K86: Hệ số điều chỉnh tương ứng (Kdc) | L86: =L64 -> 0.976
B87: Chi phí quản lý kinh doanh (%/doanh thu) | F87: 0.02 | K87: Suất vốn đầu tư phần hầm mở rộng | L87: =(L80*(F40-F41+L83)-L85*(F40-F41))/L83*L86 -> 15784725
B88: Chi phí hoạt động, bảo trì sửa chữa (%/doanh thu phần thương mại, văn phòng) | F88: 0.15 | K88: Suất vốn đầu tư hẩm mở rộng sau điều chỉnh | L88: =L87*L81 -> 16526607
A89: 2 | B89: Chi phí khác cho thấp tầng
B90: Chi phí quản lý kinh doanh (%/doanh thu) | F90: 0.02
B91: Chi phí hoạt động, bảo trì sửa chữa (%/doanh thu phần thương mại, văn phòng) | F91: 0.15
A92: 3 | B92: Lãi vay ngân hàng | F92: 0.15
A93: 4 | B93: Tỷ lệ vay | F93: 0 | G93: Chi phí xây lắp
A94: 5 | B94: Lợi nhuận nhà đầu tư (tính trên chi phí) | F94: 0.15
A95: 6 | B95: Lãi suất chiết khấu | F95: 0.12
A96: 7 | B96: Tỷ giá hối đoái | F96: 26000
A99: C. BẢNG 3: CÁC THÔNG TIN KHẢO SÁT VỀ DOANH THU
A100: STT | B100: CÁC KHOẢN THU | F100: SỐ LƯỢNG | G100: ĐVT | H100: GHI CHÚ
A101: I | B101: BÁN ĐẤT NỀN NHÀ LIÊN KẾ
A102: 1 | B102: Diện tích đất nền nhà liên kế bán | F102: =F53 -> 6572.61 | G102: m2 | H102: Bảng 1.2
A103: 2 | B103: Đơn giá bán (bao gồm VAT) | F103: 70000000 | G103: đ/m2 | H103: Khảo sát thông tin từ thị trường
A104: 3 | B104: Tỷ lệ bán hàng năm | G104: % | H104: Xem cột (4) Bảng 4 bên dưới
A105: II | B105: BÁN ĐẤT NỀN BIỆT THỰ
A106: 1 | B106: Diện tích đất nền biệt thự bán | F106: =F54 -> 0 | G106: m2 | H106: Bảng 1.2
A107: 2 | B107: Đơn giá bán (bao gồm VAT) | G107: đ/m2 | H107: Khảo sát thông tin từ thị trường
A108: 3 | B108: Tỷ lệ bán hàng năm | G108: % | H108: Xem cột (5) Bảng 4 bên dưới
A109: III | B109: CĂN HỘ BÁN
A110: 1 | B110: Diện tích sàn xây dựng | F110: =F43 -> 103768.6 | G110: m2 | H110: Bảng 1.1
...

Sheet 8.ĐO NHAY
B2: =+Summary!B2 -> Dự án Trần Đức 1
B3: Prepared by: TIGER CAPITAL
B5: PHÂN TÍCH ĐỘ NHẠY
B6: Thuế VAT | C6: 0.1 | I6: Giá sản phẩm thấp tầng | N6: BẢNG TÍNH NGHĨA VỤ NOXH
B7: Hạng mục tính toán | C7: Info nhập | D7: info bảng | E7: bước nhảy | F7: đơn vị | G7: ghi chú | I7: Giá nhà | J7: Giá đất | K7: Giá 1 căn | N7: STT | O7: Hạng mục | P7: Giá trị
B8: Giá bán căn hộ | C8: 47.5 | D8: 47.5 | E8: 2 | F8: trđ/m² | G8: (chưa VAT) | H8: =C8-D8 -> 0 | N8: 1 | O8: Giá đất ở (tr/m2) | P8: =+T27 -> 24.553307
B9: Giá bán căn shop | C9: 50 | D9: 50 | E9: 1 | F9: trđ/m² | G9: (chưa VAT) | H9: =C9-D9 -> 0 | N9: 2 | O9: 2 lô đất dự kiến nhà ở xã hội (CT2 & CT3) | P9: =+'1. thong tin quy hoach'!D21+'1. thong tin quy hoach'!D29 -> 0
B10: Giá bán căn TM | C10: 0 | D10: 0 | E10: 3 | F10: trđ/m² | G10: (chưa VAT) | H10: =C10-D10 -> 0 | N10: 3 | O10: Giá trị nghĩa vụ tài chính NOXH | P10: =+P8*P9 -> 0
B11: Giá bán căn officetel | C11: =+C8*0.95 -> 45.125 | D11: 49.4 | E11: 1 | F11: trđ/m² | G11: (chưa VAT) | H11: =C11-D11 -> -4.275
B12: Giá bán nhà phố liên kế | C12: 80 | D12: 80 | E12: 1 | F12: trđ/m² | G12: (chưa VAT) | H12: =C12-D12 -> 0 | I12: =IFERROR('3.Du toan'!E61/10^6,0) -> 7.49 | J12: =IFERROR(('5.Doanh thu'!E98*'1. thong tin quy hoach'!J38-I12*'1. thong tin quy hoach'!I38)/'1. thong tin quy hoach'!J38,0) -> 57.903079 | K12: =IFERROR(C12*'1. thong tin quy hoach'!J38/'1. thong tin quy hoach'!L38,0) -> 7200
E13: 1 | F13: trđ/m² | G13: (chưa VAT) | H13: =C13-D13 -> 0
E14: 1 | F14: trđ/m² | G14: (chưa VAT) | H14: =C14-D14 -> 0
B15: Chi phí XD chung cư … | C15: 13 | D15: 13 | F15: trđ/m² | G15: (bao gồm VAT) | H15: =C15-D15 -> 0
B16: Chi phí XD căn hộ ở A2-3 & A2-4 | C16: 13 | D16: 13 | E16: 0.5 | F16: trđ/m² | G16: (bao gồm VAT) | H16: =C16-D16 -> 0
B17: Chi phí XD nhà phố | C17: 7 | D17: 7 | E17: 0.5 | F17: trđ/m² | G17: (bao gồm VAT) | H17: =C17-D17 -> 0
B18: Chi phí XD BT | E18: 0.5 | F18: trđ/m² | G18: (bao gồm VAT) | H18: =C18-D18 -> 0
B19: Chi phí XD BT đơn lập | E19: 0.5 | F19: trđ/m² | G19: (bao gồm VAT) | H19: =C19-D19 -> 0
B20: Chi phí mua đất | C20: 520000 | D20: 520000 | E20: 20000 | F20: triệu | H20: =C20-D20 -> 0 | I20: =+C20-'3.Du toan'!F13 -> 35262.06 | T20: 55
B21: LUR | C21: 0 | D21: 0
B22: Thuế VAT | C22: 0.1 | D22: 0.1 | H22: =C22-D22 -> 0
B23: Lãi suất | C23: 0.125 | D23: 0.125 | E23: 0.005 | H23: =C23-D23 -> 0
N25: BẢNG TÍNH ĐƠN GIÁ ĐẤT ĐẤU GIÁ
B26: Độ nhạy NPV theo giá bán Giá bán và Suất xây dựng thiết bị | N26: STT | O26: Hạng mục | P26: Đơn giá bảng giá đất | Q26: Tỷ trọng giá | R26: Diện tích (m2) | S26: Diện tích theo tỷ trọng | T26: Đơn giá đất với giá đất | U26: Giá trị đấu giá
B27: Suất đầu tư xây dựng (tr.đ/m2) | C27: =Summary!E110 -> 10965.21 | D27: =E27-$E$16 -> 11 | E27: =F27-$E$16 -> 11.5 | F27: =G27-$E$16 -> 12 | G27: =H27-$E$16 -> 12.5 | H27: =D16 -> 13 | I27: =H27+$E$16 -> 13.5 | J27: =I27+$E$16 -> 14 | K27: =J27+$E$16 -> 14.5 | L27: =K27+$E$16 -> 15 | N27: 1 | O27: Giá đất ở | P27: 20000 | Q27: 1 | R27: =+'1. thong tin quy hoach'!D10 -> 21178.41 | S27: =+Q27*R27 -> 21178.41 | T27: =+C20/SUM(S27:S30) -> 24.553307 | U27: =+T27*R27 -> 520000
B28: Giá bán căn hộ (tr.đ/m2) | C28: =C29+$E$8 -> 55.5 | D28: 536780.17 | E28: 488099.61 | F28: 439419.05 | G28: 390259.68 | H28: 341044.3 | I28: 291828.92 | J28: 242613.53 | K28: 193398.15 | L28: 144182.77 | N28: 2 | O28: Đất giáo dục | P28: 9600 | Q28: 0.34 | R28: =+'1. thong tin quy hoach'!D44 -> 0 | S28: =+Q28*R28 -> 0 | T28: =+Q28*$T$27 -> 8.3481243 | U28: =+T28*R28 -> 0
C29: =C30+$E$8 -> 53.5 | D29: 454912.23 | E29: 406178.05 | F29: 356962.67 | G29: 307747.29 | H29: 258531.9 | I29: 209316.52 | J29: 160101.14 | K29: 110885.15 | L29: 61614.585 | N29: 3 | O29: Giá đất y tế | P29: 9600 | Q29: 0.34 | R29: =+'1. thong tin quy hoach'!D46 -> 0 | S29: =+Q29*R29 -> 0 | T29: =+Q29*$T$27 -> 8.3481243 | U29: =+T29*R29 -> 0
C30: =C31+$E$8 -> 51.5 | D30: 372881.23 | E30: 323665.85 | F30: 274450.47 | G30: 225235.08 | H30: 176019.7 | I30: 126804.32 | J30: 77578.333 | K30: 28307.772 | L30: -20962.789 | N30: 4 | O30: Đất văn hóa | P30: 9600 | Q30: 0.34 | R30: =+'1. thong tin quy hoach'!D45 -> 0 | S30: =+Q30*R30 -> 0 | T30: =+Q30*$T$27 -> 8.3481243 | U30: =+T30*R30 -> 0
C31: =C32+$E$8 -> 49.5 | D31: 290369.25 | E31: 241153.86 | F31: 191938.48 | G31: 142723.1 | H31: 93507.714 | I31: 44271.681 | J31: -4998.8797 | K31: -54269.441 | L31: -103540 | O31: TỔNG CỘNG | P31: =SUM(P27:P30) -> 48800 | U31: =SUM(U27:U30) -> 520000
C32: =D8 -> 47.5 | D32: 207857.5 | E32: 158642.12 | F32: 109426.73 | G32: 60211.35 | H32: 10965.21 | I32: -38305.352 | J32: -87575.913 | K32: -136846.47 | L32: -186117.04
C33: =C32-$E$8 -> 45.5 | D33: 125346.02 | E33: 76130.636 | F33: 26915.253 | G33: -22341.062 | H33: -71611.623 | I33: -120882.18 | J33: -170152.75 | K33: -217867.54 | L33: -262198.25
C34: =C33-$E$8 -> 43.5 | D34: 42834.837 | E34: -6380.5458 | F34: -55647.11 | G34: -104917.67 | H34: -154188.23 | I34: -203458.79 | J34: -249528.03 | K34: -293858.74 | L34: -338189.46
C35: =C34-$E$8 -> 41.5 | D35: -39682.345 | E35: -88952.906 | F35: -138223.47 | G35: -187494.03 | H35: -236764.59 | I35: -281188.52 | J35: -325519.24 | K35: -369849.95 | L35: -414180.66
C36: =C35-$E$8 -> 39.5 | D36: -122258.42 | E36: -171528.98 | F36: -220799.54 | G36: -268518.3 | H36: -312849.01 | I36: -357179.73 | J36: -401510.44 | K36: -445841.15 | L36: -490171.86
B38: Độ nhạy LNTT theo Giá bán và Suất xây dựng thiết bị
B39: Suất đầu tư xây dựng (tr.đ/m2) | C39: =Summary!E108 -> 440255.06 | D39: =D27 -> 11 | E39: =E27 -> 11.5 | F39: =F27 -> 12 | G39: =G27 -> 12.5 | H39: =H27 -> 13 | I39: =I27 -> 13.5 | J39: =J27 -> 14 | K39: =K27 -> 14.5 | L39: =L27 -> 15
B40: Giá bán căn hộ (tr.đ/m2) | C40: =C28 -> 55.5 | D40: 1345140.9 | E40: 1263446.2 | F40: 1181751.5 | G40: 1099258.1 | H40: 1016671.3 | I40: 934084.41 | J40: 851497.56 | K40: 768910.7 | L40: 686323.85
C41: =C29 -> 53.5 | D41: 1202124.6 | E41: 1120340.5 | F41: 1037753.6 | G41: 955166.77 | H41: 872579.91 | I41: 789993.06 | J41: 707406.2 | K41: 624818.33 | L41: 542139.43
C42: =C30 -> 51.5 | D42: 1058836.1 | E42: 976249.2 | F42: 893662.35 | G42: 811075.49 | H42: 728488.64 | I42: 645901.78 | J42: 563297.24 | K42: 480618.34 | L42: 397939.44
C43: =C31 -> 49.5 | D43: 914744.87 | E43: 832158.02 | F43: 749571.16 | G43: 666984.31 | H43: 584397.46 | I43: 501776.15 | J43: 419097.25 | K43: 336418.35 | L43: 253739.44
C44: =C32 -> 47.5 | D44: 770653.79 | E44: 688066.94 | F44: 605480.08 | G44: 522893.23 | H44: 440255.06 | I44: 357576.16 | J44: 274897.26 | K44: 192218.35 | L44: 109539.45
C45: =C33 -> 45.5 | D45: 626562.82 | E45: 543975.96 | F45: 461389.11 | G45: 378733.97 | H45: 296055.07 | I45: 213376.17 | J45: 130697.26 | K45: 48018.358 | L45: -34660.545
C46: =C34 -> 43.5 | D46: 482471.97 | E46: 399885.12 | F46: 317212.88 | G46: 234533.98 | H46: 151855.07 | I46: 69176.171 | J46: -13502.732 | K46: -96181.635 | L46: -178860.54
C47: =C35 -> 41.5 | D47: 338370.69 | E47: 255691.79 | F47: 173012.89 | G47: 90333.984 | H47: 7655.0808 | I47: -75023.823 | J47: -157702.73 | K47: -240381.63 | L47: -323060.53
C48: =C36 -> 39.5 | D48: 194170.7 | E48: 111491.8 | F48: 28812.894 | G48: -53866.01 | H48: -136544.91 | I48: -219223.82 | J48: -301902.72 | K48: -384581.62 | L48: -467260.53
B50: Độ nhạy LNTT/TMĐT theo Giá bán và Suất xây dựng thiết bị
B51: Suất đầu tư xây dựng (tr.đ/m2) gồm V - All in | D51: =+(D52*1.055)*1.1 -> 12.7655 | E51: =+(E52*1.055)*1.1 -> 13.34575 | F51: =+(F52*1.055)*1.1 -> 13.926 | G51: =+(G52*1.055)*1.1 -> 14.50625 | H51: =+(H52*1.055)*1.1 -> 15.0865 | I51: =+(I52*1.055)*1.1 -> 15.66675 | J51: =+(J52*1.055)*1.1 -> 16.247 | K51: =+(K52*1.055)*1.1 -> 16.82725 | L51: =+(L52*1.055)*1.1 -> 17.4075
B52: Suất đầu tư xây dựng (tr.đ/m2) | C52: =Summary!E112 -> 0.12213117 | D52: =D39 -> 11 | E52: =E39 -> 11.5 | F52: =F39 -> 12 | G52: =G39 -> 12.5 | H52: =H39 -> 13 | I52: =I39 -> 13.5 | J52: =J39 -> 14 | K52: =K39 -> 14.5 | L52: =L39 -> 15
B53: Giá bán căn hộ (chưa VAT, tim tường) (tr.đ/m2) | C53: =C40 -> 55.5 | D53: 0.41577353 | E53: 0.38001811 | F53: 0.34613579 | G53: 0.31368364 | H53: 0.28282727 | I53: 0.25348348 | J53: 0.22554372 | K53: 0.19890956 | L53: 0.17349158
C54: =C41 -> 53.5 | D54: 0.37140322 | E54: 0.33682024 | F54: 0.3037435 | G54: 0.27237054 | H54: 0.24257303 | I54: 0.21423519 | J54: 0.18725235 | K54: 0.16152927 | L54: 0.13695389
C55: =C42 -> 51.5 | D55: 0.32696071 | E55: 0.29327898 | F55: 0.26137675 | G55: 0.23111663 | H55: 0.202375 | I55: 0.17504038 | J55: 0.14900652 | K55: 0.12416627 | L55: 0.10045994
C56: =C43 -> 49.5 | D56: 0.28224747 | E56: 0.24980344 | F56: 0.21907225 | G56: 0.18992177 | H56: 0.16223308 | I56: 0.13588832 | J56: 0.11078513 | K56: 0.086853831 | L56: 0.064014246
C57: =C44 -> 47.5 | D57: 0.23760353 | E57: 0.20639345 | F57: 0.17682987 | G57: 0.14878584 | H57: 0.12213117 | I57: 0.096768168 | J57: 0.072616658 | K57: 0.049591858 | L57: 0.027616721
C58: =C45 -> 45.5 | D58: 0.19302873 | E58: 0.16304888 | F58: 0.13464946 | G58: 0.1076872 | H58: 0.08206897 | I58: 0.05770347 | J58: 0.034501005 | K58: 0.012380245 | L58: -0.0087327306
C59: =C46 -> 43.5 | D59: 0.14852292 | E59: 0.11976957 | F59: 0.092503681 | G59: 0.066636482 | H59: 0.042064948 | I59: 0.018694111 | J59: -0.0035619394 | K59: -0.024781108 | L59: -0.045034206
C60: =C47 -> 41.5 | D60: 0.10408234 | E60: 0.076522313 | F60: 0.050414427 | G60: 0.025646857 | H60: 0.002118974 | I60: -0.020260025 | J60: -0.041572286 | K60: -0.061892304 | L60: -0.081287799
C61: =C48 -> 39.5 | D61: 0.059678514 | E61: 0.033340621 | F61: 0.0083894152 | G61: -0.015281808 | H61: -0.037769079 | I61: -0.059159056 | J61: -0.079530142 | K61: -0.098953445 | L61: -0.11749361
B63: Độ nhạy IRR theo Giá bán và Giá thương quyền
B64: Đơn giá đầu vào (tr.đồng/m2)(bao gồm giá mua và thiệt hại thuế) | D64: =+D65/'1. thong tin quy hoach'!$D$54 -> 14.369498 | E64: =+E65/'1. thong tin quy hoach'!$D$54 -> 15.219764 | F64: =+F65/'1. thong tin quy hoach'!$D$54 -> 16.07003 | G64: =+G65/'1. thong tin quy hoach'!$D$54 -> 16.920296 | H64: =+H65/'1. thong tin quy hoach'!$D$54 -> 17.770562 | I64: =+I65/'1. thong tin quy hoach'!$D$54 -> 18.620829 | J64: =+J65/'1. thong tin quy hoach'!$D$54 -> 19.471095 | K64: =+K65/'1. thong tin quy hoach'!$D$54 -> 20.321361 | L64: =+L65/'1. thong tin quy hoach'!$D$54 -> 21.171627
B65: TỔNG GIÁ TRỊ ĐẦU VÀO (GỒM GIÁ MUA VÀ THIỆT HẠI THUẾ) (tr.đồng): | D65: =+D67+D66 -> 405600 | E65: =+E67+E66 -> 429600 | F65: =+F67+F66 -> 453600 | G65: =+G67+G66 -> 477600 | H65: =+H67+H66 -> 501600 | I65: =+I67+I66 -> 525600 | J65: =+J67+J66 -> 549600 | K65: =+K67+K66 -> 573600 | L65: =+L67+L66 -> 597600
B66: Thiệt hại thuế cho chênh lệch giá mua cp và giá sổ sách (tr.đồng) | D66: =+D96 -> 45600 | E66: =+E96 -> 49600 | F66: =+F96 -> 53600 | G66: =+G96 -> 57600 | H66: =+H96 -> 61600 | I66: =+I96 -> 65600 | J66: =+J96 -> 69600 | K66: =+K96 -> 73600 | L66: =+L96 -> 77600
B67: Giá mua dự án /cổ phần (tr.đồng) | C67: =+Summary!E111 -> 0.11468721 | D67: =E67-$E$20 -> 360000 | E67: =F67-$E$20 -> 380000 | F67: =G67-$E$20 -> 400000 | G67: =H67-$E$20 -> 420000 | H67: =I67-$E$20 -> 440000 | I67: =J67-$E$20 -> 460000 | J67: =K67-$E$20 -> 480000 | K67: =L67-$E$20 -> 500000 | L67: =D20 -> 520000
B68: Giá bán căn hộ (chưa VAT, tim tường) (tr.đ/m2) | C68: =C53 -> 55.5 | D68: 0.34799042 | E68: 0.3327291 | F68: 0.31827392 | G68: 0.30455058 | H68: 0.29149431 | I68: 0.27904838 | J68: 0.26716281 | K68: 0.25579338 | L68: 0.24490074
C69: =C54 -> 53.5 | D69: 0.31279946 | E69: 0.29822451 | F69: 0.28441133 | G69: 0.27129028 | H69: 0.25880061 | I69: 0.24688906 | J69: 0.23550864 | K69: 0.22461774 | L69: 0.21417933
C70: =C55 -> 51.5 | D70: 0.27626088 | E70: 0.2624009 | F70: 0.24925659 | G70: 0.23676315 | H70: 0.22486398 | I70: 0.2135094 | J70: 0.20265554 | K70: 0.19226352 | L70: 0.18229868
C71: =C56 -> 49.5 | D71: 0.23827338 | E71: 0.22515885 | F71: 0.21271209 | G71: 0.20087331 | H71: 0.18959019 | I71: 0.17881677 | J71: 0.16851242 | K71: 0.15864106 | L71: 0.14917052
C72: =C57 -> 47.5 | D72: 0.19871426 | E72: 0.1863778 | F72: 0.17465934 | G72: 0.16350423 | H72: 0.15286463 | I72: 0.14269841 | J72: 0.13296826 | K72: 0.12364106 | L72: 0.11468721
C73: =C58 -> 45.5 | D73: 0.15746924 | E73: 0.14594505 | F73: 0.13498718 | G73: 0.12454631 | H73: 0.11457918 | I73: 0.10504763 | J73: 0.095917841 | K73: 0.087159686 | L73: 0.07874624
C74: =C59 -> 43.5 | D74: 0.11444445 | E74: 0.10376725 | F74: 0.093602862 | G74: 0.083907454 | H74: 0.074642477 | I74: 0.065773853 | J74: 0.057271323 | K74: 0.049107891 | L74: 0.041259385
C75: =C60 -> 41.5 | D75: 0.069536024 | E75: 0.059740445 | F75: 0.050402536 | G75: 0.041484039 | H75: 0.032951218 | I75: 0.024774178 | J75: 0.016926309 | K75: 0.0093838239 | L75: 0.0021253741
C76: =C61 -> 39.5 | D76: 0.023503133 | E76: 0.014285214 | F76: 0.0054904436 | G76: -0.0029160879 | H76: -0.010965214 | I76: -0.018684296 | J76: -0.026097724 | K76: -0.033227331 | L76: -0.04009273
B78: Độ nhạy NPV theo Giá bán và Giá thương quyền
B79: Đơn giá đầu vào (tr.đồng/m2)(bao gồm giá mua và thiệt hại thuế) | D79: =+D80/'1. thong tin quy hoach'!$D$54 -> 14.369498 | E79: =+E80/'1. thong tin quy hoach'!$D$54 -> 15.219764 | F79: =+F80/'1. thong tin quy hoach'!$D$54 -> 16.07003 | G79: =+G80/'1. thong tin quy hoach'!$D$54 -> 16.920296 | H79: =+H80/'1. thong tin quy hoach'!$D$54 -> 17.770562 | I79: =+I80/'1. thong tin quy hoach'!$D$54 -> 18.620829 | J79: =+J80/'1. thong tin quy hoach'!$D$54 -> 19.471095 | K79: =+K80/'1. thong tin quy hoach'!$D$54 -> 20.321361 | L79: =+L80/'1. thong tin quy hoach'!$D$54 -> 21.171627
B80: =+B65 -> TỔNG GIÁ TRỊ ĐẦU VÀO (GỒM GIÁ MUA VÀ THIỆT HẠI THUẾ) (tr.đồng): | D80: =+D82+D81 -> 405600 | E80: =+E82+E81 -> 429600 | F80: =+F82+F81 -> 453600 | G80: =+G82+G81 -> 477600 | H80: =+H82+H81 -> 501600 | I80: =+I82+I81 -> 525600 | J80: =+J82+J81 -> 549600 | K80: =+K82+K81 -> 573600 | L80: =+L82+L81 -> 597600
B81: =+B66 -> Thiệt hại thuế cho chênh lệch giá mua cp và giá sổ sách (tr.đồng) | D81: =+D96 -> 45600 | E81: =+E96 -> 49600 | F81: =+F96 -> 53600 | G81: =+G96 -> 57600 | H81: =+H96 -> 61600 | I81: =+I96 -> 65600 | J81: =+J96 -> 69600 | K81: =+K96 -> 73600 | L81: =+L96 -> 77600
B82: =+B67 -> Giá mua dự án /cổ phần (tr.đồng) | C82: =+Summary!E110 -> 10965.21 | D82: =D67 -> 360000 | E82: =E67 -> 380000 | F82: =F67 -> 400000 | G82: =G67 -> 420000 | H82: =H67 -> 440000 | I82: =I67 -> 460000 | J82: =J67 -> 480000 | K82: =K67 -> 500000 | L82: =L67 -> 520000
B83: Giá bán căn hộ (tr.đ/m2) | C83: =C68 -> 55.5 | D83: 503564.97 | E83: 483249.88 | F83: 462934.8 | G83: 442619.72 | H83: 422304.63 | I83: 401989.55 | J83: 381674.47 | K83: 361359.38 | L83: 341044.3
C84: =C69 -> 53.5 | D84: 421052.57 | E84: 400737.49 | F84: 380422.4 | G84: 360107.32 | H84: 339792.24 | I84: 319477.15 | J84: 299162.07 | K84: 278846.99 | L84: 258531.9
C85: =C70 -> 51.5 | D85: 338540.37 | E85: 318225.28 | F85: 297910.2 | G85: 277595.12 | H85: 257280.03 | I85: 236964.95 | J85: 216649.87 | K85: 196334.78 | L85: 176019.7
C86: =C71 -> 49.5 | D86: 256028.38 | E86: 235713.3 | F86: 215398.21 | G86: 195083.13 | H86: 174768.05 | I86: 154452.96 | J86: 134137.88 | K86: 113822.8 | L86: 93507.714
C87: =C72 -> 47.5 | D87: 173485.88 | E87: 153170.79 | F87: 132855.71 | G87: 112540.63 | H87: 92225.543 | I87: 71910.459 | J87: 51595.376 | K87: 31280.293 | L87: 10965.21
C88: =C73 -> 45.5 | D88: 90909.043 | E88: 70593.96 | F88: 50278.877 | G88: 29963.793 | H88: 9648.71 | I88: -10666.373 | J88: -30981.457 | K88: -51296.54 | L88: -71611.623
C89: =C74 -> 43.5 | D89: 8332.4343 | E89: -11982.649 | F89: -32297.732 | G89: -52612.816 | H89: -72927.899 | I89: -93242.982 | J89: -113558.07 | K89: -133873.15 | L89: -154188.23
C90: =C75 -> 41.5 | D90: -74243.923 | E90: -94559.006 | F90: -114874.09 | G90: -135189.17 | H90: -155504.26 | I90: -175819.34 | J90: -196134.42 | K90: -216449.51 | L90: -236764.59
C91: =C76 -> 39.5 | D91: -150423.01 | E91: -170726.26 | F91: -191029.51 | G91: -211332.76 | H91: -231636.01 | I91: -251939.26 | J91: -272242.51 | K91: -292545.76 | L91: -312849.01
B93: Độ nhạy LNTT/TMĐT theo Giá bán và Giá thương quyền
B94: Đơn giá đầu vào (tr.đồng/m2)(bao gồm giá mua và thiệt hại thuế) | D94: =+D95/'1. thong tin quy hoach'!$D$54 -> 14.369498 | E94: =+E95/'1. thong tin quy hoach'!$D$54 -> 15.219764 | F94: =+F95/'1. thong tin quy hoach'!$D$54 -> 16.07003 | G94: =+G95/'1. thong tin quy hoach'!$D$54 -> 16.920296 | H94: =+H95/'1. thong tin quy hoach'!$D$54 -> 17.770562 | I94: =+I95/'1. thong tin quy hoach'!$D$54 -> 18.620829 | J94: =+J95/'1. thong tin quy hoach'!$D$54 -> 19.471095 | K94: =+K95/'1. thong tin quy hoach'!$D$54 -> 20.321361 | L94: =+L95/'1. thong tin quy hoach'!$D$54 -> 21.171627
B95: =+B65 -> TỔNG GIÁ TRỊ ĐẦU VÀO (GỒM GIÁ MUA VÀ THIỆT HẠI THUẾ) (tr.đồng): | D95: =+D97+D96 -> 405600 | E95: =+E97+E96 -> 429600 | F95: =+F97+F96 -> 453600 | G95: =+G97+G96 -> 477600 | H95: =+H97+H96 -> 501600 | I95: =+I97+I96 -> 525600 | J95: =+J97+J96 -> 549600 | K95: =+K97+K96 -> 573600 | L95: =+L97+L96 -> 597600
B96: =+B66 -> Thiệt hại thuế cho chênh lệch giá mua cp và giá sổ sách (tr.đồng) | D96: =+(D97-'7.CF'!$D$55)*0.2 -> 45600 | E96: =+(E97-'7.CF'!$D$55)*0.2 -> 49600 | F96: =+(F97-'7.CF'!$D$55)*0.2 -> 53600 | G96: =+(G97-'7.CF'!$D$55)*0.2 -> 57600 | H96: =+(H97-'7.CF'!$D$55)*0.2 -> 61600 | I96: =+(I97-'7.CF'!$D$55)*0.2 -> 65600 | J96: =+(J97-'7.CF'!$D$55)*0.2 -> 69600 | K96: =+(K97-'7.CF'!$D$55)*0.2 -> 73600 | L96: =+(L97-'7.CF'!$D$55)*0.2 -> 77600
B97: =+B67 -> Giá mua dự án /cổ phần (tr.đồng) | C97: =Summary!E112 -> 0.12213117 | D97: =E97-$E$20 -> 360000 | E97: =F97-$E$20 -> 380000 | F97: =G97-$E$20 -> 400000 | G97: =H97-$E$20 -> 420000 | H97: =H82 -> 440000 | I97: =H97+$E$20 -> 460000 | J97: =I97+$E$20 -> 480000 | K97: =J97+$E$20 -> 500000 | L97: =K97+$E$20 -> 520000
B98: Giá bán căn hộ (chưa VAT, tim tường) (tr.đ/m2) | C98: =C83 -> 55.5 | D98: 0.35585318 | E98: 0.34634513 | F98: 0.33694945 | G98: 0.32766415 | H98: 0.3184873 | I98: 0.30941701 | J98: 0.30045144 | K98: 0.29158878 | L98: 0.28282727
C99: =C84 -> 53.5 | D99: 0.31362128 | E99: 0.30437099 | F99: 0.29522995 | G99: 0.28619621 | H99: 0.27726792 | I99: 0.26844323 | J99: 0.25972034 | K99: 0.25109751 | L99: 0.24257303
C100: =C85 -> 51.5 | D100: 0.27145118 | E100: 0.26245791 | F100: 0.25357077 | G100: 0.24478789 | H100: 0.23610745 | I100: 0.22752766 | J100: 0.21904678 | K100: 0.21066312 | L100: 0.202375
C101: =C86 -> 49.5 | D101: 0.22934274 | E101: 0.22060575 | F101: 0.2119718 | G101: 0.20343906 | H101: 0.19500576 | I101: 0.18667019 | J101: 0.17843064 | K101: 0.17028548 | L101: 0.16223308
C102: =C87 -> 47.5 | D102: 0.18727812 | E102: 0.17879691 | F102: 0.17041564 | G102: 0.16213255 | H102: 0.15394592 | I102: 0.14585409 | J102: 0.13785542 | K102: 0.1299483 | L102: 0.12213117
C103: =C88 -> 45.5 | D103: 0.14525698 | E103: 0.13703104 | F103: 0.12890196 | G103: 0.12086804 | H103: 0.11292762 | I103: 0.10507906 | J103: 0.097320798 | K103: 0.089651272 | L103: 0.08206897
C104: =C89 -> 43.5 | D104: 0.10329976 | E104: 0.095328334 | F104: 0.087450699 | G104: 0.079665209 | H104: 0.071970255 | I104: 0.064364269 | J104: 0.056845717 | K104: 0.049413098 | L104: 0.042064948
C105: =C90 -> 41.5 | D105: 0.06140632 | E105: 0.053688644 | F105: 0.046061704 | G105: 0.03852391 | H105: 0.031073707 | I105: 0.023709579 | J105: 0.016430041 | K105: 0.0092336449 | L105: 0.002118974
C106: =C91 -> 39.5 | D106: 0.019576515 | E106: 0.012111828 | F106: 0.0047348382 | G106: -0.0025559922 | H106: -0.0097621635 | I106: -0.016885142 | J106: -0.023926359 | K106: -0.030887216 | L106: -0.037769079

Sheet QĐGB
C2: Tỉ giá USD/ VNĐ | D2: 26000 | E2: Tỉ lệ tăng giá | F2: Tỉ lệ tăng giá | G2: Tỉ lệ tăng giá | H2: Nhà trẻ | I2: TTTM | J2: Nhà trẻ CT1 | K2: Nhà Trẻ A | L2: Nhà Trẻ B | M2: Tỷ lệ khai thác Shop
C3: r | D3: 0.11 | E3: 10% / 3nam | F3: 3% /nam | G3: 3% /nam | H3: 4 | I3: 10 | J3: 3.5
B4: 2026 | D4: =1/(1+$D$3)^C4 -> 1 | K4: nam xay dung | L4: nam xay dung | M4: nam xay dung
B5: 2027 | D5: =1/(1+$D$3)^C5 -> 1 | K5: nam xay dung | L5: nam xay dung | M5: nam xay dung
B6: 2028 | D6: =1/(1+$D$3)^C6 -> 1 | K6: nam xay dung | L6: nam xay dung | M6: nam xay dung
B7: 2029 | C7: 0 | D7: =1/(1+$D$3)^C7 -> 1 | E7: 1 | F7: 1 | G7: 1 | H7: =$H$3*$D7*12*$D$2*E7*K7 -> 1248000 | I7: =$I$3*$D7*12*$D$2*E7*L7 -> 3120000 | J7: =$J$3*$D7*12*$D$2*G7*M7 -> 1092000 | K7: 1 | L7: 1 | M7: 1
B8: 2030 | C8: =C7+1 -> 1 | D8: =1/(1+$D$3)^C8 -> 0.9009009 | E8: 1 | F8: 1 | G8: 1 | H8: =$H$3*$D8*12*$D$2*E8*K8 -> 1124324.3 | I8: =$I$3*$D8*12*$D$2*E8*L8 -> 2810810.8 | J8: =$J$3*$D8*12*$D$2*G8*M8 -> 983783.78 | K8: 1 | L8: 1 | M8: 1
B9: 2031 | C9: =C8+1 -> 2 | D9: =1/(1+$D$3)^C9 -> 0.81162243 | E9: 1 | F9: 1 | G9: 1 | H9: =$H$3*$D9*12*$D$2*E9*K9 -> 1012904.8 | I9: =$I$3*$D9*12*$D$2*E9*L9 -> 2532262 | J9: =$J$3*$D9*12*$D$2*G9*M9 -> 886291.7 | K9: 1 | L9: 1 | M9: 1
B10: 2032 | C10: =C9+1 -> 3 | D10: =1/(1+$D$3)^C10 -> 0.73119138 | E10: =E7*1.1 -> 1.1 | F10: =F7*1.1 -> 1.1 | G10: =G7*1.1 -> 1.1 | H10: =$H$3*$D10*12*$D$2*E10*K10 -> 1003779.5 | I10: =$I$3*$D10*12*$D$2*E10*L10 -> 2509448.8 | J10: =$J$3*$D10*12*$D$2*G10*M10 -> 878307.09 | K10: 1 | L10: 1 | M10: 1
B11: 2033 | C11: =C10+1 -> 4 | D11: =1/(1+$D$3)^C11 -> 0.65873097 | E11: =E8*1.1 -> 1.1 | F11: =F8*1.1 -> 1.1 | G11: =G8*1.1 -> 1.1 | H11: =$H$3*$D11*12*$D$2*E11*K11 -> 904305.88 | I11: =$I$3*$D11*12*$D$2*E11*L11 -> 2260764.7 | J11: =$J$3*$D11*12*$D$2*G11*M11 -> 791267.65 | K11: 1 | L11: 1 | M11: 1
B12: 2034 | C12: =C11+1 -> 5 | D12: =1/(1+$D$3)^C12 -> 0.59345133 | E12: =E9*1.1 -> 1.1 | F12: =F9*1.1 -> 1.1 | G12: =G9*1.1 -> 1.1 | H12: =$H$3*$D12*12*$D$2*E12*K12 -> 814689.98 | I12: =$I$3*$D12*12*$D$2*E12*L12 -> 2036725 | J12: =$J$3*$D12*12*$D$2*G12*M12 -> 712853.74 | K12: 1 | L12: 1 | M12: 1
B13: 2035 | C13: =C12+1 -> 6 | D13: =1/(1+$D$3)^C13 -> 0.53464084 | E13: =E10*1.1 -> 1.21 | F13: =F10*1.1 -> 1.21 | G13: =G10*1.1 -> 1.21 | H13: =$H$3*$D13*12*$D$2*E13*K13 -> 807350.43 | I13: =$I$3*$D13*12*$D$2*E13*L13 -> 2018376.1 | J13: =$J$3*$D13*12*$D$2*G13*M13 -> 706431.63 | K13: 1 | L13: 1 | M13: 1
B14: 2036 | C14: =C13+1 -> 7 | D14: =1/(1+$D$3)^C14 -> 0.48165841 | E14: =E11*1.1 -> 1.21 | F14: =F11*1.1 -> 1.21 | G14: =G11*1.1 -> 1.21 | H14: =$H$3*$D14*12*$D$2*E14*K14 -> 727342.73 | I14: =$I$3*$D14*12*$D$2*E14*L14 -> 1818356.8 | J14: =$J$3*$D14*12*$D$2*G14*M14 -> 636424.89 | K14: 1 | L14: 1 | M14: 1
B15: 2037 | C15: =C14+1 -> 8 | D15: =1/(1+$D$3)^C15 -> 0.4339265 | E15: =E12*1.1 -> 1.21 | F15: =F12*1.1 -> 1.21 | G15: =G12*1.1 -> 1.21 | H15: =$H$3*$D15*12*$D$2*E15*K15 -> 655263.72 | I15: =$I$3*$D15*12*$D$2*E15*L15 -> 1638159.3 | J15: =$J$3*$D15*12*$D$2*G15*M15 -> 573355.76 | K15: 1 | L15: 1 | M15: 1
B16: 2038 | C16: =C15+1 -> 9 | D16: =1/(1+$D$3)^C16 -> 0.39092477 | E16: =E13*1.1 -> 1.331 | F16: =F13*1.1 -> 1.331 | G16: =G13*1.1 -> 1.331 | H16: =$H$3*$D16*12*$D$2*E16*K16 -> 649360.45 | I16: =$I$3*$D16*12*$D$2*E16*L16 -> 1623401.1 | J16: =$J$3*$D16*12*$D$2*G16*M16 -> 568190.39 | K16: 1 | L16: 1 | M16: 1
B17: 2039 | C17: =C16+1 -> 10 | D17: =1/(1+$D$3)^C17 -> 0.35218448 | E17: =E14*1.1 -> 1.331 | F17: =F14*1.1 -> 1.331 | G17: =G14*1.1 -> 1.331 | H17: =$H$3*$D17*12*$D$2*E17*K17 -> 585009.41 | I17: =$I$3*$D17*12*$D$2*E17*L17 -> 1462523.5 | J17: =$J$3*$D17*12*$D$2*G17*M17 -> 511883.24 | K17: 1 | L17: 1 | M17: 1
B18: 2040 | C18: =C17+1 -> 11 | D18: =1/(1+$D$3)^C18 -> 0.31728331 | E18: =E15*1.1 -> 1.331 | F18: =F15*1.1 -> 1.331 | G18: =G15*1.1 -> 1.331 | H18: =$H$3*$D18*12*$D$2*E18*K18 -> 527035.51 | I18: =$I$3*$D18*12*$D$2*E18*L18 -> 1317588.8 | J18: =$J$3*$D18*12*$D$2*G18*M18 -> 461156.07 | K18: 1 | L18: 1 | M18: 1
B19: 2041 | C19: =C18+1 -> 12 | D19: =1/(1+$D$3)^C19 -> 0.28584082 | E19: =E16*1.1 -> 1.4641 | F19: =F16*1.1 -> 1.4641 | G19: =G16*1.1 -> 1.4641 | H19: =$H$3*$D19*12*$D$2*E19*K19 -> 522287.44 | I19: =$I$3*$D19*12*$D$2*E19*L19 -> 1305718.6 | J19: =$J$3*$D19*12*$D$2*G19*M19 -> 457001.51 | K19: 1 | L19: 1 | M19: 1
B20: 2042 | C20: =C19+1 -> 13 | D20: =1/(1+$D$3)^C20 -> 0.25751426 | E20: =E17*1.1 -> 1.4641 | F20: =F17*1.1 -> 1.4641 | G20: =G17*1.1 -> 1.4641 | H20: =$H$3*$D20*12*$D$2*E20*K20 -> 470529.22 | I20: =$I$3*$D20*12*$D$2*E20*L20 -> 1176323.1 | J20: =$J$3*$D20*12*$D$2*G20*M20 -> 411713.07 | K20: 1 | L20: 1 | M20: 1
B21: 2043 | C21: =C20+1 -> 14 | D21: =1/(1+$D$3)^C21 -> 0.23199482 | E21: =E18*1.1 -> 1.4641 | F21: =F18*1.1 -> 1.4641 | G21: =G18*1.1 -> 1.4641 | H21: =$H$3*$D21*12*$D$2*E21*K21 -> 423900.2 | I21: =$I$3*$D21*12*$D$2*E21*L21 -> 1059750.5 | J21: =$J$3*$D21*12*$D$2*G21*M21 -> 370912.68 | K21: 1 | L21: 1 | M21: 1
... B57: 2076 | C57: =C56+1 -> 50 | D57: =1/(1+$D$3)^C57 -> 0.0054181505 | E57: =E54*1.1 -> 4.594973 | F57: =F54*1.1 -> 4.594973 | G57: =G54*1.1 -> 4.594973 | H57: =$H$3*$D57*12*$D$2*E57*K57 -> 31070.526 | I57: =$I$3*$D57*12*$D$2*E57*L57 -> 77676.316 | J57: =$J$3*$D57*12*$D$2*G57*M57 -> 27186.71 | K57: 1 | L57: 1 | M57: 1
F62: Tổng | H62: =SUM(H4:H61) -> 16872184 | I62: =SUM(I4:I61) -> 42180459 | J62: =SUM(J4:J61) -> 14763161
H63: =+H62/10^6 -> 16.872184 | I63: =+I62/10^6 -> 42.180459 | J63: =+J62/10^6 -> 14.763161
